Workbook
Name ElencoCalciatori: _Liste!$A$1:$A$479

Sheet Rosa 25
A1: PLANNER ROSA MANTRA 4-3-3 — PIANO BOMBER + GIOIELLI
A2: Target = piano di spesa; Offerta max = walk-away cap. Se paghi oltre target ma sotto cap, recupera la differenza su slot low cost/coppie.
A4: Budget totale | B4: 500 | D4: STATUS DATI: 28/08/2026 — PRE-CHIUSURA MERCATO Check finale obbligatorio il 02/09 per trasferimenti e ruoli Mantra.
A5: Spesa movimento | B5: =SUM(I11:I35)
A6: Spesa portieri | B6: =SUM(I40:I42)
A7: Spesa totale | B7: =B5+B6 | D7: GUARDRAIL: A + Pc = 272 crediti target (54,4% del budget). Il modello accetta top cari e finanzia il surplus con provincia, coppie e low cost.
A8: Residuo | B8: =B4-B7
A9: Posti rimasti | B9: =28-COUNTA(D11:D35)-COUNTA(D40:D42)
A10: # | B10: Profilo slot | C10: Target | D10: Nome | E10: Squadra | F10: R. Mantra | G10: Tit.% | H10: Offerta max | I10: Costo pagato | J10: Scost. max | K10: Strategia | L10: Note live
A11: 1 | B11: Dd 1 — TOP | C11: 18 | E11: =IFERROR(VLOOKUP($D11,'Lista calciatori'!$B$2:$AW$549,3,FALSE),"") | F11: =IFERROR(VLOOKUP($D11,'Lista calciatori'!$B$2:$AW$549,6,FALSE),"") | G11: =IFERROR(VLOOKUP($D11,'Lista calciatori'!$B$2:$AW$549,14,FALSE),"") | H11: =IFERROR(VLOOKUP($D11,'Lista calciatori'!$B$2:$AW$549,30,FALSE),"") | J11: =IF(OR(H11="",I11=""),"",H11-I11) | K11: =IFERROR(VLOOKUP($D11,'Lista calciatori'!$B$2:$AW$549,42,FALSE),"")
A12: 2 | B12: Dd 2 — TITOLARE | C12: 4 | E12: =IFERROR(VLOOKUP($D12,'Lista calciatori'!$B$2:$AW$549,3,FALSE),"") | F12: =IFERROR(VLOOKUP($D12,'Lista calciatori'!$B$2:$AW$549,6,FALSE),"") | G12: =IFERROR(VLOOKUP($D12,'Lista calciatori'!$B$2:$AW$549,14,FALSE),"") | H12: =IFERROR(VLOOKUP($D12,'Lista calciatori'!$B$2:$AW$549,30,FALSE),"") | J12: =IF(OR(H12="",I12=""),"",H12-I12) | K12: =IFERROR(VLOOKUP($D12,'Lista calciatori'!$B$2:$AW$549,42,FALSE),"")
A13: 3 | B13: Dd 3 — SCOMMESSA | C13: 2 | E13: =IFERROR(VLOOKUP($D13,'Lista calciatori'!$B$2:$AW$549,3,FALSE),"") | F13: =IFERROR(VLOOKUP($D13,'Lista calciatori'!$B$2:$AW$549,6,FALSE),"") | G13: =IFERROR(VLOOKUP($D13,'Lista calciatori'!$B$2:$AW$549,14,FALSE),"") | H13: =IFERROR(VLOOKUP($D13,'Lista calciatori'!$B$2:$AW$549,30,FALSE),"") | J13: =IF(OR(H13="",I13=""),"",H13-I13) | K13: =IFERROR(VLOOKUP($D13,'Lista calciatori'!$B$2:$AW$549,42,FALSE),"")
A14: 4 | B14: Ds 1 — TOP | C14: 18 | E14: =IFERROR(VLOOKUP($D14,'Lista calciatori'!$B$2:$AW$549,3,FALSE),"") | F14: =IFERROR(VLOOKUP($D14,'Lista calciatori'!$B$2:$AW$549,6,FALSE),"") | G14: =IFERROR(VLOOKUP($D14,'Lista calciatori'!$B$2:$AW$549,14,FALSE),"") | H14: =IFERROR(VLOOKUP($D14,'Lista calciatori'!$B$2:$AW$549,30,FALSE),"") | J14: =IF(OR(H14="",I14=""),"",H14-I14) | K14: =IFERROR(VLOOKUP($D14,'Lista calciatori'!$B$2:$AW$549,42,FALSE),"")
A15: 5 | B15: Ds 2 — TITOLARE | C15: 4 | E15: =IFERROR(VLOOKUP($D15,'Lista calciatori'!$B$2:$AW$549,3,FALSE),"") | F15: =IFERROR(VLOOKUP($D15,'Lista calciatori'!$B$2:$AW$549,6,FALSE),"") | G15: =IFERROR(VLOOKUP($D15,'Lista calciatori'!$B$2:$AW$549,14,FALSE),"") | H15: =IFERROR(VLOOKUP($D15,'Lista calciatori'!$B$2:$AW$549,30,FALSE),"") | J15: =IF(OR(H15="",I15=""),"",H15-I15) | K15: =IFERROR(VLOOKUP($D15,'Lista calciatori'!$B$2:$AW$549,42,FALSE),"")
A16: 6 | B16: Ds 3 — SCOMMESSA | C16: 2 | E16: =IFERROR(VLOOKUP($D16,'Lista calciatori'!$B$2:$AW$549,3,FALSE),"") | F16: =IFERROR(VLOOKUP($D16,'Lista calciatori'!$B$2:$AW$549,6,FALSE),"") | G16: =IFERROR(VLOOKUP($D16,'Lista calciatori'!$B$2:$AW$549,14,FALSE),"") | H16: =IFERROR(VLOOKUP($D16,'Lista calciatori'!$B$2:$AW$549,30,FALSE),"") | J16: =IF(OR(H16="",I16=""),"",H16-I16) | K16: =IFERROR(VLOOKUP($D16,'Lista calciatori'!$B$2:$AW$549,42,FALSE),"")
A17: 7 | B17: Dc 1 — TOP | C17: 20 | E17: =IFERROR(VLOOKUP($D17,'Lista calciatori'!$B$2:$AW$549,3,FALSE),"") | F17: =IFERROR(VLOOKUP($D17,'Lista calciatori'!$B$2:$AW$549,6,FALSE),"") | G17: =IFERROR(VLOOKUP($D17,'Lista calciatori'!$B$2:$AW$549,14,FALSE),"") | H17: =IFERROR(VLOOKUP($D17,'Lista calciatori'!$B$2:$AW$549,30,FALSE),"") | J17: =IF(OR(H17="",I17=""),"",H17-I17) | K17: =IFERROR(VLOOKUP($D17,'Lista calciatori'!$B$2:$AW$549,42,FALSE),"")
A18: 8 | B18: Dc 2 — SEMITOP | C18: 4 | E18: =IFERROR(VLOOKUP($D18,'Lista calciatori'!$B$2:$AW$549,3,FALSE),"") | F18: =IFERROR(VLOOKUP($D18,'Lista calciatori'!$B$2:$AW$549,6,FALSE),"") | G18: =IFERROR(VLOOKUP($D18,'Lista calciatori'!$B$2:$AW$549,14,FALSE),"") | H18: =IFERROR(VLOOKUP($D18,'Lista calciatori'!$B$2:$AW$549,30,FALSE),"") | J18: =IF(OR(H18="",I18=""),"",H18-I18) | K18: =IFERROR(VLOOKUP($D18,'Lista calciatori'!$B$2:$AW$549,42,FALSE),"")
A19: 9 | B19: Dc 3 — TITOLARE | C19: 2 | E19: =IFERROR(VLOOKUP($D19,'Lista calciatori'!$B$2:$AW$549,3,FALSE),"") | F19: =IFERROR(VLOOKUP($D19,'Lista calciatori'!$B$2:$AW$549,6,FALSE),"") | G19: =IFERROR(VLOOKUP($D19,'Lista calciatori'!$B$2:$AW$549,14,FALSE),"") | H19: =IFERROR(VLOOKUP($D19,'Lista calciatori'!$B$2:$AW$549,30,FALSE),"") | J19: =IF(OR(H19="",I19=""),"",H19-I19) | K19: =IFERROR(VLOOKUP($D19,'Lista calciatori'!$B$2:$AW$549,42,FALSE),"")
A20: 10 | B20: Dc 4 — TITOLARE | C20: 2 | E20: =IFERROR(VLOOKUP($D20,'Lista calciatori'!$B$2:$AW$549,3,FALSE),"") | F20: =IFERROR(VLOOKUP($D20,'Lista calciatori'!$B$2:$AW$549,6,FALSE),"") | G20: =IFERROR(VLOOKUP($D20,'Lista calciatori'!$B$2:$AW$549,14,FALSE),"") | H20: =IFERROR(VLOOKUP($D20,'Lista calciatori'!$B$2:$AW$549,30,FALSE),"") | J20: =IF(OR(H20="",I20=""),"",H20-I20) | K20: =IFERROR(VLOOKUP($D20,'Lista calciatori'!$B$2:$AW$549,42,FALSE),"")
A21: 11 | B21: Dc 5 — LOW | C21: 2 | E21: =IFERROR(VLOOKUP($D21,'Lista calciatori'!$B$2:$AW$549,3,FALSE),"") | F21: =IFERROR(VLOOKUP($D21,'Lista calciatori'!$B$2:$AW$549,6,FALSE),"") | G21: =IFERROR(VLOOKUP($D21,'Lista calciatori'!$B$2:$AW$549,14,FALSE),"") | H21: =IFERROR(VLOOKUP($D21,'Lista calciatori'!$B$2:$AW$549,30,FALSE),"") | J21: =IF(OR(H21="",I21=""),"",H21-I21) | K21: =IFERROR(VLOOKUP($D21,'Lista calciatori'!$B$2:$AW$549,42,FALSE),"")
A22: 12 | B22: Jolly 1 — TITOLARE | C22: 4 | E22: =IFERROR(VLOOKUP($D22,'Lista calciatori'!$B$2:$AW$549,3,FALSE),"") | F22: =IFERROR(VLOOKUP($D22,'Lista calciatori'!$B$2:$AW$549,6,FALSE),"") | G22: =IFERROR(VLOOKUP($D22,'Lista calciatori'!$B$2:$AW$549,14,FALSE),"") | H22: =IFERROR(VLOOKUP($D22,'Lista calciatori'!$B$2:$AW$549,30,FALSE),"") | J22: =IF(OR(H22="",I22=""),"",H22-I22) | K22: =IFERROR(VLOOKUP($D22,'Lista calciatori'!$B$2:$AW$549,42,FALSE),"")
... A35: 25 | B35: Pc 2 — SEMITOP | C35: 27 | E35: =IFERROR(VLOOKUP($D35,'Lista calciatori'!$B$2:$AW$549,3,FALSE),"") | F35: =IFERROR(VLOOKUP($D35,'Lista calciatori'!$B$2:$AW$549,6,FALSE),"") | G35: =IFERROR(VLOOKUP($D35,'Lista calciatori'!$B$2:$AW$549,14,FALSE),"") | H35: =IFERROR(VLOOKUP($D35,'Lista calciatori'!$B$2:$AW$549,30,FALSE),"") | J35: =IF(OR(H35="",I35=""),"",H35-I35) | K35: =IFERROR(VLOOKUP($D35,'Lista calciatori'!$B$2:$AW$549,42,FALSE),"")
A38: PORTIERI — PUOI USARE PACCHETTO DI SQUADRA O 3 SINGOLI
A39: # | B39: Profilo | C39: Target | D39: Nome | E39: Squadra | F39: R. Mantra | G39: Tit.% | H39: Offerta max | I39: Costo pagato | J39: Scost. max | K39: Strategia | L39: Note live
A40: 1 | B40: Por | C40: 50 | E40: =IFERROR(VLOOKUP($D40,'Lista calciatori'!$B$2:$AW$549,3,FALSE),"") | F40: =IFERROR(VLOOKUP($D40,'Lista calciatori'!$B$2:$AW$549,6,FALSE),"") | G40: =IFERROR(VLOOKUP($D40,'Lista calciatori'!$B$2:$AW$549,14,FALSE),"") | H40: =IFERROR(VLOOKUP($D40,'Lista calciatori'!$B$2:$AW$549,30,FALSE),"") | J40: =IF(OR(H40="",I40=""),"",H40-I40) | K40: =IFERROR(VLOOKUP($D40,'Lista calciatori'!$B$2:$AW$549,42,FALSE),"")
A41: 2 | B41: Por | C41: 1 | E41: =IFERROR(VLOOKUP($D41,'Lista calciatori'!$B$2:$AW$549,3,FALSE),"") | F41: =IFERROR(VLOOKUP($D41,'Lista calciatori'!$B$2:$AW$549,6,FALSE),"") | G41: =IFERROR(VLOOKUP($D41,'Lista calciatori'!$B$2:$AW$549,14,FALSE),"") | H41: =IFERROR(VLOOKUP($D41,'Lista calciatori'!$B$2:$AW$549,30,FALSE),"") | J41: =IF(OR(H41="",I41=""),"",H41-I41) | K41: =IFERROR(VLOOKUP($D41,'Lista calciatori'!$B$2:$AW$549,42,FALSE),"")
A42: 3 | B42: Por | C42: 1 | E42: =IFERROR(VLOOKUP($D42,'Lista calciatori'!$B$2:$AW$549,3,FALSE),"") | F42: =IFERROR(VLOOKUP($D42,'Lista calciatori'!$B$2:$AW$549,6,FALSE),"") | G42: =IFERROR(VLOOKUP($D42,'Lista calciatori'!$B$2:$AW$549,14,FALSE),"") | H42: =IFERROR(VLOOKUP($D42,'Lista calciatori'!$B$2:$AW$549,30,FALSE),"") | J42: =IF(OR(H42="",I42=""),"",H42-I42) | K42: =IFERROR(VLOOKUP($D42,'Lista calciatori'!$B$2:$AW$549,42,FALSE),"")

Sheet Strategia 433
A1: STRATEGIA ASTA MANTRA 4-3-3 — 12 SQUADRE, 500 CREDITI — BOMBER + GIOIELLI
A2: Rimodulazione su prezzi reali della lega: cap più alti sui top, ma target di rosa aggressivo su Pc/A e recupero crediti con low cost, scommesse e coppie.
A4: PARAMETRI ASTA
A5: Budget totale | B5: 500 | C5: crediti
A6: Partecipanti | B6: 12 | C6: squadre
A7: Movimento | B7: 25 | C7: giocatori
A8: Portieri | B8: 3 | C8: giocatori
A9: Slot complessivi | B9: =B7+B8
A10: Somma QUOT top 336 | B10: 3152 | C10: Top 336 = 12 rose x 28 giocatori; calcolato dal listone nel file.
A11: Fattore inflazione 12x500 | B11: =B5*B6/B10 | C11: Benchmark aritmetico generico. I prezzi operativi ora sono tarati sullo storico della tua lega per ruolo.
A13: WALK-AWAY CAP PER FAMIGLIA E FASCIA — NON SONO I BUDGET TARGET
A14: Famiglia | B14: Budget reparto | C14: N. slot | D14: Top | E14: Semitop | F14: Starter | G14: Scommessa | H14: Low
A15: Por | B15: 52 | C15: 3 | D15: 60 | E15: 45 | F15: 30 | G15: 15 | H15: 6
A16: Dd | B16: 24 | C16: 3 | D16: 40 | E16: 28 | F16: 15 | G16: 8 | H16: 4
A17: Ds | B17: 24 | C17: 3 | D17: 40 | E17: 28 | F17: 15 | G17: 8 | H17: 4
A18: Dc | B18: 30 | C18: 5 | D18: 23 | E18: 15 | F18: 8 | G18: 5 | H18: 3
A19: Jolly | B19: 8 | C19: 2 | D19: 45 | E19: 30 | F19: 18 | G19: 10 | H19: 5
A20: A | B20: 100 | C20: 4 | D20: 85 | E20: 60 | F20: 40 | G20: 22 | H20: 10
A21: C | B21: 48 | C21: 3 | D21: 50 | E21: 35 | F21: 24 | G21: 14 | H21: 8
A22: M | B22: 42 | C22: 3 | D22: 38 | E22: 28 | F22: 20 | G22: 12 | H22: 7
A23: Pc | B23: 172 | C23: 2 | D23: 160 | E23: 110 | F23: 75 | G23: 40 | H23: 20
A24: Non433 | B24: 0 | C24: 0 | D24: 8 | E24: 6 | F24: 4 | G24: 3 | H24: 2
A25: TOTALE TARGET | B25: =SUM(B15:B23) | C25: =SUM(C15:C23)
A27: MOLTIPLICATORE EMPIRICO PREZZO / QUOT — STORICO LEGA 12x500 | E27: BUDGET SLOT — PIANO BOMBER + GIOIELLI (448 MOVIMENTO + 52 POR)
A28: Famiglia | B28: Moltiplicatore | C28: Logica | E28: Slot | F28: Profilo | G28: Target | H28: Regola
A29: Por | B29: 3 | C29: prime porte molto contese; pacchetto top 50-60 | E29: Dd 1 | F29: TOP | G29: 18 | H29: se va a 30-40, finanzialo tagliando altrove
A30: Dd | B30: 2.3 | C30: specialisti e ali di fascia possono salire molto | E30: Dd 2 | F30: TITOLARE | G30: 4 | H30: 90%+; cerca provincia
A31: Ds | B31: 2.3 | C31: specialisti e ali di fascia possono salire molto | E31: Dd 3 | F31: SCOMMESSA | G31: 2 | H31: gioiellino / copertura
A32: Dc | B32: 1.45 | C32: top circa 20-23, reparto profondo | E32: Ds 1 | F32: TOP | G32: 18 | H32: se va a 30-40, finanzialo tagliando altrove
A33: Jolly | B33: 1.55 | C33: premio alla versatilita ma senza all-in | E33: Ds 2 | F33: TITOLARE | G33: 4 | H33: 90%+; cerca provincia
A34: A | B34: 2.7 | C34: top spesso oltre 60 | E34: Ds 3 | F34: SCOMMESSA | G34: 2 | H34: gioiellino / copertura
A35: C | B35: 1.7 | C35: premio ai C offensivi/bonus | E35: Dc 1 | F35: TOP | G35: 20 | H35: cap reale 23
A36: M | B36: 1.3 | C36: titolari affidabili, inflazione più contenuta | E36: Dc 2 | F36: SEMITOP | G36: 4 | H36: reparto profondo: aspetta
A37: Pc | B37: 4.7 | C37: bomber fortemente inflazionati 130-150+ | E37: Dc 3 | F37: TITOLARE | G37: 2 | H37: minuti prima del nome
A38: Non433 | B38: 0.9 | C38: non prioritario nel 4-3-3 | E38: Dc 4 | F38: TITOLARE | G38: 2 | H38: minuti prima del nome
E39: Dc 5 | F39: LOW | G39: 2 | H39: scommessa / coppia
E40: Jolly 1 | F40: TITOLARE | G40: 4 | H40: versatile e titolare
E41: Jolly 2 | F41: TITOLARE | G41: 4 | H41: versatile e titolare
E42: A 1 | F42: TOP | G42: 65 | H42: strutturale per il 4-3-3; cap 85
E43: A 2 | F43: SEMITOP | G43: 22 | H43: qui cerca il vero affare
E44: A 3 | F44: TITOLARE | G44: 9 | H44: bonus/minuti
E45: A 4 | F45: SCOMMESSA | G45: 4 | H45: gioiellino
E46: C 1 | F46: TOP/SEMITOP | G46: 28 | H46: offensivo / piazzati
E47: C 2 | F47: SEMITOP | G47: 12 | H47: cerca bonus
E48: C 3 | F48: TITOLARE | G48: 8 | H48: 90%+
E49: M 1 | F49: SEMITOP+ | G49: 16 | H49: minuti e voto
E50: M 2 | F50: SEMITOP | G50: 14 | H50: titolare
... E53: Pc 2 | F53: VALUE | G53: 27 | H53: non fare due all-in
E54: TOTALE MOVIMENTO | G54: =SUM(G29:G53) | H54: + 52 portieri = 500
A57: REGOLE D ASTA — VERSIONE RIMODULATA
A58: 1. Il cap e un walk-away price, non il budget da spendere: sui top puoi arrivarci solo se il resto della rosa lo finanzia.
A59: 2. Pc: pianifica 145 sul bomber e accetta un range 130-160; Malen/Lautaro possono richiedere anche qualcosa in più.
A60: 3. A: almeno un top vero. Target 65, cap 85. Il secondo slot va cercato a valore, non per forza un altro nome di prima fascia.
A61: 4. Dd/Ds: un esterno può arrivare a 30-40, ma non serve pagare due super-premium: un top + un titolare + una scommessa per lato.
A62: 5. Dc: qui recupera crediti. Top 20-23, poi profondita, titolarita e coppie; evitare la guerra sui nomi intermedi.
A63: 6. Coppie: se prendi un titolare di fascia/ballottaggio, la sua copertura low cost può valere più di un quarto nome isolato.
A64: 7. Gioielli: riserva 6-10 slot da 1-8 crediti per provincia/promesse. Sono il carburante che finanzia Pc e A.
A65: 8. A ogni over-spend su uno slot corrisponde un taglio esplicito su uno o più slot successivi: mai pagare il surplus “a memoria”.
A66: PACCHETTI PORTIERI — SQUADRE AMMESSE
A67: Rank valore | B67: Squadra | C67: Titolare | D67: Riserve | E67: Tetto pacchetto | F67: Qualita | G67: Mossa | H67: Nota
A68: Rank valore | B68: Squadra | C68: Titolare | D68: Riserve / copertura | E68: Tetto pacchetto | F68: Qualita | G68: Mossa | H68: Nota
A69: 1 | B69: Roma | C69: Svilar | D69: Gollini + De Marzi | E69: 60 | F69: SUPER TOP | G69: ATTACCA FINO A 55-60 | H69: coerente con storico lega; pacchetto chiuso
A70: 2 | B70: Inter | C70: Martinez Jo. | D70: Provedel + Di Gennaro | E70: 58 | F70: TOP | G70: ATTACCA | H70: Provedel può costare più del classico secondo
A71: 3 | B71: Milan | C71: Maignan | D71: Terracciano + Torriani | E71: 55 | F71: TOP | G71: ATTACCA | H71: porta affidabile; pacchetto semplice
A72: 4 | B72: Juventus | C72: Vicario | D72: Perin + Di Gregorio* | E72: 60 | F72: TOP | G72: ASPETTA MERCATO | H72: Vicario titolare; se Di Gregorio resta, costo/gerarchie da ricontrollare
A73: 5 | B73: Atalanta | C73: Carnesecchi | D73: Sportiello + Vismara | E73: 53 | F73: TOP | G73: COMPRA A VALORE | H73: titolare molto solido
A74: 6 | B74: Como | C74: Butez | D74: Tornqvist + Vigorito | E74: 53 | F74: TOP | G74: COMPRA A VALORE | H74: può costare meno per minore brand
A75: 7 | B75: Napoli | C75: Meret | D75: Milinkovic-Savic V. + Contini | E75: 50 | F75: SEMITOP | G75: SOLO PACCHETTO | H75: gerarchia più delicata: evita di prendere un solo nome
A78: COME FINANZIARE GLI OVER-SPEND
A79: Evento | B79: Extra vs target | C79: Recupero suggerito | D79: Principio
A80: Pc bomber a 160 | B80: 15 | C80: -5 A2; -4 C3; -3 Jolly; -3 Dc/terzini low | D80: il bomber si finanzia sui ruoli profondi
A81: A top a 80 | B81: 15 | C81: -7 Pc2; -3 C3; -3 Dc; -2 Jolly | D81: pagare l A top implica secondo Pc value
A82: Dd o Ds top a 35 | B82: 17 | C82: -8 sull altro lato; -4 Dc; -3 Jolly; -2 scommesse | D82: non comprare due ali premium insieme
A83: Portieri a 60 | B83: 8 | C83: -3 Dc; -2 Jolly; -3 A4/C3 | D83: porta top sì, ma senza erodere il bomber
A84: Affare Pc bomber a 130 | B84: -15 | C84: +8 A2; +4 C/M; +3 Dd/Ds | D84: reinvesti dove aumenta bonus/titolarita

Sheet Graduatorie 433
A1: GRADUATORIE 4-3-3 — 30 NOMI PER RUOLO + GIOIELLI E COPERTURE
A2: Graduatoria ampia: core + titolari value + promesse di seconda/terza fascia. “Prezzo obiettivo” è il prezzo desiderato; “Offerta max” è il walk-away cap.
A3: Fotografia 28/08/2026: mercato ancora aperto. Le coppie sono coperture tattiche/di ruolo da ricontrollare al 02/09, non garanzia di gerarchia.
A5: Ruolo | B5: Rank | C5: Nome | D5: Squadra | E5: R. Mantra | F5: Profilo asta | G5: Tier SOS | H5: Tit.% | I5: Indice Fanta | J5: QUOT | K5: FVM 500 | L5: Prezzo obiettivo | M5: Offerta max | N5: Delta | O5: Coppia/copertura | P5: Strategia | Q5: Rischio | R5: Perché | S5: Fonte
A6: Dd | B6: 1 | C6: Di Lorenzo | D6: Napoli | E6: Dd/E | F6: TOP | G6: TOP | H6: 98 | I6: =IFERROR(VLOOKUP(C6,'Lista calciatori'!$B$2:$AX$549,16,FALSE),"") | J6: 12 | K6: 20 | L6: =IFERROR(VLOOKUP(C6,'Lista calciatori'!$B$2:$AX$549,49,FALSE),"") | M6: =IFERROR(VLOOKUP(C6,'Lista calciatori'!$B$2:$AX$549,30,FALSE),"") | N6: =M6-L6 | O6: Favasuli | P6: =IFERROR(VLOOKUP(C6,'Lista calciatori'!$B$2:$AX$549,42,FALSE),"") | Q6: BASSO | R6: esterno utile al 4-3-3; pagalo premium solo se non compri due top di fascia | S6: https://www.sosfanta.com/guida-asta-fantacalcio/fantacalcio-mantra-ecco-la-guida-allasta-2026-27-la-divisione-ruolo-per-ruolo/
A7: Dd | B7: 2 | C7: Jimenez A. | D7: Fiorentina | E7: Dd/Ds/E | F7: TOP | G7: TOP | H7: 75 | I7: =IFERROR(VLOOKUP(C7,'Lista calciatori'!$B$2:$AX$549,16,FALSE),"") | J7: 9 | K7: 13 | L7: =IFERROR(VLOOKUP(C7,'Lista calciatori'!$B$2:$AX$549,49,FALSE),"") | M7: =IFERROR(VLOOKUP(C7,'Lista calciatori'!$B$2:$AX$549,30,FALSE),"") | N7: =M7-L7 | O7: Joao Mario | P7: =IFERROR(VLOOKUP(C7,'Lista calciatori'!$B$2:$AX$549,42,FALSE),"") | Q7: BALLOTTAGGIO | R7: esterno utile al 4-3-3; pagalo premium solo se non compri due top di fascia | S7: https://www.sosfanta.com/guida-asta-fantacalcio/fantacalcio-mantra-ecco-la-guida-allasta-2026-27-la-divisione-ruolo-per-ruolo/
A8: Dd | B8: 3 | C8: Dodò | D8: Fiorentina | E8: Dd/E | F8: TOP | G8: TOP | H8: 51 | I8: =IFERROR(VLOOKUP(C8,'Lista calciatori'!$B$2:$AX$549,16,FALSE),"") | J8: 10 | K8: 10 | L8: =IFERROR(VLOOKUP(C8,'Lista calciatori'!$B$2:$AX$549,49,FALSE),"") | M8: =IFERROR(VLOOKUP(C8,'Lista calciatori'!$B$2:$AX$549,30,FALSE),"") | N8: =M8-L8 | O8: Joao Mario | P8: =IFERROR(VLOOKUP(C8,'Lista calciatori'!$B$2:$AX$549,42,FALSE),"") | Q8: BALLOTTAGGIO | R8: esterno utile al 4-3-3; pagalo premium solo se non compri due top di fascia | S8: https://www.sosfanta.com/guida-asta-fantacalcio/fantacalcio-mantra-ecco-la-guida-allasta-2026-27-la-divisione-ruolo-per-ruolo/
A9: Dd | B9: 4 | C9: Kalulu | D9: Juventus | E9: Dd/Dc | F9: SEMITOP | G9: SEMITOP | H9: 98 | I9: =IFERROR(VLOOKUP(C9,'Lista calciatori'!$B$2:$AX$549,16,FALSE),"") | J9: 14 | K9: 24 | L9: =IFERROR(VLOOKUP(C9,'Lista calciatori'!$B$2:$AX$549,49,FALSE),"") | M9: =IFERROR(VLOOKUP(C9,'Lista calciatori'!$B$2:$AX$549,30,FALSE),"") | N9: =M9-L9 | O9: Gatti | P9: =IFERROR(VLOOKUP(C9,'Lista calciatori'!$B$2:$AX$549,42,FALSE),"") | Q9: BASSO | R9: esterno utile al 4-3-3; pagalo premium solo se non compri due top di fascia | S9: https://www.sosfanta.com/guida-asta-fantacalcio/fantacalcio-mantra-ecco-la-guida-allasta-2026-27-la-divisione-ruolo-per-ruolo/
A10: Dd | B10: 5 | C10: Cambiaso | D10: Juventus | E10: Dd/Ds/E | F10: SEMITOP | G10: SEMITOP | H10: 98 | I10: =IFERROR(VLOOKUP(C10,'Lista calciatori'!$B$2:$AX$549,16,FALSE),"") | J10: 10 | K10: 14 | L10: =IFERROR(VLOOKUP(C10,'Lista calciatori'!$B$2:$AX$549,49,FALSE),"") | M10: =IFERROR(VLOOKUP(C10,'Lista calciatori'!$B$2:$AX$549,30,FALSE),"") | N10: =M10-L10 | O10: Celik | P10: =IFERROR(VLOOKUP(C10,'Lista calciatori'!$B$2:$AX$549,42,FALSE),"") | Q10: BASSO | R10: esterno utile al 4-3-3; pagalo premium solo se non compri due top di fascia | S10: https://www.sosfanta.com/guida-asta-fantacalcio/fantacalcio-mantra-ecco-la-guida-allasta-2026-27-la-divisione-ruolo-per-ruolo/
A11: Dd | B11: 6 | C11: Zappacosta | D11: Atalanta | E11: Dd/E | F11: SEMITOP | G11: SEMITOP | H11: 82 | I11: =IFERROR(VLOOKUP(C11,'Lista calciatori'!$B$2:$AX$549,16,FALSE),"") | J11: 8 | K11: 10 | L11: =IFERROR(VLOOKUP(C11,'Lista calciatori'!$B$2:$AX$549,49,FALSE),"") | M11: =IFERROR(VLOOKUP(C11,'Lista calciatori'!$B$2:$AX$549,30,FALSE),"") | N11: =M11-L11 | O11: Bellanova | P11: =IFERROR(VLOOKUP(C11,'Lista calciatori'!$B$2:$AX$549,42,FALSE),"") | Q11: BALLOTTAGGIO | R11: esterno utile al 4-3-3; pagalo premium solo se non compri due top di fascia | S11: https://www.sosfanta.com/guida-asta-fantacalcio/fantacalcio-mantra-ecco-la-guida-allasta-2026-27-la-divisione-ruolo-per-ruolo/
A12: Dd | B12: 7 | C12: Delprato | D12: Parma | E12: B/Dd/E | F12: TITOLARE VALUE | G12: SOTTO AI SEMITOP | H12: 98 | I12: =IFERROR(VLOOKUP(C12,'Lista calciatori'!$B$2:$AX$549,16,FALSE),"") | J12: 8 | K12: 12 | L12: =IFERROR(VLOOKUP(C12,'Lista calciatori'!$B$2:$AX$549,49,FALSE),"") | M12: =IFERROR(VLOOKUP(C12,'Lista calciatori'!$B$2:$AX$549,30,FALSE),"") | N12: =M12-L12 | O12: Britschgi | P12: =IFERROR(VLOOKUP(C12,'Lista calciatori'!$B$2:$AX$549,42,FALSE),"") | Q12: BASSO | R12: esterno utile al 4-3-3; pagalo premium solo se non compri due top di fascia | S12: https://www.sosfanta.com/guida-asta-fantacalcio/fantacalcio-mantra-ecco-la-guida-allasta-2026-27-la-divisione-ruolo-per-ruolo/
A13: Dd | B13: 8 | C13: Chalobah T. | D13: Como | E13: Dd/Dc | F13: JOLLY / COPERTURA | G13: SOTTO AI SEMITOP | H13: 82 | I13: =IFERROR(VLOOKUP(C13,'Lista calciatori'!$B$2:$AX$549,16,FALSE),"") | J13: 10 | K13: 16 | L13: =IFERROR(VLOOKUP(C13,'Lista calciatori'!$B$2:$AX$549,49,FALSE),"") | M13: =IFERROR(VLOOKUP(C13,'Lista calciatori'!$B$2:$AX$549,30,FALSE),"") | N13: =M13-L13 | O13: Kambwala | P13: =IFERROR(VLOOKUP(C13,'Lista calciatori'!$B$2:$AX$549,42,FALSE),"") | Q13: BALLOTTAGGIO | R13: esterno utile al 4-3-3; pagalo premium solo se non compri due top di fascia | S13: https://www.sosfanta.com/guida-asta-fantacalcio/fantacalcio-mantra-ecco-la-guida-allasta-2026-27-la-divisione-ruolo-per-ruolo/
A14: Dd | B14: 9 | C14: Vojvoda | D14: Udinese | E14: Dd/E | F14: TITOLARE VALUE | G14: SOTTO AI SEMITOP | H14: 98 | I14: =IFERROR(VLOOKUP(C14,'Lista calciatori'!$B$2:$AX$549,16,FALSE),"") | J14: 8 | K14: 10 | L14: =IFERROR(VLOOKUP(C14,'Lista calciatori'!$B$2:$AX$549,49,FALSE),"") | M14: =IFERROR(VLOOKUP(C14,'Lista calciatori'!$B$2:$AX$549,30,FALSE),"") | N14: =M14-L14 | O14: Zanoli | P14: =IFERROR(VLOOKUP(C14,'Lista calciatori'!$B$2:$AX$549,42,FALSE),"") | Q14: BASSO | R14: valore aumentato dalla possibile copertura di squadra/ruolo | S14: https://www.sosfanta.com/guida-asta-fantacalcio/fantacalcio-mantra-ecco-la-guida-allasta-2026-27-la-divisione-ruolo-per-ruolo/
A15: Dd | B15: 10 | C15: Zortea | D15: Bologna | E15: Dd/E | F15: TITOLARE VALUE | G15: SOTTO AI SEMITOP | H15: 98 | I15: =IFERROR(VLOOKUP(C15,'Lista calciatori'!$B$2:$AX$549,16,FALSE),"") | J15: 6 | K15: 10 | L15: =IFERROR(VLOOKUP(C15,'Lista calciatori'!$B$2:$AX$549,49,FALSE),"") | M15: =IFERROR(VLOOKUP(C15,'Lista calciatori'!$B$2:$AX$549,30,FALSE),"") | N15: =M15-L15 | O15: Holm | P15: =IFERROR(VLOOKUP(C15,'Lista calciatori'!$B$2:$AX$549,42,FALSE),"") | Q15: BASSO | R15: valore aumentato dalla possibile copertura di squadra/ruolo | S15: https://www.sosfanta.com/guida-asta-fantacalcio/fantacalcio-mantra-ecco-la-guida-allasta-2026-27-la-divisione-ruolo-per-ruolo/
A16: Dd | B16: 11 | C16: Celik | D16: Juventus | E16: B/Dd/E | F16: LOW COST | G16: SOTTO AI SEMITOP | H16: 51 | I16: =IFERROR(VLOOKUP(C16,'Lista calciatori'!$B$2:$AX$549,16,FALSE),"") | J16: 9 | K16: 9 | L16: =IFERROR(VLOOKUP(C16,'Lista calciatori'!$B$2:$AX$549,49,FALSE),"") | M16: =IFERROR(VLOOKUP(C16,'Lista calciatori'!$B$2:$AX$549,30,FALSE),"") | N16: =M16-L16 | O16: Cabal | P16: =IFERROR(VLOOKUP(C16,'Lista calciatori'!$B$2:$AX$549,42,FALSE),"") | Q16: BALLOTTAGGIO | R16: minuti a prezzo basso: utile per finanziare Pc/A | S16: https://www.sosfanta.com/guida-asta-fantacalcio/fantacalcio-mantra-ecco-la-guida-allasta-2026-27-la-divisione-ruolo-per-ruolo/
A17: Dd | B17: 12 | C17: Couto | D17: Como | E17: Dd/E | F17: GIOIELLINO | G17: POSSIBILI SORPRESE | H17: 82 | I17: =IFERROR(VLOOKUP(C17,'Lista calciatori'!$B$2:$AX$549,16,FALSE),"") | J17: 8 | K17: 13 | L17: =IFERROR(VLOOKUP(C17,'Lista calciatori'!$B$2:$AX$549,49,FALSE),"") | M17: =IFERROR(VLOOKUP(C17,'Lista calciatori'!$B$2:$AX$549,30,FALSE),"") | N17: =M17-L17 | O17: Smolcic I. | P17: =IFERROR(VLOOKUP(C17,'Lista calciatori'!$B$2:$AX$549,42,FALSE),"") | Q17: BALLOTTAGGIO | R17: upside + costo contenuto; profilo da battere presto o a fine reparto | S17: https://www.sosfanta.com/guida-asta-fantacalcio/fantacalcio-mantra-ecco-la-guida-allasta-2026-27-la-divisione-ruolo-per-ruolo/
... A20: Dd | B20: 15 | C20: Bellanova | D20: Atalanta | E20: Dd/E | F20: JOLLY / COPERTURA | G20: JOLLY 1ª FASCIA | H20: 47 | I20: =IFERROR(VLOOKUP(C20,'Lista calciatori'!$B$2:$AX$549,16,FALSE),"") | J20: 6 | K20: 9 | L20: =IFERROR(VLOOKUP(C20,'Lista calciatori'!$B$2:$AX$549,49,FALSE),"") | M20: =IFERROR(VLOOKUP(C20,'Lista calciatori'!$B$2:$AX$549,30,FALSE),"") | N20: =M20-L20 | O20: Kossounou | P20: =IFERROR(VLOOKUP(C20,'Lista calciatori'!$B$2:$AX$549,42,FALSE),"") | Q20: BALLOTTAGGIO | R20: valore aumentato dalla possibile copertura di squadra/ruolo | S20: https://www.sosfanta.com/guida-asta-fantacalcio/fantacalcio-mantra-ecco-la-guida-allasta-2026-27-la-divisione-ruolo-per-ruolo/
A21: Dd | B21: 16 | C21: Pavard | D21: Inter | E21: Dd/Dc | F21: JOLLY / COPERTURA | G21: JOLLY 1ª FASCIA | H21: 40 | I21: =IFERROR(VLOOKUP(C21,'Lista calciatori'!$B$2:$AX$549,16,FALSE),"") | J21: 7 | K21: 8 | L21: =IFERROR(VLOOKUP(C21,'Lista calciatori'!$B$2:$AX$549,49,FALSE),"") | M21: =IFERROR(VLOOKUP(C21,'Lista calciatori'!$B$2:$AX$549,30,FALSE),"") | N21: =M21-L21 | P21: =IFERROR(VLOOKUP(C21,'Lista calciatori'!$B$2:$AX$549,42,FALSE),"") | Q21: MEDIO | R21: alternativa credibile per allargare il ventaglio d asta | S21: https://www.sosfanta.com/guida-asta-fantacalcio/fantacalcio-mantra-ecco-la-guida-allasta-2026-27-la-divisione-ruolo-per-ruolo/
A22: Dd | B22: 17 | C22: Zanoli | D22: Udinese | E22: Dd/E | F22: LOW COST | G22: JOLLY 1ª FASCIA | H22: 30 | I22: =IFERROR(VLOOKUP(C22,'Lista calciatori'!$B$2:$AX$549,16,FALSE),"") | J22: 4 | K22: 5 | L22: =IFERROR(VLOOKUP(C22,'Lista calciatori'!$B$2:$AX$549,49,FALSE),"") | M22: =IFERROR(VLOOKUP(C22,'Lista calciatori'!$B$2:$AX$549,30,FALSE),"") | N22: =M22-L22 | P22: =IFERROR(VLOOKUP(C22,'Lista calciatori'!$B$2:$AX$549,42,FALSE),"") | Q22: MEDIO | R22: minuti a prezzo basso: utile per finanziare Pc/A | S22: https://www.sosfanta.com/guida-asta-fantacalcio/fantacalcio-mantra-ecco-la-guida-allasta-2026-27-la-divisione-ruolo-per-ruolo/
A23: Dd | B23: 18 | C23: Rensch | D23: Roma | E23: B/Dd/E | F23: TITOLARE VALUE | G23: JOLLY 2ª FASCIA | H23: 87 | I23: =IFERROR(VLOOKUP(C23,'Lista calciatori'!$B$2:$AX$549,16,FALSE),"") | J23: 6 | K23: 8 | L23: =IFERROR(VLOOKUP(C23,'Lista calciatori'!$B$2:$AX$549,49,FALSE),"") | M23: =IFERROR(VLOOKUP(C23,'Lista calciatori'!$B$2:$AX$549,30,FALSE),"") | N23: =M23-L23 | O23: Lulli | P23: =IFERROR(VLOOKUP(C23,'Lista calciatori'!$B$2:$AX$549,42,FALSE),"") | Q23: INFORTUNIO — da monitorare | R23: valore aumentato dalla possibile copertura di squadra/ruolo | S23: https://www.sosfanta.com/guida-asta-fantacalcio/fantacalcio-mantra-ecco-la-guida-allasta-2026-27-la-divisione-ruolo-per-ruolo/
A24: Dd | B24: 19 | C24: Joao Mario | D24: Fiorentina | E24: Dd/E | F24: LOW COST | G24: JOLLY 2ª FASCIA | H24: 58 | I24: =IFERROR(VLOOKUP(C24,'Lista calciatori'!$B$2:$AX$549,16,FALSE),"") | J24: 3 | K24: 6 | L24: =IFERROR(VLOOKUP(C24,'Lista calciatori'!$B$2:$AX$549,49,FALSE),"") | M24: =IFERROR(VLOOKUP(C24,'Lista calciatori'!$B$2:$AX$549,30,FALSE),"") | N24: =M24-L24 | O24: Dodò | P24: =IFERROR(VLOOKUP(C24,'Lista calciatori'!$B$2:$AX$549,42,FALSE),"") | Q24: BALLOTTAGGIO | R24: minuti a prezzo basso: utile per finanziare Pc/A | S24: https://www.sosfanta.com/guida-asta-fantacalcio/fantacalcio-mantra-ecco-la-guida-allasta-2026-27-la-divisione-ruolo-per-ruolo/
A25: Dd | B25: 20 | C25: Holm | D25: Bologna | E25: Dd/E | F25: LOW COST | G25: JOLLY 2ª FASCIA | H25: 42 | I25: =IFERROR(VLOOKUP(C25,'Lista calciatori'!$B$2:$AX$549,16,FALSE),"") | J25: 5 | K25: 7 | L25: =IFERROR(VLOOKUP(C25,'Lista calciatori'!$B$2:$AX$549,49,FALSE),"") | M25: =IFERROR(VLOOKUP(C25,'Lista calciatori'!$B$2:$AX$549,30,FALSE),"") | N25: =M25-L25 | O25: De Silvestri | P25: =IFERROR(VLOOKUP(C25,'Lista calciatori'!$B$2:$AX$549,42,FALSE),"") | Q25: MEDIO | R25: minuti a prezzo basso: utile per finanziare Pc/A | S25: https://www.sosfanta.com/guida-asta-fantacalcio/fantacalcio-mantra-ecco-la-guida-allasta-2026-27-la-divisione-ruolo-per-ruolo/
A26: Dd | B26: 21 | C26: Norton-Cuffy | D26: Genoa | E26: Dd/E | F26: TITOLARE VALUE | G26: LOW COST 1ª FASCIA | H26: 98 | I26: =IFERROR(VLOOKUP(C26,'Lista calciatori'!$B$2:$AX$549,16,FALSE),"") | J26: 8 | K26: 11 | L26: =IFERROR(VLOOKUP(C26,'Lista calciatori'!$B$2:$AX$549,49,FALSE),"") | M26: =IFERROR(VLOOKUP(C26,'Lista calciatori'!$B$2:$AX$549,30,FALSE),"") | N26: =M26-L26 | O26: Sabelli | P26: =IFERROR(VLOOKUP(C26,'Lista calciatori'!$B$2:$AX$549,42,FALSE),"") | Q26: BASSO | R26: valore aumentato dalla possibile copertura di squadra/ruolo | S26: https://www.sosfanta.com/guida-asta-fantacalcio/fantacalcio-mantra-ecco-la-guida-allasta-2026-27-la-divisione-ruolo-per-ruolo/
A27: Dd | B27: 22 | C27: Marusic | D27: Lazio | E27: Dd/Ds/E | F27: LOW COST | G27: LOW COST 1ª FASCIA | H27: 60 | I27: =IFERROR(VLOOKUP(C27,'Lista calciatori'!$B$2:$AX$549,16,FALSE),"") | J27: 6 | K27: 12 | L27: =IFERROR(VLOOKUP(C27,'Lista calciatori'!$B$2:$AX$549,49,FALSE),"") | M27: =IFERROR(VLOOKUP(C27,'Lista calciatori'!$B$2:$AX$549,30,FALSE),"") | N27: =M27-L27 | O27: Pedraza | P27: =IFERROR(VLOOKUP(C27,'Lista calciatori'!$B$2:$AX$549,42,FALSE),"") | Q27: INFORTUNIO | R27: minuti a prezzo basso: utile per finanziare Pc/A | S27: https://www.sosfanta.com/guida-asta-fantacalcio/fantacalcio-mantra-ecco-la-guida-allasta-2026-27-la-divisione-ruolo-per-ruolo/
A28: Dd | B28: 23 | C28: Birindelli | D28: Monza | E28: Dd/Ds/E | F28: JOLLY / COPERTURA | G28: LOW COST 1ª FASCIA | H28: 82 | I28: =IFERROR(VLOOKUP(C28,'Lista calciatori'!$B$2:$AX$549,16,FALSE),"") | J28: 5 | K28: 7 | L28: =IFERROR(VLOOKUP(C28,'Lista calciatori'!$B$2:$AX$549,49,FALSE),"") | M28: =IFERROR(VLOOKUP(C28,'Lista calciatori'!$B$2:$AX$549,30,FALSE),"") | N28: =M28-L28 | O28: Carboni A. | P28: =IFERROR(VLOOKUP(C28,'Lista calciatori'!$B$2:$AX$549,42,FALSE),"") | Q28: BALLOTTAGGIO | R28: valore aumentato dalla possibile copertura di squadra/ruolo | S28: https://www.sosfanta.com/guida-asta-fantacalcio/fantacalcio-mantra-ecco-la-guida-allasta-2026-27-la-divisione-ruolo-per-ruolo/
A29: Dd | B29: 24 | C29: Pedersen | D29: Torino | E29: Dd/E | F29: TITOLARE VALUE | G29: LOW COST 1ª FASCIA | H29: 91 | I29: =IFERROR(VLOOKUP(C29,'Lista calciatori'!$B$2:$AX$549,16,FALSE),"") | J29: 5 | K29: 6 | L29: =IFERROR(VLOOKUP(C29,'Lista calciatori'!$B$2:$AX$549,49,FALSE),"") | M29: =IFERROR(VLOOKUP(C29,'Lista calciatori'!$B$2:$AX$549,30,FALSE),"") | N29: =M29-L29 | O29: Fortini | P29: =IFERROR(VLOOKUP(C29,'Lista calciatori'!$B$2:$AX$549,42,FALSE),"") | Q29: BASSO | R29: valore aumentato dalla possibile copertura di squadra/ruolo | S29: https://www.sosfanta.com/guida-asta-fantacalcio/fantacalcio-mantra-ecco-la-guida-allasta-2026-27-la-divisione-ruolo-per-ruolo/
A30: Dd | B30: 25 | C30: Veiga D. | D30: Lecce | E30: Dd/E | F30: TITOLARE VALUE | G30: LOW COST 2ª FASCIA | H30: 98 | I30: =IFERROR(VLOOKUP(C30,'Lista calciatori'!$B$2:$AX$549,16,FALSE),"") | J30: 6 | K30: 6 | L30: =IFERROR(VLOOKUP(C30,'Lista calciatori'!$B$2:$AX$549,49,FALSE),"") | M30: =IFERROR(VLOOKUP(C30,'Lista calciatori'!$B$2:$AX$549,30,FALSE),"") | N30: =M30-L30 | O30: Ndaba | P30: =IFERROR(VLOOKUP(C30,'Lista calciatori'!$B$2:$AX$549,42,FALSE),"") | Q30: BASSO | R30: valore aumentato dalla possibile copertura di squadra/ruolo | S30: https://www.sosfanta.com/guida-asta-fantacalcio/fantacalcio-mantra-ecco-la-guida-allasta-2026-27-la-divisione-ruolo-per-ruolo/
A31: Dd | B31: 26 | C31: Oyono A. | D31: Frosinone | E31: Dd/E | F31: TITOLARE VALUE | G31: LOW COST 2ª FASCIA | H31: 91 | I31: =IFERROR(VLOOKUP(C31,'Lista calciatori'!$B$2:$AX$549,16,FALSE),"") | J31: 5 | K31: 5 | L31: =IFERROR(VLOOKUP(C31,'Lista calciatori'!$B$2:$AX$549,49,FALSE),"") | M31: =IFERROR(VLOOKUP(C31,'Lista calciatori'!$B$2:$AX$549,30,FALSE),"") | N31: =M31-L31 | O31: Tchato | P31: =IFERROR(VLOOKUP(C31,'Lista calciatori'!$B$2:$AX$549,42,FALSE),"") | Q31: BASSO | R31: valore aumentato dalla possibile copertura di squadra/ruolo | S31: https://www.sosfanta.com/guida-asta-fantacalcio/fantacalcio-mantra-ecco-la-guida-allasta-2026-27-la-divisione-ruolo-per-ruolo/
A32: Dd | B32: 27 | C32: Walukiewicz | D32: Sassuolo | E32: Dd/Dc | F32: JOLLY / COPERTURA | G32: LOW COST 2ª FASCIA | H32: 71 | I32: =IFERROR(VLOOKUP(C32,'Lista calciatori'!$B$2:$AX$549,16,FALSE),"") | J32: 4 | K32: 6 | L32: =IFERROR(VLOOKUP(C32,'Lista calciatori'!$B$2:$AX$549,49,FALSE),"") | M32: =IFERROR(VLOOKUP(C32,'Lista calciatori'!$B$2:$AX$549,30,FALSE),"") | N32: =M32-L32 | O32: Cinquegrano | P32: =IFERROR(VLOOKUP(C32,'Lista calciatori'!$B$2:$AX$549,42,FALSE),"") | Q32: BALLOTTAGGIO | R32: valore aumentato dalla possibile copertura di squadra/ruolo | S32: https://www.sosfanta.com/guida-asta-fantacalcio/fantacalcio-mantra-ecco-la-guida-allasta-2026-27-la-divisione-ruolo-per-ruolo/
A33: Dd | B33: 28 | C33: Bertola | D33: Udinese | E33: Dd/Ds/Dc | F33: JOLLY / COPERTURA | G33: JOLLY 3ª FASCIA | H33: 78 | I33: =IFERROR(VLOOKUP(C33,'Lista calciatori'!$B$2:$AX$549,16,FALSE),"") | J33: 6 | K33: 7 | L33: =IFERROR(VLOOKUP(C33,'Lista calciatori'!$B$2:$AX$549,49,FALSE),"") | M33: =IFERROR(VLOOKUP(C33,'Lista calciatori'!$B$2:$AX$549,30,FALSE),"") | N33: =M33-L33 | O33: Ebosse | P33: =IFERROR(VLOOKUP(C33,'Lista calciatori'!$B$2:$AX$549,42,FALSE),"") | Q33: BALLOTTAGGIO | R33: valore aumentato dalla possibile copertura di squadra/ruolo | S33: https://www.sosfanta.com/guida-asta-fantacalcio/fantacalcio-mantra-ecco-la-guida-allasta-2026-27-la-divisione-ruolo-per-ruolo/
A34: Dd | B34: 29 | C34: Helland | D34: Bologna | E34: Dd/Dc | F34: LOW COST | G34: JOLLY 3ª FASCIA | H34: 82 | I34: =IFERROR(VLOOKUP(C34,'Lista calciatori'!$B$2:$AX$549,16,FALSE),"") | J34: 3 | K34: 6 | L34: =IFERROR(VLOOKUP(C34,'Lista calciatori'!$B$2:$AX$549,49,FALSE),"") | M34: =IFERROR(VLOOKUP(C34,'Lista calciatori'!$B$2:$AX$549,30,FALSE),"") | N34: =M34-L34 | O34: De Silvestri | P34: =IFERROR(VLOOKUP(C34,'Lista calciatori'!$B$2:$AX$549,42,FALSE),"") | Q34: BASSO | R34: minuti a prezzo basso: utile per finanziare Pc/A | S34: https://www.sosfanta.com/guida-asta-fantacalcio/fantacalcio-mantra-ecco-la-guida-allasta-2026-27-la-divisione-ruolo-per-ruolo/
... A52: Ds | B52: 16 | C52: Valdepenas | D52: Fiorentina | E52: Ds/Dc | F52: GIOIELLINO | G52: SCOMMESSE | H52: 78 | I52: =IFERROR(VLOOKUP(C52,'Lista calciatori'!$B$2:$AX$549,16,FALSE),"") | J52: 7 | K52: 10 | L52: =IFERROR(VLOOKUP(C52,'Lista calciatori'!$B$2:$AX$549,49,FALSE),"") | M52: =IFERROR(VLOOKUP(C52,'Lista calciatori'!$B$2:$AX$549,30,FALSE),"") | N52: =M52-L52 | O52: Ranieri L. | P52: =IFERROR(VLOOKUP(C52,'Lista calciatori'!$B$2:$AX$549,42,FALSE),"") | Q52: BALLOTTAGGIO | R52: upside + costo contenuto; profilo da battere presto o a fine reparto | S52: https://www.sosfanta.com/guida-asta-fantacalcio/fantacalcio-mantra-ecco-la-guida-allasta-2026-27-la-divisione-ruolo-per-ruolo/
A53: Ds | B53: 17 | C53: Ahanor | D53: Atalanta | E53: B/Ds/E | F53: GIOIELLINO | G53: SCOMMESSE | H53: 43 | I53: =IFERROR(VLOOKUP(C53,'Lista calciatori'!$B$2:$AX$549,16,FALSE),"") | J53: 7 | K53: 8 | L53: =IFERROR(VLOOKUP(C53,'Lista calciatori'!$B$2:$AX$549,49,FALSE),"") | M53: =IFERROR(VLOOKUP(C53,'Lista calciatori'!$B$2:$AX$549,30,FALSE),"") | N53: =M53-L53 | P53: =IFERROR(VLOOKUP(C53,'Lista calciatori'!$B$2:$AX$549,42,FALSE),"") | Q53: A RISCHIO + BALLOTTAGGIO | R53: upside + costo contenuto; profilo da battere presto o a fine reparto | S53: https://www.sosfanta.com/guida-asta-fantacalcio/fantacalcio-mantra-ecco-la-guida-allasta-2026-27-la-divisione-ruolo-per-ruolo/
A54: Ds | B54: 18 | C54: Mitaj | D54: Genoa | E54: Ds/E | F54: GIOIELLINO | G54: SCOMMESSE | H54: 30 | I54: =IFERROR(VLOOKUP(C54,'Lista calciatori'!$B$2:$AX$549,16,FALSE),"") | J54: 4 | K54: 5 | L54: =IFERROR(VLOOKUP(C54,'Lista calciatori'!$B$2:$AX$549,49,FALSE),"") | M54: =IFERROR(VLOOKUP(C54,'Lista calciatori'!$B$2:$AX$549,30,FALSE),"") | N54: =M54-L54 | O54: Sabelli | P54: =IFERROR(VLOOKUP(C54,'Lista calciatori'!$B$2:$AX$549,42,FALSE),"") | Q54: MEDIO | R54: upside + costo contenuto; profilo da battere presto o a fine reparto | S54: https://www.sosfanta.com/guida-asta-fantacalcio/fantacalcio-mantra-ecco-la-guida-allasta-2026-27-la-divisione-ruolo-per-ruolo/
A55: Ds | B55: 19 | C55: Heggem | D55: Bologna | E55: Ds/Dc | F55: JOLLY / COPERTURA | G55: JOLLY 2ª FASCIA | H55: 82 | I55: =IFERROR(VLOOKUP(C55,'Lista calciatori'!$B$2:$AX$549,16,FALSE),"") | J55: 7 | K55: 9 | L55: =IFERROR(VLOOKUP(C55,'Lista calciatori'!$B$2:$AX$549,49,FALSE),"") | M55: =IFERROR(VLOOKUP(C55,'Lista calciatori'!$B$2:$AX$549,30,FALSE),"") | N55: =M55-L55 | O55: Helland | P55: =IFERROR(VLOOKUP(C55,'Lista calciatori'!$B$2:$AX$549,42,FALSE),"") | Q55: BALLOTTAGGIO | R55: valore aumentato dalla possibile copertura di squadra/ruolo | S55: https://www.sosfanta.com/guida-asta-fantacalcio/fantacalcio-mantra-ecco-la-guida-allasta-2026-27-la-divisione-ruolo-per-ruolo/
A56: Ds | B56: 20 | C56: Kelly L. | D56: Juventus | E56: Ds/Dc | F56: JOLLY / COPERTURA | G56: JOLLY 2ª FASCIA | H56: 82 | I56: =IFERROR(VLOOKUP(C56,'Lista calciatori'!$B$2:$AX$549,16,FALSE),"") | J56: 6 | K56: 7 | L56: =IFERROR(VLOOKUP(C56,'Lista calciatori'!$B$2:$AX$549,49,FALSE),"") | M56: =IFERROR(VLOOKUP(C56,'Lista calciatori'!$B$2:$AX$549,30,FALSE),"") | N56: =M56-L56 | O56: Cabal | P56: =IFERROR(VLOOKUP(C56,'Lista calciatori'!$B$2:$AX$549,42,FALSE),"") | Q56: BALLOTTAGGIO | R56: valore aumentato dalla possibile copertura di squadra/ruolo | S56: https://www.sosfanta.com/guida-asta-fantacalcio/fantacalcio-mantra-ecco-la-guida-allasta-2026-27-la-divisione-ruolo-per-ruolo/
A57: Ds | B57: 21 | C57: Olivera | D57: Napoli | E57: B/Ds/E | F57: LOW COST | G57: JOLLY 2ª FASCIA | H57: 47 | I57: =IFERROR(VLOOKUP(C57,'Lista calciatori'!$B$2:$AX$549,16,FALSE),"") | J57: 6 | K57: 8 | L57: =IFERROR(VLOOKUP(C57,'Lista calciatori'!$B$2:$AX$549,49,FALSE),"") | M57: =IFERROR(VLOOKUP(C57,'Lista calciatori'!$B$2:$AX$549,30,FALSE),"") | N57: =M57-L57 | O57: Mazzocchi | P57: =IFERROR(VLOOKUP(C57,'Lista calciatori'!$B$2:$AX$549,42,FALSE),"") | Q57: BALLOTTAGGIO | R57: minuti a prezzo basso: utile per finanziare Pc/A | S57: https://www.sosfanta.com/guida-asta-fantacalcio/fantacalcio-mantra-ecco-la-guida-allasta-2026-27-la-divisione-ruolo-per-ruolo/
A58: Ds | B58: 22 | C58: Gallo | D58: Lecce | E58: Ds/E | F58: TITOLARE VALUE | G58: LOW COST 1ª FASCIA | H58: 98 | I58: =IFERROR(VLOOKUP(C58,'Lista calciatori'!$B$2:$AX$549,16,FALSE),"") | J58: 6 | K58: 7 | L58: =IFERROR(VLOOKUP(C58,'Lista calciatori'!$B$2:$AX$549,49,FALSE),"") | M58: =IFERROR(VLOOKUP(C58,'Lista calciatori'!$B$2:$AX$549,30,FALSE),"") | N58: =M58-L58 | O58: Ndaba | P58: =IFERROR(VLOOKUP(C58,'Lista calciatori'!$B$2:$AX$549,42,FALSE),"") | Q58: BASSO | R58: valore aumentato dalla possibile copertura di squadra/ruolo | S58: https://www.sosfanta.com/guida-asta-fantacalcio/fantacalcio-mantra-ecco-la-guida-allasta-2026-27-la-divisione-ruolo-per-ruolo/
A59: Ds | B59: 23 | C59: Marusic | D59: Lazio | E59: Dd/Ds/E | F59: LOW COST | G59: LOW COST 1ª FASCIA | H59: 60 | I59: =IFERROR(VLOOKUP(C59,'Lista calciatori'!$B$2:$AX$549,16,FALSE),"") | J59: 6 | K59: 12 | L59: =IFERROR(VLOOKUP(C59,'Lista calciatori'!$B$2:$AX$549,49,FALSE),"") | M59: =IFERROR(VLOOKUP(C59,'Lista calciatori'!$B$2:$AX$549,30,FALSE),"") | N59: =M59-L59 | O59: Pedraza | P59: =IFERROR(VLOOKUP(C59,'Lista calciatori'!$B$2:$AX$549,42,FALSE),"") | Q59: INFORTUNIO | R59: minuti a prezzo basso: utile per finanziare Pc/A | S59: https://www.sosfanta.com/guida-asta-fantacalcio/fantacalcio-mantra-ecco-la-guida-allasta-2026-27-la-divisione-ruolo-per-ruolo/
A60: Ds | B60: 24 | C60: Kamara H. | D60: Udinese | E60: Ds/E | F60: TITOLARE VALUE | G60: LOW COST 1ª FASCIA | H60: 98 | I60: =IFERROR(VLOOKUP(C60,'Lista calciatori'!$B$2:$AX$549,16,FALSE),"") | J60: 8 | K60: 6 | L60: =IFERROR(VLOOKUP(C60,'Lista calciatori'!$B$2:$AX$549,49,FALSE),"") | M60: =IFERROR(VLOOKUP(C60,'Lista calciatori'!$B$2:$AX$549,30,FALSE),"") | N60: =M60-L60 | O60: Arizala | P60: =IFERROR(VLOOKUP(C60,'Lista calciatori'!$B$2:$AX$549,42,FALSE),"") | Q60: BASSO | R60: valore aumentato dalla possibile copertura di squadra/ruolo | S60: https://www.sosfanta.com/guida-asta-fantacalcio/fantacalcio-mantra-ecco-la-guida-allasta-2026-27-la-divisione-ruolo-per-ruolo/
A61: Ds | B61: 25 | C61: Birindelli | D61: Monza | E61: Dd/Ds/E | F61: JOLLY / COPERTURA | G61: LOW COST 1ª FASCIA | H61: 82 | I61: =IFERROR(VLOOKUP(C61,'Lista calciatori'!$B$2:$AX$549,16,FALSE),"") | J61: 5 | K61: 7 | L61: =IFERROR(VLOOKUP(C61,'Lista calciatori'!$B$2:$AX$549,49,FALSE),"") | M61: =IFERROR(VLOOKUP(C61,'Lista calciatori'!$B$2:$AX$549,30,FALSE),"") | N61: =M61-L61 | O61: Carboni A. | P61: =IFERROR(VLOOKUP(C61,'Lista calciatori'!$B$2:$AX$549,42,FALSE),"") | Q61: BALLOTTAGGIO | R61: valore aumentato dalla possibile copertura di squadra/ruolo | S61: https://www.sosfanta.com/guida-asta-fantacalcio/fantacalcio-mantra-ecco-la-guida-allasta-2026-27-la-divisione-ruolo-per-ruolo/
A62: Ds | B62: 26 | C62: Doig | D62: Sassuolo | E62: Ds/E | F62: TITOLARE LOW COST | G62: LOW COST 1ª FASCIA | H62: 98 | I62: =IFERROR(VLOOKUP(C62,'Lista calciatori'!$B$2:$AX$549,16,FALSE),"") | J62: 4 | K62: 5 | L62: =IFERROR(VLOOKUP(C62,'Lista calciatori'!$B$2:$AX$549,49,FALSE),"") | M62: =IFERROR(VLOOKUP(C62,'Lista calciatori'!$B$2:$AX$549,30,FALSE),"") | N62: =M62-L62 | O62: Obrador | P62: =IFERROR(VLOOKUP(C62,'Lista calciatori'!$B$2:$AX$549,42,FALSE),"") | Q62: BASSO | R62: minuti a prezzo basso: utile per finanziare Pc/A | S62: https://www.sosfanta.com/guida-asta-fantacalcio/fantacalcio-mantra-ecco-la-guida-allasta-2026-27-la-divisione-ruolo-per-ruolo/
A63: Ds | B63: 27 | C63: Bracaglia | D63: Frosinone | E63: Ds/Dc | F63: TITOLARE VALUE | G63: LOW COST 2ª FASCIA | H63: 98 | I63: =IFERROR(VLOOKUP(C63,'Lista calciatori'!$B$2:$AX$549,16,FALSE),"") | J63: 5 | K63: 7 | L63: =IFERROR(VLOOKUP(C63,'Lista calciatori'!$B$2:$AX$549,49,FALSE),"") | M63: =IFERROR(VLOOKUP(C63,'Lista calciatori'!$B$2:$AX$549,30,FALSE),"") | N63: =M63-L63 | O63: Calvani | P63: =IFERROR(VLOOKUP(C63,'Lista calciatori'!$B$2:$AX$549,42,FALSE),"") | Q63: BASSO | R63: valore aumentato dalla possibile copertura di squadra/ruolo | S63: https://www.sosfanta.com/guida-asta-fantacalcio/fantacalcio-mantra-ecco-la-guida-allasta-2026-27-la-divisione-ruolo-per-ruolo/
A64: Ds | B64: 28 | C64: Viery | D64: Fiorentina | E64: Ds/Dc | F64: JOLLY / COPERTURA | G64: LOW COST 2ª FASCIA | H64: 71 | I64: =IFERROR(VLOOKUP(C64,'Lista calciatori'!$B$2:$AX$549,16,FALSE),"") | J64: 7 | K64: 10 | L64: =IFERROR(VLOOKUP(C64,'Lista calciatori'!$B$2:$AX$549,49,FALSE),"") | M64: =IFERROR(VLOOKUP(C64,'Lista calciatori'!$B$2:$AX$549,30,FALSE),"") | N64: =M64-L64 | O64: Ranieri L. | P64: =IFERROR(VLOOKUP(C64,'Lista calciatori'!$B$2:$AX$549,42,FALSE),"") | Q64: BALLOTTAGGIO | R64: valore aumentato dalla possibile copertura di squadra/ruolo | S64: https://www.sosfanta.com/guida-asta-fantacalcio/fantacalcio-mantra-ecco-la-guida-allasta-2026-27-la-divisione-ruolo-per-ruolo/
A65: Ds | B65: 29 | C65: Candè | D65: Sassuolo | E65: Ds/Dc | F65: TITOLARE VALUE | G65: LOW COST 2ª FASCIA | H65: 87 | I65: =IFERROR(VLOOKUP(C65,'Lista calciatori'!$B$2:$AX$549,16,FALSE),"") | J65: 3 | K65: 4 | L65: =IFERROR(VLOOKUP(C65,'Lista calciatori'!$B$2:$AX$549,49,FALSE),"") | M65: =IFERROR(VLOOKUP(C65,'Lista calciatori'!$B$2:$AX$549,30,FALSE),"") | N65: =M65-L65 | O65: Walukiewicz | P65: =IFERROR(VLOOKUP(C65,'Lista calciatori'!$B$2:$AX$549,42,FALSE),"") | Q65: BASSO | R65: valore aumentato dalla possibile copertura di squadra/ruolo | S65: https://www.sosfanta.com/guida-asta-fantacalcio/fantacalcio-mantra-ecco-la-guida-allasta-2026-27-la-divisione-ruolo-per-ruolo/
... A97: Dc | B97: 30 | C97: Kelly L. | D97: Juventus | E97: Ds/Dc | F97: JOLLY / COPERTURA | G97: JOLLY 2ª FASCIA | H97: 82 | I97: =IFERROR(VLOOKUP(C97,'Lista calciatori'!$B$2:$AX$549,16,FALSE),"") | J97: 6 | K97: 7 | L97: =IFERROR(VLOOKUP(C97,'Lista calciatori'!$B$2:$AX$549,49,FALSE),"") | M97: =IFERROR(VLOOKUP(C97,'Lista calciatori'!$B$2:$AX$549,30,FALSE),"") | N97: =M97-L97 | O97: Cabal | P97: =IFERROR(VLOOKUP(C97,'Lista calciatori'!$B$2:$AX$549,42,FALSE),"") | Q97: BALLOTTAGGIO | R97: reparto profondo: valore/titolarita prima del brand | S97: https://www.sosfanta.com/guida-asta-fantacalcio/fantacalcio-mantra-ecco-la-guida-allasta-2026-27-la-divisione-ruolo-per-ruolo/
A99: Jolly | B99: 1 | C99: Dimarco | D99: Inter | E99: E/W | F99: ALL-IN / SUPER TOP | G99: SUPER TOP | H99: 98 | I99: =IFERROR(VLOOKUP(C99,'Lista calciatori'!$B$2:$AX$549,16,FALSE),"") | J99: 30 | K99: 127 | L99: =IFERROR(VLOOKUP(C99,'Lista calciatori'!$B$2:$AX$549,49,FALSE),"") | M99: =IFERROR(VLOOKUP(C99,'Lista calciatori'!$B$2:$AX$549,30,FALSE),"") | N99: =M99-L99 | P99: =IFERROR(VLOOKUP(C99,'Lista calciatori'!$B$2:$AX$549,42,FALSE),"") | Q99: BASSO | R99: alternativa credibile per allargare il ventaglio d asta | S99: https://www.sosfanta.com/guida-asta-fantacalcio/fantacalcio-mantra-ecco-la-guida-allasta-2026-27-la-divisione-ruolo-per-ruolo/
A100: Jolly | B100: 2 | C100: McTominay | D100: Napoli | E100: C/T | F100: ALL-IN / SUPER TOP | G100: SUPER TOP | H100: 98 | I100: =IFERROR(VLOOKUP(C100,'Lista calciatori'!$B$2:$AX$549,16,FALSE),"") | J100: 28 | K100: 114 | L100: =IFERROR(VLOOKUP(C100,'Lista calciatori'!$B$2:$AX$549,49,FALSE),"") | M100: =IFERROR(VLOOKUP(C100,'Lista calciatori'!$B$2:$AX$549,30,FALSE),"") | N100: =M100-L100 | P100: =IFERROR(VLOOKUP(C100,'Lista calciatori'!$B$2:$AX$549,42,FALSE),"") | Q100: BASSO | R100: alternativa credibile per allargare il ventaglio d asta | S100: https://www.sosfanta.com/guida-asta-fantacalcio/fantacalcio-mantra-ecco-la-guida-allasta-2026-27-la-divisione-ruolo-per-ruolo/
A101: Jolly | B101: 3 | C101: Paz N. | D101: Como | E101: T/A | F101: TOP | G101: TOP | H101: 98 | I101: =IFERROR(VLOOKUP(C101,'Lista calciatori'!$B$2:$AX$549,16,FALSE),"") | J101: 27 | K101: 124 | L101: =IFERROR(VLOOKUP(C101,'Lista calciatori'!$B$2:$AX$549,49,FALSE),"") | M101: =IFERROR(VLOOKUP(C101,'Lista calciatori'!$B$2:$AX$549,30,FALSE),"") | N101: =M101-L101 | P101: =IFERROR(VLOOKUP(C101,'Lista calciatori'!$B$2:$AX$549,42,FALSE),"") | Q101: BASSO | R101: alternativa credibile per allargare il ventaglio d asta | S101: https://www.sosfanta.com/guida-asta-fantacalcio/fantacalcio-mantra-ecco-la-guida-allasta-2026-27-la-divisione-ruolo-per-ruolo/
A102: Jolly | B102: 4 | C102: Wesley | D102: Roma | E102: E | F102: TOP | G102: TOP | H102: 98 | I102: =IFERROR(VLOOKUP(C102,'Lista calciatori'!$B$2:$AX$549,16,FALSE),"") | J102: 16 | K102: 41 | L102: =IFERROR(VLOOKUP(C102,'Lista calciatori'!$B$2:$AX$549,49,FALSE),"") | M102: =IFERROR(VLOOKUP(C102,'Lista calciatori'!$B$2:$AX$549,30,FALSE),"") | N102: =M102-L102 | O102: Rensch | P102: =IFERROR(VLOOKUP(C102,'Lista calciatori'!$B$2:$AX$549,42,FALSE),"") | Q102: BASSO | R102: valore aumentato dalla possibile copertura di squadra/ruolo | S102: https://www.sosfanta.com/guida-asta-fantacalcio/fantacalcio-mantra-ecco-la-guida-allasta-2026-27-la-divisione-ruolo-per-ruolo/
A103: Jolly | B103: 5 | C103: Orsolini | D103: Bologna | E103: W/A | F103: TOP | G103: TOP | H103: 98 | I103: =IFERROR(VLOOKUP(C103,'Lista calciatori'!$B$2:$AX$549,16,FALSE),"") | J103: 24 | K103: 96 | L103: =IFERROR(VLOOKUP(C103,'Lista calciatori'!$B$2:$AX$549,49,FALSE),"") | M103: =IFERROR(VLOOKUP(C103,'Lista calciatori'!$B$2:$AX$549,30,FALSE),"") | N103: =M103-L103 | P103: =IFERROR(VLOOKUP(C103,'Lista calciatori'!$B$2:$AX$549,42,FALSE),"") | Q103: BASSO | R103: alternativa credibile per allargare il ventaglio d asta | S103: https://www.sosfanta.com/guida-asta-fantacalcio/fantacalcio-mantra-ecco-la-guida-allasta-2026-27-la-divisione-ruolo-per-ruolo/
A104: Jolly | B104: 6 | C104: Rabiot | D104: Milan | E104: C/T | F104: TOP | G104: TOP | H104: 98 | I104: =IFERROR(VLOOKUP(C104,'Lista calciatori'!$B$2:$AX$549,16,FALSE),"") | J104: 23 | K104: 73 | L104: =IFERROR(VLOOKUP(C104,'Lista calciatori'!$B$2:$AX$549,49,FALSE),"") | M104: =IFERROR(VLOOKUP(C104,'Lista calciatori'!$B$2:$AX$549,30,FALSE),"") | N104: =M104-L104 | P104: =IFERROR(VLOOKUP(C104,'Lista calciatori'!$B$2:$AX$549,42,FALSE),"") | Q104: BASSO | R104: alternativa credibile per allargare il ventaglio d asta | S104: https://www.sosfanta.com/guida-asta-fantacalcio/fantacalcio-mantra-ecco-la-guida-allasta-2026-27-la-divisione-ruolo-per-ruolo/
A105: Jolly | B105: 7 | C105: Atta | D105: Fiorentina | E105: C/T | F105: TOP | G105: TOP | H105: 98 | I105: =IFERROR(VLOOKUP(C105,'Lista calciatori'!$B$2:$AX$549,16,FALSE),"") | J105: 16 | K105: 43 | L105: =IFERROR(VLOOKUP(C105,'Lista calciatori'!$B$2:$AX$549,49,FALSE),"") | M105: =IFERROR(VLOOKUP(C105,'Lista calciatori'!$B$2:$AX$549,30,FALSE),"") | N105: =M105-L105 | P105: =IFERROR(VLOOKUP(C105,'Lista calciatori'!$B$2:$AX$549,42,FALSE),"") | Q105: BASSO | R105: alternativa credibile per allargare il ventaglio d asta | S105: https://www.sosfanta.com/guida-asta-fantacalcio/fantacalcio-mantra-ecco-la-guida-allasta-2026-27-la-divisione-ruolo-per-ruolo/
A106: Jolly | B106: 8 | C106: Di Lorenzo | D106: Napoli | E106: Dd/E | F106: TOP | G106: TOP | H106: 98 | I106: =IFERROR(VLOOKUP(C106,'Lista calciatori'!$B$2:$AX$549,16,FALSE),"") | J106: 12 | K106: 20 | L106: =IFERROR(VLOOKUP(C106,'Lista calciatori'!$B$2:$AX$549,49,FALSE),"") | M106: =IFERROR(VLOOKUP(C106,'Lista calciatori'!$B$2:$AX$549,30,FALSE),"") | N106: =M106-L106 | O106: Favasuli | P106: =IFERROR(VLOOKUP(C106,'Lista calciatori'!$B$2:$AX$549,42,FALSE),"") | Q106: BASSO | R106: valore aumentato dalla possibile copertura di squadra/ruolo | S106: https://www.sosfanta.com/guida-asta-fantacalcio/fantacalcio-mantra-ecco-la-guida-allasta-2026-27-la-divisione-ruolo-per-ruolo/
A107: Jolly | B107: 9 | C107: Pulisic | D107: Milan | E107: T/A | F107: TOP | G107: TOP | H107: 87 | I107: =IFERROR(VLOOKUP(C107,'Lista calciatori'!$B$2:$AX$549,16,FALSE),"") | J107: 22 | K107: 80 | L107: =IFERROR(VLOOKUP(C107,'Lista calciatori'!$B$2:$AX$549,49,FALSE),"") | M107: =IFERROR(VLOOKUP(C107,'Lista calciatori'!$B$2:$AX$549,30,FALSE),"") | N107: =M107-L107 | P107: =IFERROR(VLOOKUP(C107,'Lista calciatori'!$B$2:$AX$549,42,FALSE),"") | Q107: BASSO | R107: alternativa credibile per allargare il ventaglio d asta | S107: https://www.sosfanta.com/guida-asta-fantacalcio/fantacalcio-mantra-ecco-la-guida-allasta-2026-27-la-divisione-ruolo-per-ruolo/
A108: Jolly | B108: 10 | C108: Spinazzola | D108: Napoli | E108: Ds/E | F108: TOP | G108: TOP | H108: 82 | I108: =IFERROR(VLOOKUP(C108,'Lista calciatori'!$B$2:$AX$549,16,FALSE),"") | J108: 8 | K108: 13 | L108: =IFERROR(VLOOKUP(C108,'Lista calciatori'!$B$2:$AX$549,49,FALSE),"") | M108: =IFERROR(VLOOKUP(C108,'Lista calciatori'!$B$2:$AX$549,30,FALSE),"") | N108: =M108-L108 | O108: Olivera | P108: =IFERROR(VLOOKUP(C108,'Lista calciatori'!$B$2:$AX$549,42,FALSE),"") | Q108: BALLOTTAGGIO | R108: valore aumentato dalla possibile copertura di squadra/ruolo | S108: https://www.sosfanta.com/guida-asta-fantacalcio/fantacalcio-mantra-ecco-la-guida-allasta-2026-27-la-divisione-ruolo-per-ruolo/
A109: Jolly | B109: 11 | C109: Jimenez A. | D109: Fiorentina | E109: Dd/Ds/E | F109: TOP | G109: TOP | H109: 75 | I109: =IFERROR(VLOOKUP(C109,'Lista calciatori'!$B$2:$AX$549,16,FALSE),"") | J109: 9 | K109: 13 | L109: =IFERROR(VLOOKUP(C109,'Lista calciatori'!$B$2:$AX$549,49,FALSE),"") | M109: =IFERROR(VLOOKUP(C109,'Lista calciatori'!$B$2:$AX$549,30,FALSE),"") | N109: =M109-L109 | P109: =IFERROR(VLOOKUP(C109,'Lista calciatori'!$B$2:$AX$549,42,FALSE),"") | Q109: BALLOTTAGGIO | R109: alternativa credibile per allargare il ventaglio d asta | S109: https://www.sosfanta.com/guida-asta-fantacalcio/fantacalcio-mantra-ecco-la-guida-allasta-2026-27-la-divisione-ruolo-per-ruolo/
A110: Jolly | B110: 12 | C110: Dodò | D110: Fiorentina | E110: Dd/E | F110: TOP | G110: TOP | H110: 51 | I110: =IFERROR(VLOOKUP(C110,'Lista calciatori'!$B$2:$AX$549,16,FALSE),"") | J110: 10 | K110: 10 | L110: =IFERROR(VLOOKUP(C110,'Lista calciatori'!$B$2:$AX$549,49,FALSE),"") | M110: =IFERROR(VLOOKUP(C110,'Lista calciatori'!$B$2:$AX$549,30,FALSE),"") | N110: =M110-L110 | P110: =IFERROR(VLOOKUP(C110,'Lista calciatori'!$B$2:$AX$549,42,FALSE),"") | Q110: BALLOTTAGGIO | R110: alternativa credibile per allargare il ventaglio d asta | S110: https://www.sosfanta.com/guida-asta-fantacalcio/fantacalcio-mantra-ecco-la-guida-allasta-2026-27-la-divisione-ruolo-per-ruolo/
A111: Jolly | B111: 13 | C111: Da Cunha | D111: Como | E111: C/T | F111: SEMITOP | G111: SEMITOP | H111: 98 | I111: =IFERROR(VLOOKUP(C111,'Lista calciatori'!$B$2:$AX$549,16,FALSE),"") | J111: 18 | K111: 44 | L111: =IFERROR(VLOOKUP(C111,'Lista calciatori'!$B$2:$AX$549,49,FALSE),"") | M111: =IFERROR(VLOOKUP(C111,'Lista calciatori'!$B$2:$AX$549,30,FALSE),"") | N111: =M111-L111 | P111: =IFERROR(VLOOKUP(C111,'Lista calciatori'!$B$2:$AX$549,42,FALSE),"") | Q111: BASSO | R111: alternativa credibile per allargare il ventaglio d asta | S111: https://www.sosfanta.com/guida-asta-fantacalcio/fantacalcio-mantra-ecco-la-guida-allasta-2026-27-la-divisione-ruolo-per-ruolo/
A112: Jolly | B112: 14 | C112: Vlasic | D112: Torino | E112: T | F112: SEMITOP | G112: SEMITOP | H112: 98 | I112: =IFERROR(VLOOKUP(C112,'Lista calciatori'!$B$2:$AX$549,16,FALSE),"") | J112: 12 | K112: 36 | L112: =IFERROR(VLOOKUP(C112,'Lista calciatori'!$B$2:$AX$549,49,FALSE),"") | M112: =IFERROR(VLOOKUP(C112,'Lista calciatori'!$B$2:$AX$549,30,FALSE),"") | N112: =M112-L112 | P112: =IFERROR(VLOOKUP(C112,'Lista calciatori'!$B$2:$AX$549,42,FALSE),"") | Q112: BASSO | R112: alternativa credibile per allargare il ventaglio d asta | S112: https://www.sosfanta.com/guida-asta-fantacalcio/fantacalcio-mantra-ecco-la-guida-allasta-2026-27-la-divisione-ruolo-per-ruolo/
A113: Jolly | B113: 15 | C113: Cambiaso | D113: Juventus | E113: Dd/Ds/E | F113: SEMITOP | G113: SEMITOP | H113: 98 | I113: =IFERROR(VLOOKUP(C113,'Lista calciatori'!$B$2:$AX$549,16,FALSE),"") | J113: 10 | K113: 14 | L113: =IFERROR(VLOOKUP(C113,'Lista calciatori'!$B$2:$AX$549,49,FALSE),"") | M113: =IFERROR(VLOOKUP(C113,'Lista calciatori'!$B$2:$AX$549,30,FALSE),"") | N113: =M113-L113 | O113: Celik | P113: =IFERROR(VLOOKUP(C113,'Lista calciatori'!$B$2:$AX$549,42,FALSE),"") | Q113: BASSO | R113: valore aumentato dalla possibile copertura di squadra/ruolo | S113: https://www.sosfanta.com/guida-asta-fantacalcio/fantacalcio-mantra-ecco-la-guida-allasta-2026-27-la-divisione-ruolo-per-ruolo/
A114: Jolly | B114: 16 | C114: Baturina | D114: Como | E114: T | F114: SEMITOP | G114: SEMITOP | H114: 82 | I114: =IFERROR(VLOOKUP(C114,'Lista calciatori'!$B$2:$AX$549,16,FALSE),"") | J114: 18 | K114: 48 | L114: =IFERROR(VLOOKUP(C114,'Lista calciatori'!$B$2:$AX$549,49,FALSE),"") | M114: =IFERROR(VLOOKUP(C114,'Lista calciatori'!$B$2:$AX$549,30,FALSE),"") | N114: =M114-L114 | P114: =IFERROR(VLOOKUP(C114,'Lista calciatori'!$B$2:$AX$549,42,FALSE),"") | Q114: BALLOTTAGGIO | R114: alternativa credibile per allargare il ventaglio d asta | S114: https://www.sosfanta.com/guida-asta-fantacalcio/fantacalcio-mantra-ecco-la-guida-allasta-2026-27-la-divisione-ruolo-per-ruolo/
A115: Jolly | B115: 17 | C115: De Bruyne | D115: Napoli | E115: T | F115: SEMITOP | G115: SEMITOP | H115: 75 | I115: =IFERROR(VLOOKUP(C115,'Lista calciatori'!$B$2:$AX$549,16,FALSE),"") | J115: 16 | K115: 53 | L115: =IFERROR(VLOOKUP(C115,'Lista calciatori'!$B$2:$AX$549,49,FALSE),"") | M115: =IFERROR(VLOOKUP(C115,'Lista calciatori'!$B$2:$AX$549,30,FALSE),"") | N115: =M115-L115 | P115: =IFERROR(VLOOKUP(C115,'Lista calciatori'!$B$2:$AX$549,42,FALSE),"") | Q115: BALLOTTAGGIO | R115: alternativa credibile per allargare il ventaglio d asta | S115: https://www.sosfanta.com/guida-asta-fantacalcio/fantacalcio-mantra-ecco-la-guida-allasta-2026-27-la-divisione-ruolo-per-ruolo/
A116: Jolly | B116: 18 | C116: Bartesaghi | D116: Milan | E116: Ds/E | F116: SEMITOP | G116: SEMITOP | H116: 91 | I116: =IFERROR(VLOOKUP(C116,'Lista calciatori'!$B$2:$AX$549,16,FALSE),"") | J116: 8 | K116: 11 | L116: =IFERROR(VLOOKUP(C116,'Lista calciatori'!$B$2:$AX$549,49,FALSE),"") | M116: =IFERROR(VLOOKUP(C116,'Lista calciatori'!$B$2:$AX$549,30,FALSE),"") | N116: =M116-L116 | O116: Estupinan | P116: =IFERROR(VLOOKUP(C116,'Lista calciatori'!$B$2:$AX$549,42,FALSE),"") | Q116: BASSO | R116: valore aumentato dalla possibile copertura di squadra/ruolo | S116: https://www.sosfanta.com/guida-asta-fantacalcio/fantacalcio-mantra-ecco-la-guida-allasta-2026-27-la-divisione-ruolo-per-ruolo/
A117: Jolly | B117: 19 | C117: Alajbegovic | D117: Juventus | E117: W/T | F117: SEMITOP | G117: SEMITOP | H117: 71 | I117: =IFERROR(VLOOKUP(C117,'Lista calciatori'!$B$2:$AX$549,16,FALSE),"") | J117: 12 | K117: 26 | L117: =IFERROR(VLOOKUP(C117,'Lista calciatori'!$B$2:$AX$549,49,FALSE),"") | M117: =IFERROR(VLOOKUP(C117,'Lista calciatori'!$B$2:$AX$549,30,FALSE),"") | N117: =M117-L117 | P117: =IFERROR(VLOOKUP(C117,'Lista calciatori'!$B$2:$AX$549,42,FALSE),"") | Q117: BALLOTTAGGIO | R117: alternativa credibile per allargare il ventaglio d asta | S117: https://www.sosfanta.com/guida-asta-fantacalcio/fantacalcio-mantra-ecco-la-guida-allasta-2026-27-la-divisione-ruolo-per-ruolo/
A118: Jolly | B118: 20 | C118: Zappacosta | D118: Atalanta | E118: Dd/E | F118: SEMITOP | G118: SEMITOP | H118: 82 | I118: =IFERROR(VLOOKUP(C118,'Lista calciatori'!$B$2:$AX$549,16,FALSE),"") | J118: 8 | K118: 10 | L118: =IFERROR(VLOOKUP(C118,'Lista calciatori'!$B$2:$AX$549,49,FALSE),"") | M118: =IFERROR(VLOOKUP(C118,'Lista calciatori'!$B$2:$AX$549,30,FALSE),"") | N118: =M118-L118 | O118: Bellanova | P118: =IFERROR(VLOOKUP(C118,'Lista calciatori'!$B$2:$AX$549,42,FALSE),"") | Q118: BALLOTTAGGIO | R118: valore aumentato dalla possibile copertura di squadra/ruolo | S118: https://www.sosfanta.com/guida-asta-fantacalcio/fantacalcio-mantra-ecco-la-guida-allasta-2026-27-la-divisione-ruolo-per-ruolo/
A119: Jolly | B119: 21 | C119: Saelemaekers | D119: Milan | E119: E/W | F119: SEMITOP | G119: SEMITOP | H119: 51 | I119: =IFERROR(VLOOKUP(C119,'Lista calciatori'!$B$2:$AX$549,16,FALSE),"") | J119: 11 | K119: 18 | L119: =IFERROR(VLOOKUP(C119,'Lista calciatori'!$B$2:$AX$549,49,FALSE),"") | M119: =IFERROR(VLOOKUP(C119,'Lista calciatori'!$B$2:$AX$549,30,FALSE),"") | N119: =M119-L119 | P119: =IFERROR(VLOOKUP(C119,'Lista calciatori'!$B$2:$AX$549,42,FALSE),"") | Q119: BALLOTTAGGIO | R119: alternativa credibile per allargare il ventaglio d asta | S119: https://www.sosfanta.com/guida-asta-fantacalcio/fantacalcio-mantra-ecco-la-guida-allasta-2026-27-la-divisione-ruolo-per-ruolo/
A120: Jolly | B120: 22 | C120: Tourè I. | D120: Monza | E120: E/M | F120: SEMITOP | G120: SEMITOP | H120: 37 | I120: =IFERROR(VLOOKUP(C120,'Lista calciatori'!$B$2:$AX$549,16,FALSE),"") | J120: 8 | K120: 10 | L120: =IFERROR(VLOOKUP(C120,'Lista calciatori'!$B$2:$AX$549,49,FALSE),"") | M120: =IFERROR(VLOOKUP(C120,'Lista calciatori'!$B$2:$AX$549,30,FALSE),"") | N120: =M120-L120 | P120: =IFERROR(VLOOKUP(C120,'Lista calciatori'!$B$2:$AX$549,42,FALSE),"") | Q120: MEDIO | R120: alternativa credibile per allargare il ventaglio d asta | S120: https://www.sosfanta.com/guida-asta-fantacalcio/fantacalcio-mantra-ecco-la-guida-allasta-2026-27-la-divisione-ruolo-per-ruolo/
A121: Jolly | B121: 23 | C121: Diouf | D121: Inter | E121: E/C | F121: GIOIELLINO | G121: POSSIBILI SORPRESE | H121: 82 | I121: =IFERROR(VLOOKUP(C121,'Lista calciatori'!$B$2:$AX$549,16,FALSE),"") | J121: 10 | K121: 24 | L121: =IFERROR(VLOOKUP(C121,'Lista calciatori'!$B$2:$AX$549,49,FALSE),"") | M121: =IFERROR(VLOOKUP(C121,'Lista calciatori'!$B$2:$AX$549,30,FALSE),"") | N121: =M121-L121 | P121: =IFERROR(VLOOKUP(C121,'Lista calciatori'!$B$2:$AX$549,42,FALSE),"") | Q121: BALLOTTAGGIO | R121: upside + costo contenuto; profilo da battere presto o a fine reparto | S121: https://www.sosfanta.com/guida-asta-fantacalcio/fantacalcio-mantra-ecco-la-guida-allasta-2026-27-la-divisione-ruolo-per-ruolo/
A122: Jolly | B122: 24 | C122: Fazzini | D122: Cagliari | E122: C/T | F122: GIOIELLINO | G122: POSSIBILI SORPRESE | H122: 98 | I122: =IFERROR(VLOOKUP(C122,'Lista calciatori'!$B$2:$AX$549,16,FALSE),"") | J122: 8 | K122: 12 | L122: =IFERROR(VLOOKUP(C122,'Lista calciatori'!$B$2:$AX$549,49,FALSE),"") | M122: =IFERROR(VLOOKUP(C122,'Lista calciatori'!$B$2:$AX$549,30,FALSE),"") | N122: =M122-L122 | P122: =IFERROR(VLOOKUP(C122,'Lista calciatori'!$B$2:$AX$549,42,FALSE),"") | Q122: BASSO | R122: upside + costo contenuto; profilo da battere presto o a fine reparto | S122: https://www.sosfanta.com/guida-asta-fantacalcio/fantacalcio-mantra-ecco-la-guida-allasta-2026-27-la-divisione-ruolo-per-ruolo/
A123: Jolly | B123: 25 | C123: Casadei | D123: Torino | E123: C/T | F123: GIOIELLINO | G123: POSSIBILI SORPRESE | H123: 82 | I123: =IFERROR(VLOOKUP(C123,'Lista calciatori'!$B$2:$AX$549,16,FALSE),"") | J123: 10 | K123: 16 | L123: =IFERROR(VLOOKUP(C123,'Lista calciatori'!$B$2:$AX$549,49,FALSE),"") | M123: =IFERROR(VLOOKUP(C123,'Lista calciatori'!$B$2:$AX$549,30,FALSE),"") | N123: =M123-L123 | P123: =IFERROR(VLOOKUP(C123,'Lista calciatori'!$B$2:$AX$549,42,FALSE),"") | Q123: BALLOTTAGGIO | R123: upside + costo contenuto; profilo da battere presto o a fine reparto | S123: https://www.sosfanta.com/guida-asta-fantacalcio/fantacalcio-mantra-ecco-la-guida-allasta-2026-27-la-divisione-ruolo-per-ruolo/
A124: Jolly | B124: 26 | C124: Baldanzi | D124: Genoa | E124: T | F124: GIOIELLINO | G124: POSSIBILI SORPRESE | H124: 82 | I124: =IFERROR(VLOOKUP(C124,'Lista calciatori'!$B$2:$AX$549,16,FALSE),"") | J124: 10 | K124: 14 | L124: =IFERROR(VLOOKUP(C124,'Lista calciatori'!$B$2:$AX$549,49,FALSE),"") | M124: =IFERROR(VLOOKUP(C124,'Lista calciatori'!$B$2:$AX$549,30,FALSE),"") | N124: =M124-L124 | P124: =IFERROR(VLOOKUP(C124,'Lista calciatori'!$B$2:$AX$549,42,FALSE),"") | Q124: BALLOTTAGGIO | R124: upside + costo contenuto; profilo da battere presto o a fine reparto | S124: https://www.sosfanta.com/guida-asta-fantacalcio/fantacalcio-mantra-ecco-la-guida-allasta-2026-27-la-divisione-ruolo-per-ruolo/
A125: Jolly | B125: 27 | C125: Couto | D125: Como | E125: Dd/E | F125: GIOIELLINO | G125: POSSIBILI SORPRESE | H125: 82 | I125: =IFERROR(VLOOKUP(C125,'Lista calciatori'!$B$2:$AX$549,16,FALSE),"") | J125: 8 | K125: 13 | L125: =IFERROR(VLOOKUP(C125,'Lista calciatori'!$B$2:$AX$549,49,FALSE),"") | M125: =IFERROR(VLOOKUP(C125,'Lista calciatori'!$B$2:$AX$549,30,FALSE),"") | N125: =M125-L125 | P125: =IFERROR(VLOOKUP(C125,'Lista calciatori'!$B$2:$AX$549,42,FALSE),"") | Q125: BALLOTTAGGIO | R125: upside + costo contenuto; profilo da battere presto o a fine reparto | S125: https://www.sosfanta.com/guida-asta-fantacalcio/fantacalcio-mantra-ecco-la-guida-allasta-2026-27-la-divisione-ruolo-per-ruolo/
A126: Jolly | B126: 28 | C126: Mangas | D126: Monza | E126: Ds/E | F126: TITOLARE LOW COST | G126: POSSIBILI SORPRESE | H126: 98 | I126: =IFERROR(VLOOKUP(C126,'Lista calciatori'!$B$2:$AX$549,16,FALSE),"") | J126: 6 | K126: 8 | L126: =IFERROR(VLOOKUP(C126,'Lista calciatori'!$B$2:$AX$549,49,FALSE),"") | M126: =IFERROR(VLOOKUP(C126,'Lista calciatori'!$B$2:$AX$549,30,FALSE),"") | N126: =M126-L126 | P126: =IFERROR(VLOOKUP(C126,'Lista calciatori'!$B$2:$AX$549,42,FALSE),"") | Q126: BASSO | R126: minuti a prezzo basso: utile per finanziare Pc/A | S126: https://www.sosfanta.com/guida-asta-fantacalcio/fantacalcio-mantra-ecco-la-guida-allasta-2026-27-la-divisione-ruolo-per-ruolo/
A127: Jolly | B127: 29 | C127: Maldini | D127: Cagliari | E127: T/A | F127: SCOMMESSA | G127: POSSIBILI SORPRESE | H127: 98 | I127: =IFERROR(VLOOKUP(C127,'Lista calciatori'!$B$2:$AX$549,16,FALSE),"") | J127: 6 | K127: 11 | L127: =IFERROR(VLOOKUP(C127,'Lista calciatori'!$B$2:$AX$549,49,FALSE),"") | M127: =IFERROR(VLOOKUP(C127,'Lista calciatori'!$B$2:$AX$549,30,FALSE),"") | N127: =M127-L127 | P127: =IFERROR(VLOOKUP(C127,'Lista calciatori'!$B$2:$AX$549,42,FALSE),"") | Q127: BASSO | R127: alternativa credibile per allargare il ventaglio d asta | S127: https://www.sosfanta.com/guida-asta-fantacalcio/fantacalcio-mantra-ecco-la-guida-allasta-2026-27-la-divisione-ruolo-per-ruolo/
A128: Jolly | B128: 30 | C128: Hainaut | D128: Venezia | E128: Dd/E | F128: GIOIELLINO | G128: POSSIBILI SORPRESE | H128: 98 | I128: =IFERROR(VLOOKUP(C128,'Lista calciatori'!$B$2:$AX$549,16,FALSE),"") | J128: 3 | K128: 6 | L128: =IFERROR(VLOOKUP(C128,'Lista calciatori'!$B$2:$AX$549,49,FALSE),"") | M128: =IFERROR(VLOOKUP(C128,'Lista calciatori'!$B$2:$AX$549,30,FALSE),"") | N128: =M128-L128 | P128: =IFERROR(VLOOKUP(C128,'Lista calciatori'!$B$2:$AX$549,42,FALSE),"") | Q128: BASSO | R128: upside + costo contenuto; profilo da battere presto o a fine reparto | S128: https://www.sosfanta.com/guida-asta-fantacalcio/fantacalcio-mantra-ecco-la-guida-allasta-2026-27-la-divisione-ruolo-per-ruolo/
A130: A | B130: 1 | C130: Paz N. | D130: Como | E130: T/A | F130: TOP | G130: TOP | H130: 98 | I130: =IFERROR(VLOOKUP(C130,'Lista calciatori'!$B$2:$AX$549,16,FALSE),"") | J130: 27 | K130: 124 | L130: =IFERROR(VLOOKUP(C130,'Lista calciatori'!$B$2:$AX$549,49,FALSE),"") | M130: =IFERROR(VLOOKUP(C130,'Lista calciatori'!$B$2:$AX$549,30,FALSE),"") | N130: =M130-L130 | P130: =IFERROR(VLOOKUP(C130,'Lista calciatori'!$B$2:$AX$549,42,FALSE),"") | Q130: BASSO | R130: slot strutturale: qui è accettabile usare il walk-away cap | S130: https://www.sosfanta.com/guida-asta-fantacalcio/fantacalcio-mantra-ecco-la-guida-allasta-2026-27-la-divisione-ruolo-per-ruolo/
A131: A | B131: 2 | C131: Orsolini | D131: Bologna | E131: W/A | F131: TOP | G131: TOP | H131: 98 | I131: =IFERROR(VLOOKUP(C131,'Lista calciatori'!$B$2:$AX$549,16,FALSE),"") | J131: 24 | K131: 96 | L131: =IFERROR(VLOOKUP(C131,'Lista calciatori'!$B$2:$AX$549,49,FALSE),"") | M131: =IFERROR(VLOOKUP(C131,'Lista calciatori'!$B$2:$AX$549,30,FALSE),"") | N131: =M131-L131 | P131: =IFERROR(VLOOKUP(C131,'Lista calciatori'!$B$2:$AX$549,42,FALSE),"") | Q131: BASSO | R131: slot strutturale: qui è accettabile usare il walk-away cap | S131: https://www.sosfanta.com/guida-asta-fantacalcio/fantacalcio-mantra-ecco-la-guida-allasta-2026-27-la-divisione-ruolo-per-ruolo/
... A252: Pc | B252: 30 | C252: Stulic | D252: Lecce | E252: Pc | F252: JOLLY / COPERTURA | G252: LOW COST 2ª FASCIA | H252: 51 | I252: =IFERROR(VLOOKUP(C252,'Lista calciatori'!$B$2:$AX$549,16,FALSE),"") | J252: 6 | K252: 5 | L252: =IFERROR(VLOOKUP(C252,'Lista calciatori'!$B$2:$AX$549,49,FALSE),"") | M252: =IFERROR(VLOOKUP(C252,'Lista calciatori'!$B$2:$AX$549,30,FALSE),"") | N252: =M252-L252 | P252: =IFERROR(VLOOKUP(C252,'Lista calciatori'!$B$2:$AX$549,42,FALSE),"") | Q252: BALLOTTAGGIO | R252: alternativa credibile per allargare il ventaglio d asta | S252: https://www.sosfanta.com/guida-asta-fantacalcio/fantacalcio-mantra-ecco-la-guida-allasta-2026-27-la-divisione-ruolo-per-ruolo/

Sheet Coppie & Gioielli
A1: COPPIE, COPERTURE E GIOIELLI — COME FINANZIARE I TOP
A2: La coppia non significa necessariamente “riserva secca”: è una copertura di ruolo/gerarchia che riduce il rischio e consente di investire più crediti sugli slot decisivi.
A4: COPPIE / COPERTURE DA TENERE NEL MIRINO
A5: Priorita | B5: Squadra | C5: Titolare / primo nome | D5: R.Mantra | E5: Copertura | F5: R.Mantra | G5: Tipo | H5: Budget coppia indicativo | I5: Nota | J5: Fonte
A6: ALTA | B6: Roma | C6: Wesley | D6: E | E6: Rensch | F6: B/Dd/E | G6: copertura di fascia E/Dd | H6: 28-35 | I6: copertura di fascia, non handcuff puro finché gerarchia e condizione di Rensch non sono chiarite | J6: https://www.fantacalcio.it/probabili-formazioni-serie-a
A7: ALTA | B7: Milan | C7: Bartesaghi | D7: Ds/E | E7: Estupinan | F7: Ds/E | G7: ballottaggio/copertura Ds-E | H7: 12-18 | I7: se uno resta basso di prezzo, la coppia sterilizza il ballottaggio | J7: https://www.sosfanta.com/lista-formazioni/probabili-formazioni-serie-a/
A8: ALTA | B8: Napoli | C8: Spinazzola | D8: Ds/E | E8: Olivera | F8: B/Ds/E | G8: copertura Ds-E | H8: 15-20 | I8: utile se Spinazzola viene pagato da top ma Olivera resta low | J8: https://www.sosfanta.com/guida-asta-fantacalcio/fantacalcio-mantra-ecco-la-guida-allasta-2026-27-la-divisione-ruolo-per-ruolo/
A9: MEDIA | B9: Bologna | C9: Zortea | D9: Dd/E | E9: Holm | F9: Dd/E | G9: copertura Dd-E | H9: 12-16 | I9: buon modo per non pagare una seconda fascia premium | J9: https://www.sosfanta.com/guida-asta-fantacalcio/fantacalcio-mantra-ecco-la-guida-allasta-2026-27-la-divisione-ruolo-per-ruolo/
A10: MEDIA | B10: Atalanta | C10: Zappacosta | D10: Dd/E | E10: Bellanova | F10: Dd/E | G10: rotazione Dd-E | H10: 15-22 | I10: coppia più costosa: prendila solo se il secondo scivola | J10: https://www.sosfanta.com/guida-asta-fantacalcio/fantacalcio-mantra-ecco-la-guida-allasta-2026-27-la-divisione-ruolo-per-ruolo/
A11: MEDIA | B11: Napoli | C11: Di Lorenzo | D11: Dd/E | E11: Favasuli | F11: Dd/Ds/E | G11: copertura Dd-E | H11: 22-28 | I11: top + scommessa: struttura coerente con il piano | J11: https://www.sosfanta.com/guida-asta-fantacalcio/fantacalcio-mantra-ecco-la-guida-allasta-2026-27-la-divisione-ruolo-per-ruolo/
A12: MEDIA | B12: Parma | C12: Valeri | D12: Ds/E | E12: Britschgi | F12: Dd/Ds/E | G12: copertura Ds-E | H12: 8-12 | I12: provincia + pluriruolo: profilo da asta paziente | J12: https://www.sosfanta.com/guida-asta-fantacalcio/fantacalcio-mantra-ecco-la-guida-allasta-2026-27-la-divisione-ruolo-per-ruolo/
A13: MEDIA | B13: Roma | C13: Mancini | D13: Dc | E13: Koulierakis | F13: Dc | G13: Dc top + promessa | H13: 24-30 | I13: non una riserva secca: profondità con upside | J13: https://www.sosfanta.com/guida-asta-fantacalcio/fantacalcio-mantra-ecco-la-guida-allasta-2026-27-la-divisione-ruolo-per-ruolo/
A14: BASSA | B14: Inter | C14: Bastoni | D14: Dc | E14: Bisseck | F14: Dc | G14: profondita Dc | H14: 25-35 | I14: utile solo se Bisseck non viene rilanciato | J14: https://www.sosfanta.com/guida-asta-fantacalcio/fantacalcio-mantra-ecco-la-guida-allasta-2026-27-la-divisione-ruolo-per-ruolo/
A17: PACCHETTI PORTIERI — QUI LA COPPIA/TRIS È PARTE DELLA STRATEGIA
A18: Rank | B18: Squadra | C18: Titolare | D18: Riserve | E18: Cap pacchetto | F18: Target | G18: Qualita | H18: Mossa | I18: Nota | J18: Fonte
A19: 1 | B19: Roma | C19: Svilar | D19: Gollini + De Marzi | E19: 60 | F19: 55 | G19: SUPER TOP | H19: ATTACCA FINO A 55-60 | I19: coerente con storico lega; pacchetto chiuso | J19: https://www.sosfanta.com/guida-asta-fantacalcio/guida-asta-fantacalcio-2026-2027-tutti-consigli-fasce-chi-prendere/
A20: 2 | B20: Inter | C20: Martinez Jo. | D20: Provedel + Di Gennaro | E20: 58 | F20: 52 | G20: TOP | H20: ATTACCA | I20: Provedel può costare più del classico secondo | J20: https://www.sosfanta.com/guida-asta-fantacalcio/guida-asta-fantacalcio-2026-2027-tutti-consigli-fasce-chi-prendere/
A21: 3 | B21: Milan | C21: Maignan | D21: Terracciano + Torriani | E21: 55 | F21: 52 | G21: TOP | H21: ATTACCA | I21: porta affidabile; pacchetto semplice | J21: https://www.sosfanta.com/guida-asta-fantacalcio/guida-asta-fantacalcio-2026-2027-tutti-consigli-fasce-chi-prendere/
A22: 4 | B22: Juventus | C22: Vicario | D22: Perin + Di Gregorio* | E22: 60 | F22: 52 | G22: TOP | H22: ASPETTA MERCATO | I22: Vicario titolare; se Di Gregorio resta, costo/gerarchie da ricontrollare | J22: https://www.sosfanta.com/guida-asta-fantacalcio/guida-asta-fantacalcio-2026-2027-tutti-consigli-fasce-chi-prendere/
A23: 5 | B23: Atalanta | C23: Carnesecchi | D23: Sportiello + Vismara | E23: 53 | F23: 52 | G23: TOP | H23: COMPRA A VALORE | I23: titolare molto solido | J23: https://www.sosfanta.com/guida-asta-fantacalcio/guida-asta-fantacalcio-2026-2027-tutti-consigli-fasce-chi-prendere/
A24: 6 | B24: Como | C24: Butez | D24: Tornqvist + Vigorito | E24: 53 | F24: 52 | G24: TOP | H24: COMPRA A VALORE | I24: può costare meno per minore brand | J24: https://www.sosfanta.com/guida-asta-fantacalcio/guida-asta-fantacalcio-2026-2027-tutti-consigli-fasce-chi-prendere/
A25: 7 | B25: Napoli | C25: Meret | D25: Milinkovic-Savic V. + Contini | E25: 50 | F25: 50 | G25: SEMITOP | H25: SOLO PACCHETTO | I25: gerarchia più delicata: evita di prendere un solo nome | J25: https://www.sosfanta.com/guida-asta-fantacalcio/guida-asta-fantacalcio-2026-2027-tutti-consigli-fasce-chi-prendere/
A28: GIOIELLI / LOW COST — PROFILI DA 1-20 CREDITI CHE POSSONO FINANZIARE I TOP
A29: Ruolo | B29: Nome | C29: Squadra | D29: R.Mantra | E29: Tier | F29: Tit.% | G29: Prezzo obiettivo | H29: Offerta max | I29: Perché interessa | J29: Fonte
A30: Dc | B30: Ostigard | C30: Genoa | D30: Dc | E30: SOTTO AI SEMITOP | F30: 98 | G30: 7 | H30: 8 | I30: titolare/low cost da provincia; minutaggio forte | J30: https://www.sosfanta.com/guida-asta-fantacalcio/fantacalcio-mantra-ecco-la-guida-allasta-2026-27-la-divisione-ruolo-per-ruolo/
A31: Dc | B31: Dragusin | C31: Fiorentina | D31: Dc | E31: SOTTO AI SEMITOP | F31: 98 | G31: 7 | H31: 8 | I31: titolare/low cost da provincia; minutaggio forte | J31: https://www.sosfanta.com/guida-asta-fantacalcio/fantacalcio-mantra-ecco-la-guida-allasta-2026-27-la-divisione-ruolo-per-ruolo/
A32: Jolly | B32: Fazzini | C32: Cagliari | D32: C/T | E32: POSSIBILI SORPRESE | F32: 98 | G32: 11 | H32: 13 | I32: promessa segnalata; minutaggio forte | J32: https://www.sosfanta.com/guida-asta-fantacalcio/fantacalcio-mantra-ecco-la-guida-allasta-2026-27-la-divisione-ruolo-per-ruolo/
A33: C | B33: Fitz-Jim | C33: Torino | D33: M/C | E33: POSSIBILI SORPRESE | F33: 98 | G33: 5 | H33: 6 | I33: promessa segnalata; minutaggio forte | J33: https://www.sosfanta.com/guida-asta-fantacalcio/fantacalcio-mantra-ecco-la-guida-allasta-2026-27-la-divisione-ruolo-per-ruolo/
A34: Jolly | B34: Casadei | C34: Torino | D34: C/T | E34: POSSIBILI SORPRESE | F34: 82 | G34: 12 | H34: 14 | I34: promessa segnalata | J34: https://www.sosfanta.com/guida-asta-fantacalcio/fantacalcio-mantra-ecco-la-guida-allasta-2026-27-la-divisione-ruolo-per-ruolo/
A35: Jolly | B35: Baldanzi | C35: Genoa | D35: T | E35: POSSIBILI SORPRESE | F35: 82 | G35: 8 | H35: 10 | I35: promessa segnalata | J35: https://www.sosfanta.com/guida-asta-fantacalcio/fantacalcio-mantra-ecco-la-guida-allasta-2026-27-la-divisione-ruolo-per-ruolo/
A36: Dc | B36: Tiago Gabriel | C36: Lecce | D36: Dc | E36: FASCIA ALTA | F36: 98 | G36: 7 | H36: 8 | I36: titolare/low cost da provincia; minutaggio forte | J36: https://www.sosfanta.com/guida-asta-fantacalcio/fantacalcio-mantra-ecco-la-guida-allasta-2026-27-la-divisione-ruolo-per-ruolo/
A37: Jolly | B37: Diouf | C37: Inter | D37: E/C | E37: POSSIBILI SORPRESE | F37: 82 | G37: 12 | H37: 14 | I37: promessa segnalata | J37: https://www.sosfanta.com/guida-asta-fantacalcio/fantacalcio-mantra-ecco-la-guida-allasta-2026-27-la-divisione-ruolo-per-ruolo/
A38: Dc | B38: Scalvini | C38: Atalanta | D38: Dc | E38: FASCIA ALTA | F38: 98 | G38: 7 | H38: 8 | I38: titolare/low cost da provincia; minutaggio forte | J38: https://www.sosfanta.com/guida-asta-fantacalcio/fantacalcio-mantra-ecco-la-guida-allasta-2026-27-la-divisione-ruolo-per-ruolo/
A39: Dc | B39: Mina | C39: Cagliari | D39: Dc | E39: FASCIA ALTA | F39: 94 | G39: 7 | H39: 8 | I39: titolare/low cost da provincia; minutaggio forte | J39: https://www.sosfanta.com/guida-asta-fantacalcio/fantacalcio-mantra-ecco-la-guida-allasta-2026-27-la-divisione-ruolo-per-ruolo/
A40: C | B40: Oulai | C40: Fiorentina | D40: M/C | E40: POSSIBILI SORPRESE | F40: 75 | G40: 6 | H40: 7 | I40: promessa segnalata | J40: https://www.sosfanta.com/guida-asta-fantacalcio/fantacalcio-mantra-ecco-la-guida-allasta-2026-27-la-divisione-ruolo-per-ruolo/
A41: Dd | B41: Norton-Cuffy | C41: Genoa | D41: Dd/E | E41: LOW COST 1ª FASCIA | F41: 98 | G41: 13 | H41: 15 | I41: titolare/low cost da provincia; minutaggio forte | J41: https://www.sosfanta.com/guida-asta-fantacalcio/fantacalcio-mantra-ecco-la-guida-allasta-2026-27-la-divisione-ruolo-per-ruolo/
... A69: Dd | B69: Birindelli | C69: Monza | D69: Dd/Ds/E | E69: LOW COST 1ª FASCIA | F69: 82 | G69: 7 | H69: 8 | I69: titolare/low cost da provincia | J69: https://www.sosfanta.com/guida-asta-fantacalcio/fantacalcio-mantra-ecco-la-guida-allasta-2026-27-la-divisione-ruolo-per-ruolo/

Sheet Dashboard
A1: DASHBOARD ASTA MANTRA — 4-3-3 BOMBER + GIOIELLI
A2: 12 squadre | 500 crediti | prezzi tarati sullo storico della lega | strategia: pagare davvero 1-2 stelle e finanziare con titolari value, scommesse e coppie.
A4: BUDGET | C4: A + Pc | E4: MOVIMENTO | G4: PORTIERI
A5: 500 | C5: 272 | E5: 448 | G5: 52
A7: crediti | C7: 54,4% budget | E7: target | G7: target pacchetto
A9: BUDGET PER REPARTO | F9: PRIORITA OPERATIVE
A10: Reparto | B10: Slot | C10: Target | D10: % budget | F10: 1 | G10: Pc | H10: 145 target, 160+ cap sui supertop
A11: Por | B11: 3 | C11: 52 | D11: =C11/$A$100 | F11: 2 | G11: A | H11: 1 top vero: target 65, cap 85
A12: Dd | B12: 3 | C12: 24 | D12: =C12/$A$100 | F12: 3 | G12: Portieri | H12: pacchetto top 50-60 è accettabile
A13: Ds | B13: 3 | C13: 24 | D13: =C13/$A$100 | F13: 4 | G13: C/M | H13: bonus e titolarità, ma evita guerre
A14: Dc | B14: 5 | C14: 30 | D14: =C14/$A$100 | F14: 5 | G14: Dd/Ds | H14: un premium per lato solo se finanziabile
A15: Jolly | B15: 2 | C15: 8 | D15: =C15/$A$100 | F15: 6 | G15: Dc/Jolly | H15: zona di recupero crediti e coppie
A16: A | B16: 4 | C16: 100 | D16: =C16/$A$100
A17: C | B17: 3 | C17: 48 | D17: =C17/$A$100
A18: M | B18: 3 | C18: 42 | D18: =C18/$A$100
A19: Pc | B19: 2 | C19: 172 | D19: =C19/$A$100
A21: TARGET PRINCIPALI — PROFILI SOSTENIBILI, NON CLASSIFICA ASSOLUTA
A22: Dd | B22: Kalulu / Di Lorenzo / Cambiaso | F22: cap top 35-40, ma target slot 18
A23: Ds | B23: Jimenez / Spinazzola / Cambiaso | F23: top sì, non obbligatorio pagarlo 35
A24: Dc | B24: Bremer / Bastoni / Mancini / Solet | F24: 20-23 è coerente; poi low cost
A25: A | B25: Paz / Orsolini / Pulisic / Yildiz | F25: 65-80 realistici sui top
A26: C | B26: McTominay / Atta / Da Cunha / Barella | F26: priorità ai profili offensivi
A27: M | B27: Ederson / Modric / Konè / Perrone | F27: 3 titolari, non servono 3 nomi premium
A28: Pc | B28: Malen / Lautaro / Hojlund / Ramos / Kolo | F28: bomber: 130-160 realistico
A29: Gioielli | B29: vedi foglio Coppie & Gioielli | F29: 10 slot da pochi crediti finanziano le stelle
A32: ATTENZIONE CALENDARIO
A33: Il file e aggiornato alla mattina del 28/08, ma non puo essere ancora "post mercato": la finestra Serie A chiude il 1 settembre alle 20:00. Fantacalcio ha annunciato un check finale dei ruoli Mantra il 2 settembre, solo espansivo (puo aggiungere un ruolo, non toglierlo).
A100: 500

Sheet Lista calciatori
A1: # | B1: Nome | C1: Fuori lista | D1: Sq. | E1: Under | F1: R. | G1: R.MANTRA | H1: PGv | I1: MV | J1: FM | K1: FVM (scala 500) | L1: QUOT. | M1: FantaSquadra | N1: Costo | O1: Titolarità % | P1: Classe tit. | Q1: Indice Fanta | R1: Indice Affare | S1: Fascia | T1: Mia mossa | U1: Priorità 1-5 | V1: Rischio | W1: Versatilità | X1: Tier SOS | Y1: Affidabilità | Z1: Motivo sintetico | AA1: Fonte titolarità | AB1: Fonte Mantra | AC1: Fonte update | AD1: Stato asta | AE1: Offerta max | AF1: Note asta | AG1: H_TitBase | AH1: H_TitAdj | AI1: H_SOSScore | AJ1: H_FVMpct | AK1: H_Perf | AL1: H_SeasonMatch | AM1: H_SOSMatch | AN1: H_CurrentMatch | AO1: Prezzo atteso lega 12x500 | AP1: Fit 4-3-3 | AQ1: Strategia 4-3-3 | AR1: Famiglia 4-3-3 | AS1: Tier gruppo | AT1: Fattore rischio | AU1: Moltiplicatore asta storico | AV1: Walk-away cap ruolo | AW1: Fonte prezzo | AX1: Prezzo obiettivo
A2: 5585 | B2: Malen | D2: Roma | E2: 27 | F2: A | G2: Pc | H2: 1 | I2: 8.5 | J2: 17.5 | K2: 207 | L2: 36 | O2: =MAX(0,MIN(99,AG2+AH2)) | P2: =IF(O2>=80,"Alta",IF(O2>=60,"Medio-alta",IF(O2>=40,"Media",IF(O2>=20,"Bassa","Minima")))) | Q2: =MAX(5,MIN(99,ROUND(IF(AI2>0,0.5*AI2+0.25*AJ2+0.2*O2+0.05*AK2,0.55*AJ2+0.32*O2+0.08*AK2+0.05*MIN(100,L2*4))+MIN(6,(LEN(G2)-LEN(SUBSTITUTE(G2,"/","")))*2.5)-IF(C2="*",3,0),0))) | R2: =MAX(5,MIN(99,ROUND(50+0.65*(Q2-50)+0.2*(O2-60)-0.55*(AJ2-50),0))) | S2: =IF(Q2>=90,"S",IF(Q2>=80,"A",IF(Q2>=70,"B",IF(Q2>=60,"C",IF(Q2>=48,"D","E"))))) | T2: =IF(AND(Q2>=90,O2>=62),"PUNTA FORTE",IF(AND(Q2>=80,O2>=58),"COMPRA",IF(AND(R2>=75,Q2>=62,O2>=55),"AFFARE / ATTACCA",IF(AND(Q2>=69,O2>=50),"AL GIUSTO PREZZO",IF(AND(Q2>=58,O2>=40),"JOLLY / SCOMMESSA",IF(Q2>=45,"SOLO LOW COST","EVITA")))))) | U2: 5 | V2: BASSO | W2: =LEN(G2)-LEN(SUBSTITUTE(G2,"/",""))+1 | X2: SUPER TOP | Y2: =IF(AL2+AM2+AN2>=3,"Alta",IF(AL2+AM2+AN2>=2,"Medio-alta",IF(AL2+AM2+AN2=1,"Media","Bassa"))) | Z2: XI base; SOS: super top | AA2: https://www.fantacalcio.it/news/calcio-italia/06_08_2026/asta-fantacalcio-le-probabili-formazioni-della-serie-a-enilive-2026-27-495558 | https://www.fantacalcio.it/probabili-formazioni-serie-a | AB2: https://www.sosfanta.com/guida-asta-fantacalcio/fantacalcio-mantra-ecco-la-guida-allasta-2026-27-la-divisione-ruolo-per-ruolo/ | AC2: https://www.fantacalcio.it/probabili-formazioni-serie-a | https://www.fantacalcio.it/quotazioni-fantacalcio | AD2: Da valutare | AE2: =MAX(1,MIN(AV2,ROUND(AO2*1.06,0))) | AG2: 98 | AH2: 0 | AI2: 98 | AJ2: 99.5 | AK2: 100 | AL2: 1 | AM2: 1 | AN2: 1 | AO2: =MAX(1,ROUND(L2*AU2*AT2*IF(ISNUMBER(SEARCH("SUPER TOP",X2&"")),1.08,IF(AS2="Top",1.04,IF(AS2="Semitop",1,IF(AS2="Starter",0.94,IF(AS2="Scommessa",0.9,0.85))))),0)) | AP2: =IF(AR2="Non433","BASSO",IF(OR(AR2="A",AR2="Pc"),"ALTISSIMO",IF(OR(AR2="M",AR2="C",AR2="Jolly"),"ALTO",IF(OR(AR2="Dd",AR2="Ds"),"MEDIO-ALTO","MEDIO")))) | AQ2: =IF(C2="*","EVITA - FUORI LISTA",IF(AR2="Non433","NON PRIORITARIO 4-3-3",IF(AND(OR(AR2="Pc",AR2="A"),AS2="Top"),"ALL-IN CONTROLLATO",IF(AND(AE2<=8,O2>=80),"GIOIELLO / TITOLARE LOW COST",IF(OR(AS2="Top",AS2="Semitop"),"COMPRA A VALORE",IF(O2>=80,"TITOLARE DA ASPETTARE","SOLO LOW COST")))))) | AR2: =IF(G2="Por","Por",IF(ISNUMBER(SEARCH("/Pc/","/"&G2&"/")),"Pc",IF(ISNUMBER(SEARCH("/A/","/"&G2&"/")),"A",IF(ISNUMBER(SEARCH("/M/","/"&G2&"/")),"M",IF(ISNUMBER(SEARCH("/C/","/"&G2&"/")),"C",IF(ISNUMBER(SEARCH("/Dd/","/"&G2&"/")),"Dd",IF(ISNUMBER(SEARCH("/Ds/","/"&G2&"/")),"Ds",IF(ISNUMBER(SEARCH("/Dc/","/"&G2&"/")),"Dc",IF(OR(ISNUMBER(SEARCH("/E/","/"&G2&"/")),ISNUMBER(SEARCH("/W/","/"&G2&"/")),ISNUMBER(SEARCH("/T/","/"&G2&"/")),ISNUMBER(SEARCH("/B/","/"&G2&"/"))),"Jolly","Non433"))))))))) | AS2: =IF(OR(X2="SUPER TOP",X2="TOP"),"Top",IF(X2="SEMITOP","Semitop",IF(OR(ISNUMBER(SEARCH("POSSIBILI SORPRESE",X2&"")),ISNUMBER(SEARCH("SCOMMES",X2&""))),"Scommessa",IF(OR(ISNUMBER(SEARCH("FASCIA ALTA",X2&"")),ISNUMBER(SEARCH("JOLLY 1",X2&"")),O2>=85),"Starter",IF(O2>=68,"Scommessa","Low"))))) | AT2: =IF(O2>=90,1,IF(O2>=80,0.93,IF(O2>=65,0.85,0.72)))*IF(ISNUMBER(SEARCH("MERCATO",V2&"")),0.85,1)*IF(ISNUMBER(SEARCH("INFORTUN",V2&"")),0.9,1)*IF(C2="*",0.55,1) | AU2: =IFERROR(VLOOKUP(AR2,'Strategia 433'!$A$29:$B$38,2,FALSE),0.9) | AV2: =IFERROR(INDEX('Strategia 433'!$D$15:$H$24,MATCH(AR2,'Strategia 433'!$A$15:$A$24,0),MATCH(AS2,'Strategia 433'!$D$14:$H$14,0))*IF(AND(ISNUMBER(SEARCH("SUPER TOP",X2&"")),OR(AR2="Por",AR2="Pc")),1.08,1),1) | AW2: Taratura storico lega 12x500 + QUOT Fantacalcio | https://www.fantacalcio.it/quotazioni-fantacalcio | AX2: =MAX(1,ROUND(AE2*IF(AND(AR2="Pc",AS2="Top"),0.95,IF(AND(OR(AR2="A",AR2="Por",AR2="Dc"),AS2="Top"),0.90,0.85)),0))
A3: 2764 | B3: Martinez L. | D3: Inter | E3: 29 | F3: A | G3: Pc | H3: 1 | I3: 5.5 | J3: 5 | K3: 184 | L3: 34 | O3: =MAX(0,MIN(99,AG3+AH3)) | P3: =IF(O3>=80,"Alta",IF(O3>=60,"Medio-alta",IF(O3>=40,"Media",IF(O3>=20,"Bassa","Minima")))) | Q3: =MAX(5,MIN(99,ROUND(IF(AI3>0,0.5*AI3+0.25*AJ3+0.2*O3+0.05*AK3,0.55*AJ3+0.32*O3+0.08*AK3+0.05*MIN(100,L3*4))+MIN(6,(LEN(G3)-LEN(SUBSTITUTE(G3,"/","")))*2.5)-IF(C3="*",3,0),0))) | R3: =MAX(5,MIN(99,ROUND(50+0.65*(Q3-50)+0.2*(O3-60)-0.55*(AJ3-50),0))) | S3: =IF(Q3>=90,"S",IF(Q3>=80,"A",IF(Q3>=70,"B",IF(Q3>=60,"C",IF(Q3>=48,"D","E"))))) | T3: =IF(AND(Q3>=90,O3>=62),"PUNTA FORTE",IF(AND(Q3>=80,O3>=58),"COMPRA",IF(AND(R3>=75,Q3>=62,O3>=55),"AFFARE / ATTACCA",IF(AND(Q3>=69,O3>=50),"AL GIUSTO PREZZO",IF(AND(Q3>=58,O3>=40),"JOLLY / SCOMMESSA",IF(Q3>=45,"SOLO LOW COST","EVITA")))))) | U3: 5 | V3: BASSO | W3: =LEN(G3)-LEN(SUBSTITUTE(G3,"/",""))+1 | X3: SUPER TOP | Y3: =IF(AL3+AM3+AN3>=3,"Alta",IF(AL3+AM3+AN3>=2,"Medio-alta",IF(AL3+AM3+AN3=1,"Media","Bassa"))) | Z3: XI base; SOS: super top | AA3: https://www.fantacalcio.it/news/calcio-italia/06_08_2026/asta-fantacalcio-le-probabili-formazioni-della-serie-a-enilive-2026-27-495558 | https://www.fantacalcio.it/probabili-formazioni-serie-a | AB3: https://www.sosfanta.com/guida-asta-fantacalcio/fantacalcio-mantra-ecco-la-guida-allasta-2026-27-la-divisione-ruolo-per-ruolo/ | AC3: https://www.fantacalcio.it/probabili-formazioni-serie-a | https://www.fantacalcio.it/quotazioni-fantacalcio | AD3: Da valutare | AE3: =MAX(1,MIN(AV3,ROUND(AO3*1.06,0))) | AG3: 98 | AH3: 0 | AI3: 98 | AJ3: 98.4 | AK3: 32 | AL3: 1 | AM3: 1 | AN3: 1 | AO3: =MAX(1,ROUND(L3*AU3*AT3*IF(ISNUMBER(SEARCH("SUPER TOP",X3&"")),1.08,IF(AS3="Top",1.04,IF(AS3="Semitop",1,IF(AS3="Starter",0.94,IF(AS3="Scommessa",0.9,0.85))))),0)) | AP3: =IF(AR3="Non433","BASSO",IF(OR(AR3="A",AR3="Pc"),"ALTISSIMO",IF(OR(AR3="M",AR3="C",AR3="Jolly"),"ALTO",IF(OR(AR3="Dd",AR3="Ds"),"MEDIO-ALTO","MEDIO")))) | AQ3: =IF(C3="*","EVITA - FUORI LISTA",IF(AR3="Non433","NON PRIORITARIO 4-3-3",IF(AND(OR(AR3="Pc",AR3="A"),AS3="Top"),"ALL-IN CONTROLLATO",IF(AND(AE3<=8,O3>=80),"GIOIELLO / TITOLARE LOW COST",IF(OR(AS3="Top",AS3="Semitop"),"COMPRA A VALORE",IF(O3>=80,"TITOLARE DA ASPETTARE","SOLO LOW COST")))))) | AR3: =IF(G3="Por","Por",IF(ISNUMBER(SEARCH("/Pc/","/"&G3&"/")),"Pc",IF(ISNUMBER(SEARCH("/A/","/"&G3&"/")),"A",IF(ISNUMBER(SEARCH("/M/","/"&G3&"/")),"M",IF(ISNUMBER(SEARCH("/C/","/"&G3&"/")),"C",IF(ISNUMBER(SEARCH("/Dd/","/"&G3&"/")),"Dd",IF(ISNUMBER(SEARCH("/Ds/","/"&G3&"/")),"Ds",IF(ISNUMBER(SEARCH("/Dc/","/"&G3&"/")),"Dc",IF(OR(ISNUMBER(SEARCH("/E/","/"&G3&"/")),ISNUMBER(SEARCH("/W/","/"&G3&"/")),ISNUMBER(SEARCH("/T/","/"&G3&"/")),ISNUMBER(SEARCH("/B/","/"&G3&"/"))),"Jolly","Non433"))))))))) | AS3: =IF(OR(X3="SUPER TOP",X3="TOP"),"Top",IF(X3="SEMITOP","Semitop",IF(OR(ISNUMBER(SEARCH("POSSIBILI SORPRESE",X3&"")),ISNUMBER(SEARCH("SCOMMES",X3&""))),"Scommessa",IF(OR(ISNUMBER(SEARCH("FASCIA ALTA",X3&"")),ISNUMBER(SEARCH("JOLLY 1",X3&"")),O3>=85),"Starter",IF(O3>=68,"Scommessa","Low"))))) | AT3: =IF(O3>=90,1,IF(O3>=80,0.93,IF(O3>=65,0.85,0.72)))*IF(ISNUMBER(SEARCH("MERCATO",V3&"")),0.85,1)*IF(ISNUMBER(SEARCH("INFORTUN",V3&"")),0.9,1)*IF(C3="*",0.55,1) | AU3: =IFERROR(VLOOKUP(AR3,'Strategia 433'!$A$29:$B$38,2,FALSE),0.9) | AV3: =IFERROR(INDEX('Strategia 433'!$D$15:$H$24,MATCH(AR3,'Strategia 433'!$A$15:$A$24,0),MATCH(AS3,'Strategia 433'!$D$14:$H$14,0))*IF(AND(ISNUMBER(SEARCH("SUPER TOP",X3&"")),OR(AR3="Por",AR3="Pc")),1.08,1),1) | AW3: Taratura storico lega 12x500 + QUOT Fantacalcio | https://www.fantacalcio.it/quotazioni-fantacalcio | AX3: =MAX(1,ROUND(AE3*IF(AND(AR3="Pc",AS3="Top"),0.95,IF(AND(OR(AR3="A",AR3="Por",AR3="Dc"),AS3="Top"),0.90,0.85)),0))
A4: 2194 | B4: Calhanoglu | D4: Inter | E4: 32 | F4: C | G4: M/C | H4: 1 | I4: 7 | J4: 9.5 | K4: 133 | L4: 29 | O4: =MAX(0,MIN(99,AG4+AH4)) | P4: =IF(O4>=80,"Alta",IF(O4>=60,"Medio-alta",IF(O4>=40,"Media",IF(O4>=20,"Bassa","Minima")))) | Q4: =MAX(5,MIN(99,ROUND(IF(AI4>0,0.5*AI4+0.25*AJ4+0.2*O4+0.05*AK4,0.55*AJ4+0.32*O4+0.08*AK4+0.05*MIN(100,L4*4))+MIN(6,(LEN(G4)-LEN(SUBSTITUTE(G4,"/","")))*2.5)-IF(C4="*",3,0),0))) | R4: =MAX(5,MIN(99,ROUND(50+0.65*(Q4-50)+0.2*(O4-60)-0.55*(AJ4-50),0))) | S4: =IF(Q4>=90,"S",IF(Q4>=80,"A",IF(Q4>=70,"B",IF(Q4>=60,"C",IF(Q4>=48,"D","E"))))) | T4: =IF(AND(Q4>=90,O4>=62),"PUNTA FORTE",IF(AND(Q4>=80,O4>=58),"COMPRA",IF(AND(R4>=75,Q4>=62,O4>=55),"AFFARE / ATTACCA",IF(AND(Q4>=69,O4>=50),"AL GIUSTO PREZZO",IF(AND(Q4>=58,O4>=40),"JOLLY / SCOMMESSA",IF(Q4>=45,"SOLO LOW COST","EVITA")))))) | U4: 5 | V4: BASSO | W4: =LEN(G4)-LEN(SUBSTITUTE(G4,"/",""))+1 | X4: SUPER TOP | Y4: =IF(AL4+AM4+AN4>=3,"Alta",IF(AL4+AM4+AN4>=2,"Medio-alta",IF(AL4+AM4+AN4=1,"Media","Bassa"))) | Z4: XI base; SOS: super top; pluriruolo | AA4: https://www.fantacalcio.it/news/calcio-italia/06_08_2026/asta-fantacalcio-le-probabili-formazioni-della-serie-a-enilive-2026-27-495558 | https://www.fantacalcio.it/probabili-formazioni-serie-a | AB4: https://www.sosfanta.com/guida-asta-fantacalcio/fantacalcio-mantra-ecco-la-guida-allasta-2026-27-la-divisione-ruolo-per-ruolo/ | AC4: https://www.fantacalcio.it/probabili-formazioni-serie-a | https://www.fantacalcio.it/quotazioni-fantacalcio | AD4: Da valutare | AE4: =MAX(1,MIN(AV4,ROUND(AO4*1.06,0))) | AG4: 98 | AH4: 0 | AI4: 98 | AJ4: 99.7 | AK4: 100 | AL4: 1 | AM4: 1 | AN4: 1 | AO4: =MAX(1,ROUND(L4*AU4*AT4*IF(ISNUMBER(SEARCH("SUPER TOP",X4&"")),1.08,IF(AS4="Top",1.04,IF(AS4="Semitop",1,IF(AS4="Starter",0.94,IF(AS4="Scommessa",0.9,0.85))))),0)) | AP4: =IF(AR4="Non433","BASSO",IF(OR(AR4="A",AR4="Pc"),"ALTISSIMO",IF(OR(AR4="M",AR4="C",AR4="Jolly"),"ALTO",IF(OR(AR4="Dd",AR4="Ds"),"MEDIO-ALTO","MEDIO")))) | AQ4: =IF(C4="*","EVITA - FUORI LISTA",IF(AR4="Non433","NON PRIORITARIO 4-3-3",IF(AND(OR(AR4="Pc",AR4="A"),AS4="Top"),"ALL-IN CONTROLLATO",IF(AND(AE4<=8,O4>=80),"GIOIELLO / TITOLARE LOW COST",IF(OR(AS4="Top",AS4="Semitop"),"COMPRA A VALORE",IF(O4>=80,"TITOLARE DA ASPETTARE","SOLO LOW COST")))))) | AR4: =IF(G4="Por","Por",IF(ISNUMBER(SEARCH("/Pc/","/"&G4&"/")),"Pc",IF(ISNUMBER(SEARCH("/A/","/"&G4&"/")),"A",IF(ISNUMBER(SEARCH("/M/","/"&G4&"/")),"M",IF(ISNUMBER(SEARCH("/C/","/"&G4&"/")),"C",IF(ISNUMBER(SEARCH("/Dd/","/"&G4&"/")),"Dd",IF(ISNUMBER(SEARCH("/Ds/","/"&G4&"/")),"Ds",IF(ISNUMBER(SEARCH("/Dc/","/"&G4&"/")),"Dc",IF(OR(ISNUMBER(SEARCH("/E/","/"&G4&"/")),ISNUMBER(SEARCH("/W/","/"&G4&"/")),ISNUMBER(SEARCH("/T/","/"&G4&"/")),ISNUMBER(SEARCH("/B/","/"&G4&"/"))),"Jolly","Non433"))))))))) | AS4: =IF(OR(X4="SUPER TOP",X4="TOP"),"Top",IF(X4="SEMITOP","Semitop",IF(OR(ISNUMBER(SEARCH("POSSIBILI SORPRESE",X4&"")),ISNUMBER(SEARCH("SCOMMES",X4&""))),"Scommessa",IF(OR(ISNUMBER(SEARCH("FASCIA ALTA",X4&"")),ISNUMBER(SEARCH("JOLLY 1",X4&"")),O4>=85),"Starter",IF(O4>=68,"Scommessa","Low"))))) | AT4: =IF(O4>=90,1,IF(O4>=80,0.93,IF(O4>=65,0.85,0.72)))*IF(ISNUMBER(SEARCH("MERCATO",V4&"")),0.85,1)*IF(ISNUMBER(SEARCH("INFORTUN",V4&"")),0.9,1)*IF(C4="*",0.55,1) | AU4: =IFERROR(VLOOKUP(AR4,'Strategia 433'!$A$29:$B$38,2,FALSE),0.9) | AV4: =IFERROR(INDEX('Strategia 433'!$D$15:$H$24,MATCH(AR4,'Strategia 433'!$A$15:$A$24,0),MATCH(AS4,'Strategia 433'!$D$14:$H$14,0))*IF(AND(ISNUMBER(SEARCH("SUPER TOP",X4&"")),OR(AR4="Por",AR4="Pc")),1.08,1),1) | AW4: Taratura storico lega 12x500 + QUOT Fantacalcio | https://www.fantacalcio.it/quotazioni-fantacalcio | AX4: =MAX(1,ROUND(AE4*IF(AND(AR4="Pc",AS4="Top"),0.95,IF(AND(OR(AR4="A",AR4="Por",AR4="Dc"),AS4="Top"),0.90,0.85)),0))
A5: 4871 | B5: Thuram | D5: Inter | E5: 29 | F5: A | G5: Pc | H5: 0 | I5: 0 | J5: 0 | K5: 132 | L5: 28 | O5: =MAX(0,MIN(99,AG5+AH5)) | P5: =IF(O5>=80,"Alta",IF(O5>=60,"Medio-alta",IF(O5>=40,"Media",IF(O5>=20,"Bassa","Minima")))) | Q5: =MAX(5,MIN(99,ROUND(IF(AI5>0,0.5*AI5+0.25*AJ5+0.2*O5+0.05*AK5,0.55*AJ5+0.32*O5+0.08*AK5+0.05*MIN(100,L5*4))+MIN(6,(LEN(G5)-LEN(SUBSTITUTE(G5,"/","")))*2.5)-IF(C5="*",3,0),0))) | R5: =MAX(5,MIN(99,ROUND(50+0.65*(Q5-50)+0.2*(O5-60)-0.55*(AJ5-50),0))) | S5: =IF(Q5>=90,"S",IF(Q5>=80,"A",IF(Q5>=70,"B",IF(Q5>=60,"C",IF(Q5>=48,"D","E"))))) | T5: =IF(AND(Q5>=90,O5>=62),"PUNTA FORTE",IF(AND(Q5>=80,O5>=58),"COMPRA",IF(AND(R5>=75,Q5>=62,O5>=55),"AFFARE / ATTACCA",IF(AND(Q5>=69,O5>=50),"AL GIUSTO PREZZO",IF(AND(Q5>=58,O5>=40),"JOLLY / SCOMMESSA",IF(Q5>=45,"SOLO LOW COST","EVITA")))))) | U5: 4 | V5: BALLOTTAGGIO | W5: =LEN(G5)-LEN(SUBSTITUTE(G5,"/",""))+1 | X5: TOP | Y5: =IF(AL5+AM5+AN5>=3,"Alta",IF(AL5+AM5+AN5>=2,"Medio-alta",IF(AL5+AM5+AN5=1,"Media","Bassa"))) | Z5: XI base; ballottaggio; SOS: top | AA5: https://www.fantacalcio.it/news/calcio-italia/06_08_2026/asta-fantacalcio-le-probabili-formazioni-della-serie-a-enilive-2026-27-495558 | https://www.fantacalcio.it/probabili-formazioni-serie-a | AB5: https://www.sosfanta.com/guida-asta-fantacalcio/fantacalcio-mantra-ecco-la-guida-allasta-2026-27-la-divisione-ruolo-per-ruolo/ | AC5: https://www.fantacalcio.it/probabili-formazioni-serie-a | https://www.fantacalcio.it/quotazioni-fantacalcio | AD5: Da valutare | AE5: =MAX(1,MIN(AV5,ROUND(AO5*1.06,0))) | AG5: 71 | AH5: 0 | AI5: 90 | AJ5: 97.3 | AK5: 50 | AL5: 1 | AM5: 1 | AN5: 0 | AO5: =MAX(1,ROUND(L5*AU5*AT5*IF(ISNUMBER(SEARCH("SUPER TOP",X5&"")),1.08,IF(AS5="Top",1.04,IF(AS5="Semitop",1,IF(AS5="Starter",0.94,IF(AS5="Scommessa",0.9,0.85))))),0)) | AP5: =IF(AR5="Non433","BASSO",IF(OR(AR5="A",AR5="Pc"),"ALTISSIMO",IF(OR(AR5="M",AR5="C",AR5="Jolly"),"ALTO",IF(OR(AR5="Dd",AR5="Ds"),"MEDIO-ALTO","MEDIO")))) | AQ5: =IF(C5="*","EVITA - FUORI LISTA",IF(AR5="Non433","NON PRIORITARIO 4-3-3",IF(AND(OR(AR5="Pc",AR5="A"),AS5="Top"),"ALL-IN CONTROLLATO",IF(AND(AE5<=8,O5>=80),"GIOIELLO / TITOLARE LOW COST",IF(OR(AS5="Top",AS5="Semitop"),"COMPRA A VALORE",IF(O5>=80,"TITOLARE DA ASPETTARE","SOLO LOW COST")))))) | AR5: =IF(G5="Por","Por",IF(ISNUMBER(SEARCH("/Pc/","/"&G5&"/")),"Pc",IF(ISNUMBER(SEARCH("/A/","/"&G5&"/")),"A",IF(ISNUMBER(SEARCH("/M/","/"&G5&"/")),"M",IF(ISNUMBER(SEARCH("/C/","/"&G5&"/")),"C",IF(ISNUMBER(SEARCH("/Dd/","/"&G5&"/")),"Dd",IF(ISNUMBER(SEARCH("/Ds/","/"&G5&"/")),"Ds",IF(ISNUMBER(SEARCH("/Dc/","/"&G5&"/")),"Dc",IF(OR(ISNUMBER(SEARCH("/E/","/"&G5&"/")),ISNUMBER(SEARCH("/W/","/"&G5&"/")),ISNUMBER(SEARCH("/T/","/"&G5&"/")),ISNUMBER(SEARCH("/B/","/"&G5&"/"))),"Jolly","Non433"))))))))) | AS5: =IF(OR(X5="SUPER TOP",X5="TOP"),"Top",IF(X5="SEMITOP","Semitop",IF(OR(ISNUMBER(SEARCH("POSSIBILI SORPRESE",X5&"")),ISNUMBER(SEARCH("SCOMMES",X5&""))),"Scommessa",IF(OR(ISNUMBER(SEARCH("FASCIA ALTA",X5&"")),ISNUMBER(SEARCH("JOLLY 1",X5&"")),O5>=85),"Starter",IF(O5>=68,"Scommessa","Low"))))) | AT5: =IF(O5>=90,1,IF(O5>=80,0.93,IF(O5>=65,0.85,0.72)))*IF(ISNUMBER(SEARCH("MERCATO",V5&"")),0.85,1)*IF(ISNUMBER(SEARCH("INFORTUN",V5&"")),0.9,1)*IF(C5="*",0.55,1) | AU5: =IFERROR(VLOOKUP(AR5,'Strategia 433'!$A$29:$B$38,2,FALSE),0.9) | AV5: =IFERROR(INDEX('Strategia 433'!$D$15:$H$24,MATCH(AR5,'Strategia 433'!$A$15:$A$24,0),MATCH(AS5,'Strategia 433'!$D$14:$H$14,0))*IF(AND(ISNUMBER(SEARCH("SUPER TOP",X5&"")),OR(AR5="Por",AR5="Pc")),1.08,1),1) | AW5: Taratura storico lega 12x500 + QUOT Fantacalcio | https://www.fantacalcio.it/quotazioni-fantacalcio | AX5: =MAX(1,ROUND(AE5*IF(AND(AR5="Pc",AS5="Top"),0.95,IF(AND(OR(AR5="A",AR5="Por",AR5="Dc"),AS5="Top"),0.90,0.85)),0))
A6: 6052 | B6: Hojlund | D6: Napoli | E6: 23 | F6: A | G6: Pc | H6: 1 | I6: 5.5 | J6: 5.5 | K6: 129 | L6: 27 | O6: =MAX(0,MIN(99,AG6+AH6)) | P6: =IF(O6>=80,"Alta",IF(O6>=60,"Medio-alta",IF(O6>=40,"Media",IF(O6>=20,"Bassa","Minima")))) | Q6: =MAX(5,MIN(99,ROUND(IF(AI6>0,0.5*AI6+0.25*AJ6+0.2*O6+0.05*AK6,0.55*AJ6+0.32*O6+0.08*AK6+0.05*MIN(100,L6*4))+MIN(6,(LEN(G6)-LEN(SUBSTITUTE(G6,"/","")))*2.5)-IF(C6="*",3,0),0))) | R6: =MAX(5,MIN(99,ROUND(50+0.65*(Q6-50)+0.2*(O6-60)-0.55*(AJ6-50),0))) | S6: =IF(Q6>=90,"S",IF(Q6>=80,"A",IF(Q6>=70,"B",IF(Q6>=60,"C",IF(Q6>=48,"D","E"))))) | T6: =IF(AND(Q6>=90,O6>=62),"PUNTA FORTE",IF(AND(Q6>=80,O6>=58),"COMPRA",IF(AND(R6>=75,Q6>=62,O6>=55),"AFFARE / ATTACCA",IF(AND(Q6>=69,O6>=50),"AL GIUSTO PREZZO",IF(AND(Q6>=58,O6>=40),"JOLLY / SCOMMESSA",IF(Q6>=45,"SOLO LOW COST","EVITA")))))) | U6: 5 | V6: BASSO | W6: =LEN(G6)-LEN(SUBSTITUTE(G6,"/",""))+1 | X6: TOP | Y6: =IF(AL6+AM6+AN6>=3,"Alta",IF(AL6+AM6+AN6>=2,"Medio-alta",IF(AL6+AM6+AN6=1,"Media","Bassa"))) | Z6: XI base; SOS: top | AA6: https://www.fantacalcio.it/news/calcio-italia/06_08_2026/asta-fantacalcio-le-probabili-formazioni-della-serie-a-enilive-2026-27-495558 | https://www.fantacalcio.it/probabili-formazioni-serie-a | AB6: https://www.sosfanta.com/guida-asta-fantacalcio/fantacalcio-mantra-ecco-la-guida-allasta-2026-27-la-divisione-ruolo-per-ruolo/ | AC6: https://www.fantacalcio.it/probabili-formazioni-serie-a | https://www.fantacalcio.it/quotazioni-fantacalcio | AD6: Da valutare | AE6: =MAX(1,MIN(AV6,ROUND(AO6*1.06,0))) | AG6: 98 | AH6: 0 | AI6: 90 | AJ6: 96.3 | AK6: 41 | AL6: 1 | AM6: 1 | AN6: 1 | AO6: =MAX(1,ROUND(L6*AU6*AT6*IF(ISNUMBER(SEARCH("SUPER TOP",X6&"")),1.08,IF(AS6="Top",1.04,IF(AS6="Semitop",1,IF(AS6="Starter",0.94,IF(AS6="Scommessa",0.9,0.85))))),0)) | AP6: =IF(AR6="Non433","BASSO",IF(OR(AR6="A",AR6="Pc"),"ALTISSIMO",IF(OR(AR6="M",AR6="C",AR6="Jolly"),"ALTO",IF(OR(AR6="Dd",AR6="Ds"),"MEDIO-ALTO","MEDIO")))) | AQ6: =IF(C6="*","EVITA - FUORI LISTA",IF(AR6="Non433","NON PRIORITARIO 4-3-3",IF(AND(OR(AR6="Pc",AR6="A"),AS6="Top"),"ALL-IN CONTROLLATO",IF(AND(AE6<=8,O6>=80),"GIOIELLO / TITOLARE LOW COST",IF(OR(AS6="Top",AS6="Semitop"),"COMPRA A VALORE",IF(O6>=80,"TITOLARE DA ASPETTARE","SOLO LOW COST")))))) | AR6: =IF(G6="Por","Por",IF(ISNUMBER(SEARCH("/Pc/","/"&G6&"/")),"Pc",IF(ISNUMBER(SEARCH("/A/","/"&G6&"/")),"A",IF(ISNUMBER(SEARCH("/M/","/"&G6&"/")),"M",IF(ISNUMBER(SEARCH("/C/","/"&G6&"/")),"C",IF(ISNUMBER(SEARCH("/Dd/","/"&G6&"/")),"Dd",IF(ISNUMBER(SEARCH("/Ds/","/"&G6&"/")),"Ds",IF(ISNUMBER(SEARCH("/Dc/","/"&G6&"/")),"Dc",IF(OR(ISNUMBER(SEARCH("/E/","/"&G6&"/")),ISNUMBER(SEARCH("/W/","/"&G6&"/")),ISNUMBER(SEARCH("/T/","/"&G6&"/")),ISNUMBER(SEARCH("/B/","/"&G6&"/"))),"Jolly","Non433"))))))))) | AS6: =IF(OR(X6="SUPER TOP",X6="TOP"),"Top",IF(X6="SEMITOP","Semitop",IF(OR(ISNUMBER(SEARCH("POSSIBILI SORPRESE",X6&"")),ISNUMBER(SEARCH("SCOMMES",X6&""))),"Scommessa",IF(OR(ISNUMBER(SEARCH("FASCIA ALTA",X6&"")),ISNUMBER(SEARCH("JOLLY 1",X6&"")),O6>=85),"Starter",IF(O6>=68,"Scommessa","Low"))))) | AT6: =IF(O6>=90,1,IF(O6>=80,0.93,IF(O6>=65,0.85,0.72)))*IF(ISNUMBER(SEARCH("MERCATO",V6&"")),0.85,1)*IF(ISNUMBER(SEARCH("INFORTUN",V6&"")),0.9,1)*IF(C6="*",0.55,1) | AU6: =IFERROR(VLOOKUP(AR6,'Strategia 433'!$A$29:$B$38,2,FALSE),0.9) | AV6: =IFERROR(INDEX('Strategia 433'!$D$15:$H$24,MATCH(AR6,'Strategia 433'!$A$15:$A$24,0),MATCH(AS6,'Strategia 433'!$D$14:$H$14,0))*IF(AND(ISNUMBER(SEARCH("SUPER TOP",X6&"")),OR(AR6="Por",AR6="Pc")),1.08,1),1) | AW6: Taratura storico lega 12x500 + QUOT Fantacalcio | https://www.fantacalcio.it/quotazioni-fantacalcio | AX6: =MAX(1,ROUND(AE6*IF(AND(AR6="Pc",AS6="Top"),0.95,IF(AND(OR(AR6="A",AR6="Por",AR6="Dc"),AS6="Top"),0.90,0.85)),0))
A7: 254 | B7: Dimarco | D7: Inter | E7: 29 | F7: D | G7: E/W | H7: 1 | I7: 6 | J7: 6 | K7: 127 | L7: 30 | O7: =MAX(0,MIN(99,AG7+AH7)) | P7: =IF(O7>=80,"Alta",IF(O7>=60,"Medio-alta",IF(O7>=40,"Media",IF(O7>=20,"Bassa","Minima")))) | Q7: =MAX(5,MIN(99,ROUND(IF(AI7>0,0.5*AI7+0.25*AJ7+0.2*O7+0.05*AK7,0.55*AJ7+0.32*O7+0.08*AK7+0.05*MIN(100,L7*4))+MIN(6,(LEN(G7)-LEN(SUBSTITUTE(G7,"/","")))*2.5)-IF(C7="*",3,0),0))) | R7: =MAX(5,MIN(99,ROUND(50+0.65*(Q7-50)+0.2*(O7-60)-0.55*(AJ7-50),0))) | S7: =IF(Q7>=90,"S",IF(Q7>=80,"A",IF(Q7>=70,"B",IF(Q7>=60,"C",IF(Q7>=48,"D","E"))))) | T7: =IF(AND(Q7>=90,O7>=62),"PUNTA FORTE",IF(AND(Q7>=80,O7>=58),"COMPRA",IF(AND(R7>=75,Q7>=62,O7>=55),"AFFARE / ATTACCA",IF(AND(Q7>=69,O7>=50),"AL GIUSTO PREZZO",IF(AND(Q7>=58,O7>=40),"JOLLY / SCOMMESSA",IF(Q7>=45,"SOLO LOW COST","EVITA")))))) | U7: 5 | V7: BASSO | W7: =LEN(G7)-LEN(SUBSTITUTE(G7,"/",""))+1 | X7: SUPER TOP | Y7: =IF(AL7+AM7+AN7>=3,"Alta",IF(AL7+AM7+AN7>=2,"Medio-alta",IF(AL7+AM7+AN7=1,"Media","Bassa"))) | Z7: XI base; SOS: super top; pluriruolo | AA7: https://www.fantacalcio.it/news/calcio-italia/06_08_2026/asta-fantacalcio-le-probabili-formazioni-della-serie-a-enilive-2026-27-495558 | https://www.fantacalcio.it/probabili-formazioni-serie-a | AB7: https://www.sosfanta.com/guida-asta-fantacalcio/fantacalcio-mantra-ecco-la-guida-allasta-2026-27-la-divisione-ruolo-per-ruolo/ | AC7: https://www.fantacalcio.it/probabili-formazioni-serie-a | https://www.fantacalcio.it/quotazioni-fantacalcio | AD7: Da valutare | AE7: =MAX(1,MIN(AV7,ROUND(AO7*1.06,0))) | AG7: 98 | AH7: 0 | AI7: 98 | AJ7: 99.7 | AK7: 50 | AL7: 1 | AM7: 1 | AN7: 1 | AO7: =MAX(1,ROUND(L7*AU7*AT7*IF(ISNUMBER(SEARCH("SUPER TOP",X7&"")),1.08,IF(AS7="Top",1.04,IF(AS7="Semitop",1,IF(AS7="Starter",0.94,IF(AS7="Scommessa",0.9,0.85))))),0)) | AP7: =IF(AR7="Non433","BASSO",IF(OR(AR7="A",AR7="Pc"),"ALTISSIMO",IF(OR(AR7="M",AR7="C",AR7="Jolly"),"ALTO",IF(OR(AR7="Dd",AR7="Ds"),"MEDIO-ALTO","MEDIO")))) | AQ7: =IF(C7="*","EVITA - FUORI LISTA",IF(AR7="Non433","NON PRIORITARIO 4-3-3",IF(AND(OR(AR7="Pc",AR7="A"),AS7="Top"),"ALL-IN CONTROLLATO",IF(AND(AE7<=8,O7>=80),"GIOIELLO / TITOLARE LOW COST",IF(OR(AS7="Top",AS7="Semitop"),"COMPRA A VALORE",IF(O7>=80,"TITOLARE DA ASPETTARE","SOLO LOW COST")))))) | AR7: =IF(G7="Por","Por",IF(ISNUMBER(SEARCH("/Pc/","/"&G7&"/")),"Pc",IF(ISNUMBER(SEARCH("/A/","/"&G7&"/")),"A",IF(ISNUMBER(SEARCH("/M/","/"&G7&"/")),"M",IF(ISNUMBER(SEARCH("/C/","/"&G7&"/")),"C",IF(ISNUMBER(SEARCH("/Dd/","/"&G7&"/")),"Dd",IF(ISNUMBER(SEARCH("/Ds/","/"&G7&"/")),"Ds",IF(ISNUMBER(SEARCH("/Dc/","/"&G7&"/")),"Dc",IF(OR(ISNUMBER(SEARCH("/E/","/"&G7&"/")),ISNUMBER(SEARCH("/W/","/"&G7&"/")),ISNUMBER(SEARCH("/T/","/"&G7&"/")),ISNUMBER(SEARCH("/B/","/"&G7&"/"))),"Jolly","Non433"))))))))) | AS7: =IF(OR(X7="SUPER TOP",X7="TOP"),"Top",IF(X7="SEMITOP","Semitop",IF(OR(ISNUMBER(SEARCH("POSSIBILI SORPRESE",X7&"")),ISNUMBER(SEARCH("SCOMMES",X7&""))),"Scommessa",IF(OR(ISNUMBER(SEARCH("FASCIA ALTA",X7&"")),ISNUMBER(SEARCH("JOLLY 1",X7&"")),O7>=85),"Starter",IF(O7>=68,"Scommessa","Low"))))) | AT7: =IF(O7>=90,1,IF(O7>=80,0.93,IF(O7>=65,0.85,0.72)))*IF(ISNUMBER(SEARCH("MERCATO",V7&"")),0.85,1)*IF(ISNUMBER(SEARCH("INFORTUN",V7&"")),0.9,1)*IF(C7="*",0.55,1) | AU7: =IFERROR(VLOOKUP(AR7,'Strategia 433'!$A$29:$B$38,2,FALSE),0.9) | AV7: =IFERROR(INDEX('Strategia 433'!$D$15:$H$24,MATCH(AR7,'Strategia 433'!$A$15:$A$24,0),MATCH(AS7,'Strategia 433'!$D$14:$H$14,0))*IF(AND(ISNUMBER(SEARCH("SUPER TOP",X7&"")),OR(AR7="Por",AR7="Pc")),1.08,1),1) | AW7: Taratura storico lega 12x500 + QUOT Fantacalcio | https://www.fantacalcio.it/quotazioni-fantacalcio | AX7: =MAX(1,ROUND(AE7*IF(AND(AR7="Pc",AS7="Top"),0.95,IF(AND(OR(AR7="A",AR7="Por",AR7="Dc"),AS7="Top"),0.90,0.85)),0))
A8: 6875 | B8: Paz N. | D8: Como | E8: 22 | F8: C | G8: T/A | H8: 1 | I8: 5.5 | J8: 5.5 | K8: 124 | L8: 27 | O8: =MAX(0,MIN(99,AG8+AH8)) | P8: =IF(O8>=80,"Alta",IF(O8>=60,"Medio-alta",IF(O8>=40,"Media",IF(O8>=20,"Bassa","Minima")))) | Q8: =MAX(5,MIN(99,ROUND(IF(AI8>0,0.5*AI8+0.25*AJ8+0.2*O8+0.05*AK8,0.55*AJ8+0.32*O8+0.08*AK8+0.05*MIN(100,L8*4))+MIN(6,(LEN(G8)-LEN(SUBSTITUTE(G8,"/","")))*2.5)-IF(C8="*",3,0),0))) | R8: =MAX(5,MIN(99,ROUND(50+0.65*(Q8-50)+0.2*(O8-60)-0.55*(AJ8-50),0))) | S8: =IF(Q8>=90,"S",IF(Q8>=80,"A",IF(Q8>=70,"B",IF(Q8>=60,"C",IF(Q8>=48,"D","E"))))) | T8: =IF(AND(Q8>=90,O8>=62),"PUNTA FORTE",IF(AND(Q8>=80,O8>=58),"COMPRA",IF(AND(R8>=75,Q8>=62,O8>=55),"AFFARE / ATTACCA",IF(AND(Q8>=69,O8>=50),"AL GIUSTO PREZZO",IF(AND(Q8>=58,O8>=40),"JOLLY / SCOMMESSA",IF(Q8>=45,"SOLO LOW COST","EVITA")))))) | U8: 5 | V8: BASSO | W8: =LEN(G8)-LEN(SUBSTITUTE(G8,"/",""))+1 | X8: TOP | Y8: =IF(AL8+AM8+AN8>=3,"Alta",IF(AL8+AM8+AN8>=2,"Medio-alta",IF(AL8+AM8+AN8=1,"Media","Bassa"))) | Z8: XI base; SOS: super top; pluriruolo | AA8: https://www.fantacalcio.it/news/calcio-italia/06_08_2026/asta-fantacalcio-le-probabili-formazioni-della-serie-a-enilive-2026-27-495558 | https://www.fantacalcio.it/probabili-formazioni-serie-a | AB8: https://www.sosfanta.com/guida-asta-fantacalcio/fantacalcio-mantra-ecco-la-guida-allasta-2026-27-la-divisione-ruolo-per-ruolo/ | AC8: https://www.fantacalcio.it/probabili-formazioni-serie-a | https://www.fantacalcio.it/quotazioni-fantacalcio | AD8: Da valutare | AE8: =MAX(1,MIN(AV8,ROUND(AO8*1.06,0))) | AG8: 98 | AH8: 0 | AI8: 98 | AJ8: 99.2 | AK8: 41 | AL8: 1 | AM8: 1 | AN8: 1 | AO8: =MAX(1,ROUND(L8*AU8*AT8*IF(ISNUMBER(SEARCH("SUPER TOP",X8&"")),1.08,IF(AS8="Top",1.04,IF(AS8="Semitop",1,IF(AS8="Starter",0.94,IF(AS8="Scommessa",0.9,0.85))))),0)) | AP8: =IF(AR8="Non433","BASSO",IF(OR(AR8="A",AR8="Pc"),"ALTISSIMO",IF(OR(AR8="M",AR8="C",AR8="Jolly"),"ALTO",IF(OR(AR8="Dd",AR8="Ds"),"MEDIO-ALTO","MEDIO")))) | AQ8: =IF(C8="*","EVITA - FUORI LISTA",IF(AR8="Non433","NON PRIORITARIO 4-3-3",IF(AND(OR(AR8="Pc",AR8="A"),AS8="Top"),"ALL-IN CONTROLLATO",IF(AND(AE8<=8,O8>=80),"GIOIELLO / TITOLARE LOW COST",IF(OR(AS8="Top",AS8="Semitop"),"COMPRA A VALORE",IF(O8>=80,"TITOLARE DA ASPETTARE","SOLO LOW COST")))))) | AR8: =IF(G8="Por","Por",IF(ISNUMBER(SEARCH("/Pc/","/"&G8&"/")),"Pc",IF(ISNUMBER(SEARCH("/A/","/"&G8&"/")),"A",IF(ISNUMBER(SEARCH("/M/","/"&G8&"/")),"M",IF(ISNUMBER(SEARCH("/C/","/"&G8&"/")),"C",IF(ISNUMBER(SEARCH("/Dd/","/"&G8&"/")),"Dd",IF(ISNUMBER(SEARCH("/Ds/","/"&G8&"/")),"Ds",IF(ISNUMBER(SEARCH("/Dc/","/"&G8&"/")),"Dc",IF(OR(ISNUMBER(SEARCH("/E/","/"&G8&"/")),ISNUMBER(SEARCH("/W/","/"&G8&"/")),ISNUMBER(SEARCH("/T/","/"&G8&"/")),ISNUMBER(SEARCH("/B/","/"&G8&"/"))),"Jolly","Non433"))))))))) | AS8: =IF(OR(X8="SUPER TOP",X8="TOP"),"Top",IF(X8="SEMITOP","Semitop",IF(OR(ISNUMBER(SEARCH("POSSIBILI SORPRESE",X8&"")),ISNUMBER(SEARCH("SCOMMES",X8&""))),"Scommessa",IF(OR(ISNUMBER(SEARCH("FASCIA ALTA",X8&"")),ISNUMBER(SEARCH("JOLLY 1",X8&"")),O8>=85),"Starter",IF(O8>=68,"Scommessa","Low"))))) | AT8: =IF(O8>=90,1,IF(O8>=80,0.93,IF(O8>=65,0.85,0.72)))*IF(ISNUMBER(SEARCH("MERCATO",V8&"")),0.85,1)*IF(ISNUMBER(SEARCH("INFORTUN",V8&"")),0.9,1)*IF(C8="*",0.55,1) | AU8: =IFERROR(VLOOKUP(AR8,'Strategia 433'!$A$29:$B$38,2,FALSE),0.9) | AV8: =IFERROR(INDEX('Strategia 433'!$D$15:$H$24,MATCH(AR8,'Strategia 433'!$A$15:$A$24,0),MATCH(AS8,'Strategia 433'!$D$14:$H$14,0))*IF(AND(ISNUMBER(SEARCH("SUPER TOP",X8&"")),OR(AR8="Por",AR8="Pc")),1.08,1),1) | AW8: Taratura storico lega 12x500 + QUOT Fantacalcio | https://www.fantacalcio.it/quotazioni-fantacalcio | AX8: =MAX(1,ROUND(AE8*IF(AND(AR8="Pc",AS8="Top"),0.95,IF(AND(OR(AR8="A",AR8="Por",AR8="Dc"),AS8="Top"),0.90,0.85)),0))
A9: 6397 | B9: Ramos G. | D9: Milan | E9: 25 | F9: A | G9: Pc | H9: 1 | I9: 6 | J9: 6 | K9: 114 | L9: 27 | O9: =MAX(0,MIN(99,AG9+AH9)) | P9: =IF(O9>=80,"Alta",IF(O9>=60,"Medio-alta",IF(O9>=40,"Media",IF(O9>=20,"Bassa","Minima")))) | Q9: =MAX(5,MIN(99,ROUND(IF(AI9>0,0.5*AI9+0.25*AJ9+0.2*O9+0.05*AK9,0.55*AJ9+0.32*O9+0.08*AK9+0.05*MIN(100,L9*4))+MIN(6,(LEN(G9)-LEN(SUBSTITUTE(G9,"/","")))*2.5)-IF(C9="*",3,0),0))) | R9: =MAX(5,MIN(99,ROUND(50+0.65*(Q9-50)+0.2*(O9-60)-0.55*(AJ9-50),0))) | S9: =IF(Q9>=90,"S",IF(Q9>=80,"A",IF(Q9>=70,"B",IF(Q9>=60,"C",IF(Q9>=48,"D","E"))))) | T9: =IF(AND(Q9>=90,O9>=62),"PUNTA FORTE",IF(AND(Q9>=80,O9>=58),"COMPRA",IF(AND(R9>=75,Q9>=62,O9>=55),"AFFARE / ATTACCA",IF(AND(Q9>=69,O9>=50),"AL GIUSTO PREZZO",IF(AND(Q9>=58,O9>=40),"JOLLY / SCOMMESSA",IF(Q9>=45,"SOLO LOW COST","EVITA")))))) | U9: 5 | V9: BASSO | W9: =LEN(G9)-LEN(SUBSTITUTE(G9,"/",""))+1 | X9: TOP | Y9: =IF(AL9+AM9+AN9>=3,"Alta",IF(AL9+AM9+AN9>=2,"Medio-alta",IF(AL9+AM9+AN9=1,"Media","Bassa"))) | Z9: XI base; SOS: top | AA9: https://www.fantacalcio.it/news/calcio-italia/06_08_2026/asta-fantacalcio-le-probabili-formazioni-della-serie-a-enilive-2026-27-495558 | https://www.fantacalcio.it/probabili-formazioni-serie-a | AB9: https://www.sosfanta.com/guida-asta-fantacalcio/fantacalcio-mantra-ecco-la-guida-allasta-2026-27-la-divisione-ruolo-per-ruolo/ | AC9: https://www.fantacalcio.it/probabili-formazioni-serie-a | https://www.fantacalcio.it/quotazioni-fantacalcio | AD9: Da valutare | AE9: =MAX(1,MIN(AV9,ROUND(AO9*1.06,0))) | AG9: 98 | AH9: 0 | AI9: 90 | AJ9: 95.2 | AK9: 50 | AL9: 1 | AM9: 1 | AN9: 1 | AO9: =MAX(1,ROUND(L9*AU9*AT9*IF(ISNUMBER(SEARCH("SUPER TOP",X9&"")),1.08,IF(AS9="Top",1.04,IF(AS9="Semitop",1,IF(AS9="Starter",0.94,IF(AS9="Scommessa",0.9,0.85))))),0)) | AP9: =IF(AR9="Non433","BASSO",IF(OR(AR9="A",AR9="Pc"),"ALTISSIMO",IF(OR(AR9="M",AR9="C",AR9="Jolly"),"ALTO",IF(OR(AR9="Dd",AR9="Ds"),"MEDIO-ALTO","MEDIO")))) | AQ9: =IF(C9="*","EVITA - FUORI LISTA",IF(AR9="Non433","NON PRIORITARIO 4-3-3",IF(AND(OR(AR9="Pc",AR9="A"),AS9="Top"),"ALL-IN CONTROLLATO",IF(AND(AE9<=8,O9>=80),"GIOIELLO / TITOLARE LOW COST",IF(OR(AS9="Top",AS9="Semitop"),"COMPRA A VALORE",IF(O9>=80,"TITOLARE DA ASPETTARE","SOLO LOW COST")))))) | AR9: =IF(G9="Por","Por",IF(ISNUMBER(SEARCH("/Pc/","/"&G9&"/")),"Pc",IF(ISNUMBER(SEARCH("/A/","/"&G9&"/")),"A",IF(ISNUMBER(SEARCH("/M/","/"&G9&"/")),"M",IF(ISNUMBER(SEARCH("/C/","/"&G9&"/")),"C",IF(ISNUMBER(SEARCH("/Dd/","/"&G9&"/")),"Dd",IF(ISNUMBER(SEARCH("/Ds/","/"&G9&"/")),"Ds",IF(ISNUMBER(SEARCH("/Dc/","/"&G9&"/")),"Dc",IF(OR(ISNUMBER(SEARCH("/E/","/"&G9&"/")),ISNUMBER(SEARCH("/W/","/"&G9&"/")),ISNUMBER(SEARCH("/T/","/"&G9&"/")),ISNUMBER(SEARCH("/B/","/"&G9&"/"))),"Jolly","Non433"))))))))) | AS9: =IF(OR(X9="SUPER TOP",X9="TOP"),"Top",IF(X9="SEMITOP","Semitop",IF(OR(ISNUMBER(SEARCH("POSSIBILI SORPRESE",X9&"")),ISNUMBER(SEARCH("SCOMMES",X9&""))),"Scommessa",IF(OR(ISNUMBER(SEARCH("FASCIA ALTA",X9&"")),ISNUMBER(SEARCH("JOLLY 1",X9&"")),O9>=85),"Starter",IF(O9>=68,"Scommessa","Low"))))) | AT9: =IF(O9>=90,1,IF(O9>=80,0.93,IF(O9>=65,0.85,0.72)))*IF(ISNUMBER(SEARCH("MERCATO",V9&"")),0.85,1)*IF(ISNUMBER(SEARCH("INFORTUN",V9&"")),0.9,1)*IF(C9="*",0.55,1) | AU9: =IFERROR(VLOOKUP(AR9,'Strategia 433'!$A$29:$B$38,2,FALSE),0.9) | AV9: =IFERROR(INDEX('Strategia 433'!$D$15:$H$24,MATCH(AR9,'Strategia 433'!$A$15:$A$24,0),MATCH(AS9,'Strategia 433'!$D$14:$H$14,0))*IF(AND(ISNUMBER(SEARCH("SUPER TOP",X9&"")),OR(AR9="Por",AR9="Pc")),1.08,1),1) | AW9: Taratura storico lega 12x500 + QUOT Fantacalcio | https://www.fantacalcio.it/quotazioni-fantacalcio | AX9: =MAX(1,ROUND(AE9*IF(AND(AR9="Pc",AS9="Top"),0.95,IF(AND(OR(AR9="A",AR9="Por",AR9="Dc"),AS9="Top"),0.90,0.85)),0))
A10: 4777 | B10: McTominay | D10: Napoli | E10: 30 | F10: C | G10: C/T | H10: 1 | I10: 6 | J10: 6 | K10: 114 | L10: 28 | O10: =MAX(0,MIN(99,AG10+AH10)) | P10: =IF(O10>=80,"Alta",IF(O10>=60,"Medio-alta",IF(O10>=40,"Media",IF(O10>=20,"Bassa","Minima")))) | Q10: =MAX(5,MIN(99,ROUND(IF(AI10>0,0.5*AI10+0.25*AJ10+0.2*O10+0.05*AK10,0.55*AJ10+0.32*O10+0.08*AK10+0.05*MIN(100,L10*4))+MIN(6,(LEN(G10)-LEN(SUBSTITUTE(G10,"/","")))*2.5)-IF(C10="*",3,0),0))) | R10: =MAX(5,MIN(99,ROUND(50+0.65*(Q10-50)+0.2*(O10-60)-0.55*(AJ10-50),0))) | S10: =IF(Q10>=90,"S",IF(Q10>=80,"A",IF(Q10>=70,"B",IF(Q10>=60,"C",IF(Q10>=48,"D","E"))))) | T10: =IF(AND(Q10>=90,O10>=62),"PUNTA FORTE",IF(AND(Q10>=80,O10>=58),"COMPRA",IF(AND(R10>=75,Q10>=62,O10>=55),"AFFARE / ATTACCA",IF(AND(Q10>=69,O10>=50),"AL GIUSTO PREZZO",IF(AND(Q10>=58,O10>=40),"JOLLY / SCOMMESSA",IF(Q10>=45,"SOLO LOW COST","EVITA")))))) | U10: 5 | V10: BASSO | W10: =LEN(G10)-LEN(SUBSTITUTE(G10,"/",""))+1 | X10: SUPER TOP | Y10: =IF(AL10+AM10+AN10>=3,"Alta",IF(AL10+AM10+AN10>=2,"Medio-alta",IF(AL10+AM10+AN10=1,"Media","Bassa"))) | Z10: XI base; SOS: super top; pluriruolo | AA10: https://www.fantacalcio.it/news/calcio-italia/06_08_2026/asta-fantacalcio-le-probabili-formazioni-della-serie-a-enilive-2026-27-495558 | https://www.fantacalcio.it/probabili-formazioni-serie-a | AB10: https://www.sosfanta.com/guida-asta-fantacalcio/fantacalcio-mantra-ecco-la-guida-allasta-2026-27-la-divisione-ruolo-per-ruolo/ | AC10: https://www.fantacalcio.it/probabili-formazioni-serie-a | https://www.fantacalcio.it/quotazioni-fantacalcio | AD10: Da valutare | AE10: =MAX(1,MIN(AV10,ROUND(AO10*1.06,0))) | AG10: 98 | AH10: 0 | AI10: 98 | AJ10: 98.7 | AK10: 50 | AL10: 1 | AM10: 1 | AN10: 1 | AO10: =MAX(1,ROUND(L10*AU10*AT10*IF(ISNUMBER(SEARCH("SUPER TOP",X10&"")),1.08,IF(AS10="Top",1.04,IF(AS10="Semitop",1,IF(AS10="Starter",0.94,IF(AS10="Scommessa",0.9,0.85))))),0)) | AP10: =IF(AR10="Non433","BASSO",IF(OR(AR10="A",AR10="Pc"),"ALTISSIMO",IF(OR(AR10="M",AR10="C",AR10="Jolly"),"ALTO",IF(OR(AR10="Dd",AR10="Ds"),"MEDIO-ALTO","MEDIO")))) | AQ10: =IF(C10="*","EVITA - FUORI LISTA",IF(AR10="Non433","NON PRIORITARIO 4-3-3",IF(AND(OR(AR10="Pc",AR10="A"),AS10="Top"),"ALL-IN CONTROLLATO",IF(AND(AE10<=8,O10>=80),"GIOIELLO / TITOLARE LOW COST",IF(OR(AS10="Top",AS10="Semitop"),"COMPRA A VALORE",IF(O10>=80,"TITOLARE DA ASPETTARE","SOLO LOW COST")))))) | AR10: =IF(G10="Por","Por",IF(ISNUMBER(SEARCH("/Pc/","/"&G10&"/")),"Pc",IF(ISNUMBER(SEARCH("/A/","/"&G10&"/")),"A",IF(ISNUMBER(SEARCH("/M/","/"&G10&"/")),"M",IF(ISNUMBER(SEARCH("/C/","/"&G10&"/")),"C",IF(ISNUMBER(SEARCH("/Dd/","/"&G10&"/")),"Dd",IF(ISNUMBER(SEARCH("/Ds/","/"&G10&"/")),"Ds",IF(ISNUMBER(SEARCH("/Dc/","/"&G10&"/")),"Dc",IF(OR(ISNUMBER(SEARCH("/E/","/"&G10&"/")),ISNUMBER(SEARCH("/W/","/"&G10&"/")),ISNUMBER(SEARCH("/T/","/"&G10&"/")),ISNUMBER(SEARCH("/B/","/"&G10&"/"))),"Jolly","Non433"))))))))) | AS10: =IF(OR(X10="SUPER TOP",X10="TOP"),"Top",IF(X10="SEMITOP","Semitop",IF(OR(ISNUMBER(SEARCH("POSSIBILI SORPRESE",X10&"")),ISNUMBER(SEARCH("SCOMMES",X10&""))),"Scommessa",IF(OR(ISNUMBER(SEARCH("FASCIA ALTA",X10&"")),ISNUMBER(SEARCH("JOLLY 1",X10&"")),O10>=85),"Starter",IF(O10>=68,"Scommessa","Low"))))) | AT10: =IF(O10>=90,1,IF(O10>=80,0.93,IF(O10>=65,0.85,0.72)))*IF(ISNUMBER(SEARCH("MERCATO",V10&"")),0.85,1)*IF(ISNUMBER(SEARCH("INFORTUN",V10&"")),0.9,1)*IF(C10="*",0.55,1) | AU10: =IFERROR(VLOOKUP(AR10,'Strategia 433'!$A$29:$B$38,2,FALSE),0.9) | AV10: =IFERROR(INDEX('Strategia 433'!$D$15:$H$24,MATCH(AR10,'Strategia 433'!$A$15:$A$24,0),MATCH(AS10,'Strategia 433'!$D$14:$H$14,0))*IF(AND(ISNUMBER(SEARCH("SUPER TOP",X10&"")),OR(AR10="Por",AR10="Pc")),1.08,1),1) | AW10: Taratura storico lega 12x500 + QUOT Fantacalcio | https://www.fantacalcio.it/quotazioni-fantacalcio | AX10: =MAX(1,ROUND(AE10*IF(AND(AR10="Pc",AS10="Top"),0.95,IF(AND(OR(AR10="A",AR10="Por",AR10="Dc"),AS10="Top"),0.90,0.85)),0))
A11: 5951 | B11: Kolo Muani | D11: Juventus | E11: 28 | F11: A | G11: Pc | H11: 1 | I11: 5 | J11: 5 | K11: 106 | L11: 25 | O11: =MAX(0,MIN(99,AG11+AH11)) | P11: =IF(O11>=80,"Alta",IF(O11>=60,"Medio-alta",IF(O11>=40,"Media",IF(O11>=20,"Bassa","Minima")))) | Q11: =MAX(5,MIN(99,ROUND(IF(AI11>0,0.5*AI11+0.25*AJ11+0.2*O11+0.05*AK11,0.55*AJ11+0.32*O11+0.08*AK11+0.05*MIN(100,L11*4))+MIN(6,(LEN(G11)-LEN(SUBSTITUTE(G11,"/","")))*2.5)-IF(C11="*",3,0),0))) | R11: =MAX(5,MIN(99,ROUND(50+0.65*(Q11-50)+0.2*(O11-60)-0.55*(AJ11-50),0))) | S11: =IF(Q11>=90,"S",IF(Q11>=80,"A",IF(Q11>=70,"B",IF(Q11>=60,"C",IF(Q11>=48,"D","E"))))) | T11: =IF(AND(Q11>=90,O11>=62),"PUNTA FORTE",IF(AND(Q11>=80,O11>=58),"COMPRA",IF(AND(R11>=75,Q11>=62,O11>=55),"AFFARE / ATTACCA",IF(AND(Q11>=69,O11>=50),"AL GIUSTO PREZZO",IF(AND(Q11>=58,O11>=40),"JOLLY / SCOMMESSA",IF(Q11>=45,"SOLO LOW COST","EVITA")))))) | U11: 5 | V11: BASSO | W11: =LEN(G11)-LEN(SUBSTITUTE(G11,"/",""))+1 | X11: TOP | Y11: =IF(AL11+AM11+AN11>=3,"Alta",IF(AL11+AM11+AN11>=2,"Medio-alta",IF(AL11+AM11+AN11=1,"Media","Bassa"))) | Z11: XI base; SOS: top | AA11: https://www.fantacalcio.it/news/calcio-italia/06_08_2026/asta-fantacalcio-le-probabili-formazioni-della-serie-a-enilive-2026-27-495558 | https://www.fantacalcio.it/probabili-formazioni-serie-a | AB11: https://www.sosfanta.com/guida-asta-fantacalcio/fantacalcio-mantra-ecco-la-guida-allasta-2026-27-la-divisione-ruolo-per-ruolo/ | AC11: https://www.fantacalcio.it/probabili-formazioni-serie-a | https://www.fantacalcio.it/quotazioni-fantacalcio | AD11: Da valutare | AE11: =MAX(1,MIN(AV11,ROUND(AO11*1.06,0))) | AG11: 98 | AH11: 0 | AI11: 90 | AJ11: 94.1 | AK11: 32 | AL11: 1 | AM11: 1 | AN11: 1 | AO11: =MAX(1,ROUND(L11*AU11*AT11*IF(ISNUMBER(SEARCH("SUPER TOP",X11&"")),1.08,IF(AS11="Top",1.04,IF(AS11="Semitop",1,IF(AS11="Starter",0.94,IF(AS11="Scommessa",0.9,0.85))))),0)) | AP11: =IF(AR11="Non433","BASSO",IF(OR(AR11="A",AR11="Pc"),"ALTISSIMO",IF(OR(AR11="M",AR11="C",AR11="Jolly"),"ALTO",IF(OR(AR11="Dd",AR11="Ds"),"MEDIO-ALTO","MEDIO")))) | AQ11: =IF(C11="*","EVITA - FUORI LISTA",IF(AR11="Non433","NON PRIORITARIO 4-3-3",IF(AND(OR(AR11="Pc",AR11="A"),AS11="Top"),"ALL-IN CONTROLLATO",IF(AND(AE11<=8,O11>=80),"GIOIELLO / TITOLARE LOW COST",IF(OR(AS11="Top",AS11="Semitop"),"COMPRA A VALORE",IF(O11>=80,"TITOLARE DA ASPETTARE","SOLO LOW COST")))))) | AR11: =IF(G11="Por","Por",IF(ISNUMBER(SEARCH("/Pc/","/"&G11&"/")),"Pc",IF(ISNUMBER(SEARCH("/A/","/"&G11&"/")),"A",IF(ISNUMBER(SEARCH("/M/","/"&G11&"/")),"M",IF(ISNUMBER(SEARCH("/C/","/"&G11&"/")),"C",IF(ISNUMBER(SEARCH("/Dd/","/"&G11&"/")),"Dd",IF(ISNUMBER(SEARCH("/Ds/","/"&G11&"/")),"Ds",IF(ISNUMBER(SEARCH("/Dc/","/"&G11&"/")),"Dc",IF(OR(ISNUMBER(SEARCH("/E/","/"&G11&"/")),ISNUMBER(SEARCH("/W/","/"&G11&"/")),ISNUMBER(SEARCH("/T/","/"&G11&"/")),ISNUMBER(SEARCH("/B/","/"&G11&"/"))),"Jolly","Non433"))))))))) | AS11: =IF(OR(X11="SUPER TOP",X11="TOP"),"Top",IF(X11="SEMITOP","Semitop",IF(OR(ISNUMBER(SEARCH("POSSIBILI SORPRESE",X11&"")),ISNUMBER(SEARCH("SCOMMES",X11&""))),"Scommessa",IF(OR(ISNUMBER(SEARCH("FASCIA ALTA",X11&"")),ISNUMBER(SEARCH("JOLLY 1",X11&"")),O11>=85),"Starter",IF(O11>=68,"Scommessa","Low"))))) | AT11: =IF(O11>=90,1,IF(O11>=80,0.93,IF(O11>=65,0.85,0.72)))*IF(ISNUMBER(SEARCH("MERCATO",V11&"")),0.85,1)*IF(ISNUMBER(SEARCH("INFORTUN",V11&"")),0.9,1)*IF(C11="*",0.55,1) | AU11: =IFERROR(VLOOKUP(AR11,'Strategia 433'!$A$29:$B$38,2,FALSE),0.9) | AV11: =IFERROR(INDEX('Strategia 433'!$D$15:$H$24,MATCH(AR11,'Strategia 433'!$A$15:$A$24,0),MATCH(AS11,'Strategia 433'!$D$14:$H$14,0))*IF(AND(ISNUMBER(SEARCH("SUPER TOP",X11&"")),OR(AR11="Por",AR11="Pc")),1.08,1),1) | AW11: Taratura storico lega 12x500 + QUOT Fantacalcio | https://www.fantacalcio.it/quotazioni-fantacalcio | AX11: =MAX(1,ROUND(AE11*IF(AND(AR11="Pc",AS11="Top"),0.95,IF(AND(OR(AR11="A",AR11="Por",AR11="Dc"),AS11="Top"),0.90,0.85)),0))
A12: 2167 | B12: Orsolini | D12: Bologna | E12: 29 | F12: C | G12: W/A | H12: 1 | I12: 5.5 | J12: 5.5 | K12: 96 | L12: 24 | O12: =MAX(0,MIN(99,AG12+AH12)) | P12: =IF(O12>=80,"Alta",IF(O12>=60,"Medio-alta",IF(O12>=40,"Media",IF(O12>=20,"Bassa","Minima")))) | Q12: =MAX(5,MIN(99,ROUND(IF(AI12>0,0.5*AI12+0.25*AJ12+0.2*O12+0.05*AK12,0.55*AJ12+0.32*O12+0.08*AK12+0.05*MIN(100,L12*4))+MIN(6,(LEN(G12)-LEN(SUBSTITUTE(G12,"/","")))*2.5)-IF(C12="*",3,0),0))) | R12: =MAX(5,MIN(99,ROUND(50+0.65*(Q12-50)+0.2*(O12-60)-0.55*(AJ12-50),0))) | S12: =IF(Q12>=90,"S",IF(Q12>=80,"A",IF(Q12>=70,"B",IF(Q12>=60,"C",IF(Q12>=48,"D","E"))))) | T12: =IF(AND(Q12>=90,O12>=62),"PUNTA FORTE",IF(AND(Q12>=80,O12>=58),"COMPRA",IF(AND(R12>=75,Q12>=62,O12>=55),"AFFARE / ATTACCA",IF(AND(Q12>=69,O12>=50),"AL GIUSTO PREZZO",IF(AND(Q12>=58,O12>=40),"JOLLY / SCOMMESSA",IF(Q12>=45,"SOLO LOW COST","EVITA")))))) | U12: 5 | V12: BASSO | W12: =LEN(G12)-LEN(SUBSTITUTE(G12,"/",""))+1 | X12: TOP | Y12: =IF(AL12+AM12+AN12>=3,"Alta",IF(AL12+AM12+AN12>=2,"Medio-alta",IF(AL12+AM12+AN12=1,"Media","Bassa"))) | Z12: XI base; SOS: top; pluriruolo | AA12: https://www.fantacalcio.it/news/calcio-italia/06_08_2026/asta-fantacalcio-le-probabili-formazioni-della-serie-a-enilive-2026-27-495558 | https://www.fantacalcio.it/probabili-formazioni-serie-a | AB12: https://www.sosfanta.com/guida-asta-fantacalcio/fantacalcio-mantra-ecco-la-guida-allasta-2026-27-la-divisione-ruolo-per-ruolo/ | AC12: https://www.fantacalcio.it/probabili-formazioni-serie-a | https://www.fantacalcio.it/quotazioni-fantacalcio | AD12: Da valutare | AE12: =MAX(1,MIN(AV12,ROUND(AO12*1.06,0))) | AG12: 98 | AH12: 0 | AI12: 90 | AJ12: 98.1 | AK12: 41 | AL12: 1 | AM12: 1 | AN12: 1 | AO12: =MAX(1,ROUND(L12*AU12*AT12*IF(ISNUMBER(SEARCH("SUPER TOP",X12&"")),1.08,IF(AS12="Top",1.04,IF(AS12="Semitop",1,IF(AS12="Starter",0.94,IF(AS12="Scommessa",0.9,0.85))))),0)) | AP12: =IF(AR12="Non433","BASSO",IF(OR(AR12="A",AR12="Pc"),"ALTISSIMO",IF(OR(AR12="M",AR12="C",AR12="Jolly"),"ALTO",IF(OR(AR12="Dd",AR12="Ds"),"MEDIO-ALTO","MEDIO")))) | AQ12: =IF(C12="*","EVITA - FUORI LISTA",IF(AR12="Non433","NON PRIORITARIO 4-3-3",IF(AND(OR(AR12="Pc",AR12="A"),AS12="Top"),"ALL-IN CONTROLLATO",IF(AND(AE12<=8,O12>=80),"GIOIELLO / TITOLARE LOW COST",IF(OR(AS12="Top",AS12="Semitop"),"COMPRA A VALORE",IF(O12>=80,"TITOLARE DA ASPETTARE","SOLO LOW COST")))))) | AR12: =IF(G12="Por","Por",IF(ISNUMBER(SEARCH("/Pc/","/"&G12&"/")),"Pc",IF(ISNUMBER(SEARCH("/A/","/"&G12&"/")),"A",IF(ISNUMBER(SEARCH("/M/","/"&G12&"/")),"M",IF(ISNUMBER(SEARCH("/C/","/"&G12&"/")),"C",IF(ISNUMBER(SEARCH("/Dd/","/"&G12&"/")),"Dd",IF(ISNUMBER(SEARCH("/Ds/","/"&G12&"/")),"Ds",IF(ISNUMBER(SEARCH("/Dc/","/"&G12&"/")),"Dc",IF(OR(ISNUMBER(SEARCH("/E/","/"&G12&"/")),ISNUMBER(SEARCH("/W/","/"&G12&"/")),ISNUMBER(SEARCH("/T/","/"&G12&"/")),ISNUMBER(SEARCH("/B/","/"&G12&"/"))),"Jolly","Non433"))))))))) | AS12: =IF(OR(X12="SUPER TOP",X12="TOP"),"Top",IF(X12="SEMITOP","Semitop",IF(OR(ISNUMBER(SEARCH("POSSIBILI SORPRESE",X12&"")),ISNUMBER(SEARCH("SCOMMES",X12&""))),"Scommessa",IF(OR(ISNUMBER(SEARCH("FASCIA ALTA",X12&"")),ISNUMBER(SEARCH("JOLLY 1",X12&"")),O12>=85),"Starter",IF(O12>=68,"Scommessa","Low"))))) | AT12: =IF(O12>=90,1,IF(O12>=80,0.93,IF(O12>=65,0.85,0.72)))*IF(ISNUMBER(SEARCH("MERCATO",V12&"")),0.85,1)*IF(ISNUMBER(SEARCH("INFORTUN",V12&"")),0.9,1)*IF(C12="*",0.55,1) | AU12: =IFERROR(VLOOKUP(AR12,'Strategia 433'!$A$29:$B$38,2,FALSE),0.9) | AV12: =IFERROR(INDEX('Strategia 433'!$D$15:$H$24,MATCH(AR12,'Strategia 433'!$A$15:$A$24,0),MATCH(AS12,'Strategia 433'!$D$14:$H$14,0))*IF(AND(ISNUMBER(SEARCH("SUPER TOP",X12&"")),OR(AR12="Por",AR12="Pc")),1.08,1),1) | AW12: Taratura storico lega 12x500 + QUOT Fantacalcio | https://www.fantacalcio.it/quotazioni-fantacalcio | AX12: =MAX(1,ROUND(AE12*IF(AND(AR12="Pc",AS12="Top"),0.95,IF(AND(OR(AR12="A",AR12="Por",AR12="Dc"),AS12="Top"),0.90,0.85)),0))
A13: 2097 | B13: Kean | D13: Fiorentina | E13: 26 | F13: A | G13: Pc | H13: 1 | I13: 6 | J13: 6 | K13: 94 | L13: 25 | O13: =MAX(0,MIN(99,AG13+AH13)) | P13: =IF(O13>=80,"Alta",IF(O13>=60,"Medio-alta",IF(O13>=40,"Media",IF(O13>=20,"Bassa","Minima")))) | Q13: =MAX(5,MIN(99,ROUND(IF(AI13>0,0.5*AI13+0.25*AJ13+0.2*O13+0.05*AK13,0.55*AJ13+0.32*O13+0.08*AK13+0.05*MIN(100,L13*4))+MIN(6,(LEN(G13)-LEN(SUBSTITUTE(G13,"/","")))*2.5)-IF(C13="*",3,0),0))) | R13: =MAX(5,MIN(99,ROUND(50+0.65*(Q13-50)+0.2*(O13-60)-0.55*(AJ13-50),0))) | S13: =IF(Q13>=90,"S",IF(Q13>=80,"A",IF(Q13>=70,"B",IF(Q13>=60,"C",IF(Q13>=48,"D","E"))))) | T13: =IF(AND(Q13>=90,O13>=62),"PUNTA FORTE",IF(AND(Q13>=80,O13>=58),"COMPRA",IF(AND(R13>=75,Q13>=62,O13>=55),"AFFARE / ATTACCA",IF(AND(Q13>=69,O13>=50),"AL GIUSTO PREZZO",IF(AND(Q13>=58,O13>=40),"JOLLY / SCOMMESSA",IF(Q13>=45,"SOLO LOW COST","EVITA")))))) | U13: 4 | V13: MERCATO - situazione da monitorare | W13: =LEN(G13)-LEN(SUBSTITUTE(G13,"/",""))+1 | X13: SEMITOP | Y13: =IF(AL13+AM13+AN13>=3,"Alta",IF(AL13+AM13+AN13>=2,"Medio-alta",IF(AL13+AM13+AN13=1,"Media","Bassa"))) | Z13: XI base; SOS: semitop; Mercato: possibile esclusione/gestione finché il mercato è aperto | AA13: https://www.fantacalcio.it/news/calcio-italia/06_08_2026/asta-fantacalcio-le-probabili-formazioni-della-serie-a-enilive-2026-27-495558 | https://www.fantacalcio.it/probabili-formazioni-serie-a | AB13: https://www.sosfanta.com/guida-asta-fantacalcio/fantacalcio-mantra-ecco-la-guida-allasta-2026-27-la-divisione-ruolo-per-ruolo/ | AC13: https://www.fantacalcio.it/probabili-formazioni-serie-a | https://www.fantacalcio.it/quotazioni-fantacalcio | AD13: Da valutare | AE13: =MAX(1,MIN(AV13,ROUND(AO13*1.06,0))) | AG13: 83 | AH13: 0 | AI13: 82 | AJ13: 93.1 | AK13: 50 | AL13: 1 | AM13: 1 | AN13: 0 | AO13: =MAX(1,ROUND(L13*AU13*AT13*IF(ISNUMBER(SEARCH("SUPER TOP",X13&"")),1.08,IF(AS13="Top",1.04,IF(AS13="Semitop",1,IF(AS13="Starter",0.94,IF(AS13="Scommessa",0.9,0.85))))),0)) | AP13: =IF(AR13="Non433","BASSO",IF(OR(AR13="A",AR13="Pc"),"ALTISSIMO",IF(OR(AR13="M",AR13="C",AR13="Jolly"),"ALTO",IF(OR(AR13="Dd",AR13="Ds"),"MEDIO-ALTO","MEDIO")))) | AQ13: =IF(C13="*","EVITA - FUORI LISTA",IF(AR13="Non433","NON PRIORITARIO 4-3-3",IF(AND(OR(AR13="Pc",AR13="A"),AS13="Top"),"ALL-IN CONTROLLATO",IF(AND(AE13<=8,O13>=80),"GIOIELLO / TITOLARE LOW COST",IF(OR(AS13="Top",AS13="Semitop"),"COMPRA A VALORE",IF(O13>=80,"TITOLARE DA ASPETTARE","SOLO LOW COST")))))) | AR13: =IF(G13="Por","Por",IF(ISNUMBER(SEARCH("/Pc/","/"&G13&"/")),"Pc",IF(ISNUMBER(SEARCH("/A/","/"&G13&"/")),"A",IF(ISNUMBER(SEARCH("/M/","/"&G13&"/")),"M",IF(ISNUMBER(SEARCH("/C/","/"&G13&"/")),"C",IF(ISNUMBER(SEARCH("/Dd/","/"&G13&"/")),"Dd",IF(ISNUMBER(SEARCH("/Ds/","/"&G13&"/")),"Ds",IF(ISNUMBER(SEARCH("/Dc/","/"&G13&"/")),"Dc",IF(OR(ISNUMBER(SEARCH("/E/","/"&G13&"/")),ISNUMBER(SEARCH("/W/","/"&G13&"/")),ISNUMBER(SEARCH("/T/","/"&G13&"/")),ISNUMBER(SEARCH("/B/","/"&G13&"/"))),"Jolly","Non433"))))))))) | AS13: =IF(OR(X13="SUPER TOP",X13="TOP"),"Top",IF(X13="SEMITOP","Semitop",IF(OR(ISNUMBER(SEARCH("POSSIBILI SORPRESE",X13&"")),ISNUMBER(SEARCH("SCOMMES",X13&""))),"Scommessa",IF(OR(ISNUMBER(SEARCH("FASCIA ALTA",X13&"")),ISNUMBER(SEARCH("JOLLY 1",X13&"")),O13>=85),"Starter",IF(O13>=68,"Scommessa","Low"))))) | AT13: =IF(O13>=90,1,IF(O13>=80,0.93,IF(O13>=65,0.85,0.72)))*IF(ISNUMBER(SEARCH("MERCATO",V13&"")),0.85,1)*IF(ISNUMBER(SEARCH("INFORTUN",V13&"")),0.9,1)*IF(C13="*",0.55,1) | AU13: =IFERROR(VLOOKUP(AR13,'Strategia 433'!$A$29:$B$38,2,FALSE),0.9) | AV13: =IFERROR(INDEX('Strategia 433'!$D$15:$H$24,MATCH(AR13,'Strategia 433'!$A$15:$A$24,0),MATCH(AS13,'Strategia 433'!$D$14:$H$14,0))*IF(AND(ISNUMBER(SEARCH("SUPER TOP",X13&"")),OR(AR13="Por",AR13="Pc")),1.08,1),1) | AW13: Taratura storico lega 12x500 + QUOT Fantacalcio | https://www.fantacalcio.it/quotazioni-fantacalcio | AX13: =MAX(1,ROUND(AE13*IF(AND(AR13="Pc",AS13="Top"),0.95,IF(AND(OR(AR13="A",AR13="Por",AR13="Dc"),AS13="Top"),0.90,0.85)),0))
... A82: 7484 | B82: Adams A. | D82: Venezia | E82: 26 | F82: A | G82: Pc | H82: 1 | I82: 5.5 | J82: 5.5 | K82: 21 | L82: 11 | O82: =MAX(0,MIN(99,AG82+AH82)) | P82: =IF(O82>=80,"Alta",IF(O82>=60,"Medio-alta",IF(O82>=40,"Media",IF(O82>=20,"Bassa","Minima")))) | Q82: =MAX(5,MIN(99,ROUND(IF(AI82>0,0.5*AI82+0.25*AJ82+0.2*O82+0.05*AK82,0.55*AJ82+0.32*O82+0.08*AK82+0.05*MIN(100,L82*4))+MIN(6,(LEN(G82)-LEN(SUBSTITUTE(G82,"/","")))*2.5)-IF(C82="*",3,0),0))) | R82: =MAX(5,MIN(99,ROUND(50+0.65*(Q82-50)+0.2*(O82-60)-0.55*(AJ82-50),0))) | S82: =IF(Q82>=90,"S",IF(Q82>=80,"A",IF(Q82>=70,"B",IF(Q82>=60,"C",IF(Q82>=48,"D","E"))))) | T82: =IF(AND(Q82>=90,O82>=62),"PUNTA FORTE",IF(AND(Q82>=80,O82>=58),"COMPRA",IF(AND(R82>=75,Q82>=62,O82>=55),"AFFARE / ATTACCA",IF(AND(Q82>=69,O82>=50),"AL GIUSTO PREZZO",IF(AND(Q82>=58,O82>=40),"JOLLY / SCOMMESSA",IF(Q82>=45,"SOLO LOW COST","EVITA")))))) | U82: 3 | V82: BALLOTTAGGIO | W82: =LEN(G82)-LEN(SUBSTITUTE(G82,"/",""))+1 | X82: FASCIA ALTA | Y82: =IF(AL82+AM82+AN82>=3,"Alta",IF(AL82+AM82+AN82>=2,"Medio-alta",IF(AL82+AM82+AN82=1,"Media","Bassa"))) | Z82: XI base; ballottaggio; SOS: fascia alta | AA82: https://www.fantacalcio.it/news/calcio-italia/06_08_2026/asta-fantacalcio-le-probabili-formazioni-della-serie-a-enilive-2026-27-495558 | https://www.fantacalcio.it/probabili-formazioni-serie-a | AB82: https://www.sosfanta.com/guida-asta-fantacalcio/fantacalcio-mantra-ecco-la-guida-allasta-2026-27-la-divisione-ruolo-per-ruolo/ | AC82: https://www.fantacalcio.it/probabili-formazioni-serie-a | https://www.fantacalcio.it/quotazioni-fantacalcio | AD82: Da valutare | AE82: =MAX(1,MIN(AV82,ROUND(AO82*1.06,0))) | AG82: 82 | AH82: 0 | AI82: 69 | AJ82: 68.1 | AK82: 41 | AL82: 1 | AM82: 1 | AN82: 1 | AO82: =MAX(1,ROUND(L82*AU82*AT82*IF(ISNUMBER(SEARCH("SUPER TOP",X82&"")),1.08,IF(AS82="Top",1.04,IF(AS82="Semitop",1,IF(AS82="Starter",0.94,IF(AS82="Scommessa",0.9,0.85))))),0)) | AP82: =IF(AR82="Non433","BASSO",IF(OR(AR82="A",AR82="Pc"),"ALTISSIMO",IF(OR(AR82="M",AR82="C",AR82="Jolly"),"ALTO",IF(OR(AR82="Dd",AR82="Ds"),"MEDIO-ALTO","MEDIO")))) | AQ82: =IF(C82="*","EVITA - FUORI LISTA",IF(AR82="Non433","NON PRIORITARIO 4-3-3",IF(AND(OR(AR82="Pc",AR82="A"),AS82="Top"),"ALL-IN CONTROLLATO",IF(AND(AE82<=8,O82>=80),"GIOIELLO / TITOLARE LOW COST",IF(OR(AS82="Top",AS82="Semitop"),"COMPRA A VALORE",IF(O82>=80,"TITOLARE DA ASPETTARE","SOLO LOW COST")))))) | AR82: =IF(G82="Por","Por",IF(ISNUMBER(SEARCH("/Pc/","/"&G82&"/")),"Pc",IF(ISNUMBER(SEARCH("/A/","/"&G82&"/")),"A",IF(ISNUMBER(SEARCH("/M/","/"&G82&"/")),"M",IF(ISNUMBER(SEARCH("/C/","/"&G82&"/")),"C",IF(ISNUMBER(SEARCH("/Dd/","/"&G82&"/")),"Dd",IF(ISNUMBER(SEARCH("/Ds/","/"&G82&"/")),"Ds",IF(ISNUMBER(SEARCH("/Dc/","/"&G82&"/")),"Dc",IF(OR(ISNUMBER(SEARCH("/E/","/"&G82&"/")),ISNUMBER(SEARCH("/W/","/"&G82&"/")),ISNUMBER(SEARCH("/T/","/"&G82&"/")),ISNUMBER(SEARCH("/B/","/"&G82&"/"))),"Jolly","Non433"))))))))) | AS82: =IF(OR(X82="SUPER TOP",X82="TOP"),"Top",IF(X82="SEMITOP","Semitop",IF(OR(ISNUMBER(SEARCH("POSSIBILI SORPRESE",X82&"")),ISNUMBER(SEARCH("SCOMMES",X82&""))),"Scommessa",IF(OR(ISNUMBER(SEARCH("FASCIA ALTA",X82&"")),ISNUMBER(SEARCH("JOLLY 1",X82&"")),O82>=85),"Starter",IF(O82>=68,"Scommessa","Low"))))) | AT82: =IF(O82>=90,1,IF(O82>=80,0.93,IF(O82>=65,0.85,0.72)))*IF(ISNUMBER(SEARCH("MERCATO",V82&"")),0.85,1)*IF(ISNUMBER(SEARCH("INFORTUN",V82&"")),0.9,1)*IF(C82="*",0.55,1) | AU82: =IFERROR(VLOOKUP(AR82,'Strategia 433'!$A$29:$B$38,2,FALSE),0.9) | AV82: =IFERROR(INDEX('Strategia 433'!$D$15:$H$24,MATCH(AR82,'Strategia 433'!$A$15:$A$24,0),MATCH(AS82,'Strategia 433'!$D$14:$H$14,0))*IF(AND(ISNUMBER(SEARCH("SUPER TOP",X82&"")),OR(AR82="Por",AR82="Pc")),1.08,1),1) | AW82: Taratura storico lega 12x500 + QUOT Fantacalcio | https://www.fantacalcio.it/quotazioni-fantacalcio | AX82: =MAX(1,ROUND(AE82*IF(AND(AR82="Pc",AS82="Top"),0.95,IF(AND(OR(AR82="A",AR82="Por",AR82="Dc"),AS82="Top"),0.90,0.85)),0))
A83: 2531 | B83: Lukaku | C83: * | D83: Napoli | E83: 33 | F83: A | G83: Pc | H83: 0 | I83: 0 | J83: 0 | K83: 21 | L83: 9 | O83: =MAX(0,MIN(99,AG83+AH83)) | P83: =IF(O83>=80,"Alta",IF(O83>=60,"Medio-alta",IF(O83>=40,"Media",IF(O83>=20,"Bassa","Minima")))) | Q83: =MAX(5,MIN(99,ROUND(IF(AI83>0,0.5*AI83+0.25*AJ83+0.2*O83+0.05*AK83,0.55*AJ83+0.32*O83+0.08*AK83+0.05*MIN(100,L83*4))+MIN(6,(LEN(G83)-LEN(SUBSTITUTE(G83,"/","")))*2.5)-IF(C83="*",3,0),0))) | R83: =MAX(5,MIN(99,ROUND(50+0.65*(Q83-50)+0.2*(O83-60)-0.55*(AJ83-50),0))) | S83: =IF(Q83>=90,"S",IF(Q83>=80,"A",IF(Q83>=70,"B",IF(Q83>=60,"C",IF(Q83>=48,"D","E"))))) | T83: =IF(AND(Q83>=90,O83>=62),"PUNTA FORTE",IF(AND(Q83>=80,O83>=58),"COMPRA",IF(AND(R83>=75,Q83>=62,O83>=55),"AFFARE / ATTACCA",IF(AND(Q83>=69,O83>=50),"AL GIUSTO PREZZO",IF(AND(Q83>=58,O83>=40),"JOLLY / SCOMMESSA",IF(Q83>=45,"SOLO LOW COST","EVITA")))))) | U83: 1 | V83: FUORI LISTA * + MERCATO | W83: =LEN(G83)-LEN(SUBSTITUTE(G83,"/",""))+1 | X83: MERCATO | Y83: =IF(AL83+AM83+AN83>=3,"Alta",IF(AL83+AM83+AN83>=2,"Medio-alta",IF(AL83+AM83+AN83=1,"Media","Bassa"))) | Z83: SOS: mercato; flag fuori lista nel file: verifica prima di rilanciare | AA83: https://www.fantacalcio.it/news/calcio-italia/06_08_2026/asta-fantacalcio-le-probabili-formazioni-della-serie-a-enilive-2026-27-495558 | https://www.fantacalcio.it/probabili-formazioni-serie-a | AB83: https://www.sosfanta.com/guida-asta-fantacalcio/fantacalcio-mantra-ecco-la-guida-allasta-2026-27-la-divisione-ruolo-per-ruolo/ | AC83: https://www.fantacalcio.it/probabili-formazioni-serie-a | https://www.fantacalcio.it/quotazioni-fantacalcio | AD83: Da valutare | AE83: =MAX(1,MIN(AV83,ROUND(AO83*1.06,0))) | AG83: 25 | AH83: 0 | AI83: 45 | AJ83: 68.1 | AK83: 50 | AL83: 0 | AM83: 1 | AN83: 0 | AO83: =MAX(1,ROUND(L83*AU83*AT83*IF(ISNUMBER(SEARCH("SUPER TOP",X83&"")),1.08,IF(AS83="Top",1.04,IF(AS83="Semitop",1,IF(AS83="Starter",0.94,IF(AS83="Scommessa",0.9,0.85))))),0)) | AP83: =IF(AR83="Non433","BASSO",IF(OR(AR83="A",AR83="Pc"),"ALTISSIMO",IF(OR(AR83="M",AR83="C",AR83="Jolly"),"ALTO",IF(OR(AR83="Dd",AR83="Ds"),"MEDIO-ALTO","MEDIO")))) | AQ83: =IF(C83="*","EVITA - FUORI LISTA",IF(AR83="Non433","NON PRIORITARIO 4-3-3",IF(AND(OR(AR83="Pc",AR83="A"),AS83="Top"),"ALL-IN CONTROLLATO",IF(AND(AE83<=8,O83>=80),"GIOIELLO / TITOLARE LOW COST",IF(OR(AS83="Top",AS83="Semitop"),"COMPRA A VALORE",IF(O83>=80,"TITOLARE DA ASPETTARE","SOLO LOW COST")))))) | AR83: =IF(G83="Por","Por",IF(ISNUMBER(SEARCH("/Pc/","/"&G83&"/")),"Pc",IF(ISNUMBER(SEARCH("/A/","/"&G83&"/")),"A",IF(ISNUMBER(SEARCH("/M/","/"&G83&"/")),"M",IF(ISNUMBER(SEARCH("/C/","/"&G83&"/")),"C",IF(ISNUMBER(SEARCH("/Dd/","/"&G83&"/")),"Dd",IF(ISNUMBER(SEARCH("/Ds/","/"&G83&"/")),"Ds",IF(ISNUMBER(SEARCH("/Dc/","/"&G83&"/")),"Dc",IF(OR(ISNUMBER(SEARCH("/E/","/"&G83&"/")),ISNUMBER(SEARCH("/W/","/"&G83&"/")),ISNUMBER(SEARCH("/T/","/"&G83&"/")),ISNUMBER(SEARCH("/B/","/"&G83&"/"))),"Jolly","Non433"))))))))) | AS83: =IF(OR(X83="SUPER TOP",X83="TOP"),"Top",IF(X83="SEMITOP","Semitop",IF(OR(ISNUMBER(SEARCH("POSSIBILI SORPRESE",X83&"")),ISNUMBER(SEARCH("SCOMMES",X83&""))),"Scommessa",IF(OR(ISNUMBER(SEARCH("FASCIA ALTA",X83&"")),ISNUMBER(SEARCH("JOLLY 1",X83&"")),O83>=85),"Starter",IF(O83>=68,"Scommessa","Low"))))) | AT83: =IF(O83>=90,1,IF(O83>=80,0.93,IF(O83>=65,0.85,0.72)))*IF(ISNUMBER(SEARCH("MERCATO",V83&"")),0.85,1)*IF(ISNUMBER(SEARCH("INFORTUN",V83&"")),0.9,1)*IF(C83="*",0.55,1) | AU83: =IFERROR(VLOOKUP(AR83,'Strategia 433'!$A$29:$B$38,2,FALSE),0.9) | AV83: =IFERROR(INDEX('Strategia 433'!$D$15:$H$24,MATCH(AR83,'Strategia 433'!$A$15:$A$24,0),MATCH(AS83,'Strategia 433'!$D$14:$H$14,0))*IF(AND(ISNUMBER(SEARCH("SUPER TOP",X83&"")),OR(AR83="Por",AR83="Pc")),1.08,1),1) | AW83: Taratura storico lega 12x500 + QUOT Fantacalcio | https://www.fantacalcio.it/quotazioni-fantacalcio | AX83: =MAX(1,ROUND(AE83*IF(AND(AR83="Pc",AS83="Top"),0.95,IF(AND(OR(AR83="A",AR83="Por",AR83="Dc"),AS83="Top"),0.90,0.85)),0))
A84: 4892 | B84: Saelemaekers | D84: Milan | E84: 27 | F84: C | G84: E/W | H84: 1 | I84: 6 | J84: 6 | K84: 18 | L84: 11 | O84: =MAX(0,MIN(99,AG84+AH84)) | P84: =IF(O84>=80,"Alta",IF(O84>=60,"Medio-alta",IF(O84>=40,"Media",IF(O84>=20,"Bassa","Minima")))) | Q84: =MAX(5,MIN(99,ROUND(IF(AI84>0,0.5*AI84+0.25*AJ84+0.2*O84+0.05*AK84,0.55*AJ84+0.32*O84+0.08*AK84+0.05*MIN(100,L84*4))+MIN(6,(LEN(G84)-LEN(SUBSTITUTE(G84,"/","")))*2.5)-IF(C84="*",3,0),0))) | R84: =MAX(5,MIN(99,ROUND(50+0.65*(Q84-50)+0.2*(O84-60)-0.55*(AJ84-50),0))) | S84: =IF(Q84>=90,"S",IF(Q84>=80,"A",IF(Q84>=70,"B",IF(Q84>=60,"C",IF(Q84>=48,"D","E"))))) | T84: =IF(AND(Q84>=90,O84>=62),"PUNTA FORTE",IF(AND(Q84>=80,O84>=58),"COMPRA",IF(AND(R84>=75,Q84>=62,O84>=55),"AFFARE / ATTACCA",IF(AND(Q84>=69,O84>=50),"AL GIUSTO PREZZO",IF(AND(Q84>=58,O84>=40),"JOLLY / SCOMMESSA",IF(Q84>=45,"SOLO LOW COST","EVITA")))))) | U84: 4 | V84: BALLOTTAGGIO | W84: =LEN(G84)-LEN(SUBSTITUTE(G84,"/",""))+1 | X84: SEMITOP | Y84: =IF(AL84+AM84+AN84>=3,"Alta",IF(AL84+AM84+AN84>=2,"Medio-alta",IF(AL84+AM84+AN84=1,"Media","Bassa"))) | Z84: XI base; ballottaggio; SOS: semitop; pluriruolo | AA84: https://www.fantacalcio.it/news/calcio-italia/06_08_2026/asta-fantacalcio-le-probabili-formazioni-della-serie-a-enilive-2026-27-495558 | https://www.fantacalcio.it/probabili-formazioni-serie-a | AB84: https://www.sosfanta.com/guida-asta-fantacalcio/fantacalcio-mantra-ecco-la-guida-allasta-2026-27-la-divisione-ruolo-per-ruolo/ | AC84: https://www.fantacalcio.it/probabili-formazioni-serie-a | https://www.fantacalcio.it/quotazioni-fantacalcio | AD84: Da valutare | AE84: =MAX(1,MIN(AV84,ROUND(AO84*1.06,0))) | AG84: 51 | AH84: 0 | AI84: 64 | AJ84: 82.7 | AK84: 100 | AL84: 1 | AM84: 1 | AN84: 0 | AO84: =MAX(1,ROUND(L84*AU84*AT84*IF(ISNUMBER(SEARCH("SUPER TOP",X84&"")),1.08,IF(AS84="Top",1.04,IF(AS84="Semitop",1,IF(AS84="Starter",0.94,IF(AS84="Scommessa",0.9,0.85))))),0)) | AP84: =IF(AR84="Non433","BASSO",IF(OR(AR84="A",AR84="Pc"),"ALTISSIMO",IF(OR(AR84="M",AR84="C",AR84="Jolly"),"ALTO",IF(OR(AR84="Dd",AR84="Ds"),"MEDIO-ALTO","MEDIO")))) | AQ84: =IF(C84="*","EVITA - FUORI LISTA",IF(AR84="Non433","NON PRIORITARIO 4-3-3",IF(AND(OR(AR84="Pc",AR84="A"),AS84="Top"),"ALL-IN CONTROLLATO",IF(AND(AE84<=8,O84>=80),"GIOIELLO / TITOLARE LOW COST",IF(OR(AS84="Top",AS84="Semitop"),"COMPRA A VALORE",IF(O84>=80,"TITOLARE DA ASPETTARE","SOLO LOW COST")))))) | AR84: =IF(G84="Por","Por",IF(ISNUMBER(SEARCH("/Pc/","/"&G84&"/")),"Pc",IF(ISNUMBER(SEARCH("/A/","/"&G84&"/")),"A",IF(ISNUMBER(SEARCH("/M/","/"&G84&"/")),"M",IF(ISNUMBER(SEARCH("/C/","/"&G84&"/")),"C",IF(ISNUMBER(SEARCH("/Dd/","/"&G84&"/")),"Dd",IF(ISNUMBER(SEARCH("/Ds/","/"&G84&"/")),"Ds",IF(ISNUMBER(SEARCH("/Dc/","/"&G84&"/")),"Dc",IF(OR(ISNUMBER(SEARCH("/E/","/"&G84&"/")),ISNUMBER(SEARCH("/W/","/"&G84&"/")),ISNUMBER(SEARCH("/T/","/"&G84&"/")),ISNUMBER(SEARCH("/B/","/"&G84&"/"))),"Jolly","Non433"))))))))) | AS84: =IF(OR(X84="SUPER TOP",X84="TOP"),"Top",IF(X84="SEMITOP","Semitop",IF(OR(ISNUMBER(SEARCH("POSSIBILI SORPRESE",X84&"")),ISNUMBER(SEARCH("SCOMMES",X84&""))),"Scommessa",IF(OR(ISNUMBER(SEARCH("FASCIA ALTA",X84&"")),ISNUMBER(SEARCH("JOLLY 1",X84&"")),O84>=85),"Starter",IF(O84>=68,"Scommessa","Low"))))) | AT84: =IF(O84>=90,1,IF(O84>=80,0.93,IF(O84>=65,0.85,0.72)))*IF(ISNUMBER(SEARCH("MERCATO",V84&"")),0.85,1)*IF(ISNUMBER(SEARCH("INFORTUN",V84&"")),0.9,1)*IF(C84="*",0.55,1) | AU84: =IFERROR(VLOOKUP(AR84,'Strategia 433'!$A$29:$B$38,2,FALSE),0.9) | AV84: =IFERROR(INDEX('Strategia 433'!$D$15:$H$24,MATCH(AR84,'Strategia 433'!$A$15:$A$24,0),MATCH(AS84,'Strategia 433'!$D$14:$H$14,0))*IF(AND(ISNUMBER(SEARCH("SUPER TOP",X84&"")),OR(AR84="Por",AR84="Pc")),1.08,1),1) | AW84: Taratura storico lega 12x500 + QUOT Fantacalcio | https://www.fantacalcio.it/quotazioni-fantacalcio | AX84: =MAX(1,ROUND(AE84*IF(AND(AR84="Pc",AS84="Top"),0.95,IF(AND(OR(AR84="A",AR84="Por",AR84="Dc"),AS84="Top"),0.90,0.85)),0))
A85: 6151 | B85: Perrone | D85: Como | E85: 23 | F85: C | G85: M/C | H85: 1 | I85: 6 | J85: 6 | K85: 21 | L85: 11 | O85: =MAX(0,MIN(99,AG85+AH85)) | P85: =IF(O85>=80,"Alta",IF(O85>=60,"Medio-alta",IF(O85>=40,"Media",IF(O85>=20,"Bassa","Minima")))) | Q85: =MAX(5,MIN(99,ROUND(IF(AI85>0,0.5*AI85+0.25*AJ85+0.2*O85+0.05*AK85,0.55*AJ85+0.32*O85+0.08*AK85+0.05*MIN(100,L85*4))+MIN(6,(LEN(G85)-LEN(SUBSTITUTE(G85,"/","")))*2.5)-IF(C85="*",3,0),0))) | R85: =MAX(5,MIN(99,ROUND(50+0.65*(Q85-50)+0.2*(O85-60)-0.55*(AJ85-50),0))) | S85: =IF(Q85>=90,"S",IF(Q85>=80,"A",IF(Q85>=70,"B",IF(Q85>=60,"C",IF(Q85>=48,"D","E"))))) | T85: =IF(AND(Q85>=90,O85>=62),"PUNTA FORTE",IF(AND(Q85>=80,O85>=58),"COMPRA",IF(AND(R85>=75,Q85>=62,O85>=55),"AFFARE / ATTACCA",IF(AND(Q85>=69,O85>=50),"AL GIUSTO PREZZO",IF(AND(Q85>=58,O85>=40),"JOLLY / SCOMMESSA",IF(Q85>=45,"SOLO LOW COST","EVITA")))))) | U85: 5 | V85: BASSO | W85: =LEN(G85)-LEN(SUBSTITUTE(G85,"/",""))+1 | X85: SEMITOP | Y85: =IF(AL85+AM85+AN85>=3,"Alta",IF(AL85+AM85+AN85>=2,"Medio-alta",IF(AL85+AM85+AN85=1,"Media","Bassa"))) | Z85: XI base; SOS: semitop; pluriruolo | AA85: https://www.fantacalcio.it/news/calcio-italia/06_08_2026/asta-fantacalcio-le-probabili-formazioni-della-serie-a-enilive-2026-27-495558 | https://www.fantacalcio.it/probabili-formazioni-serie-a | AB85: https://www.sosfanta.com/guida-asta-fantacalcio/fantacalcio-mantra-ecco-la-guida-allasta-2026-27-la-divisione-ruolo-per-ruolo/ | AC85: https://www.fantacalcio.it/probabili-formazioni-serie-a | https://www.fantacalcio.it/quotazioni-fantacalcio | AD85: Da valutare | AE85: =MAX(1,MIN(AV85,ROUND(AO85*1.06,0))) | AG85: 98 | AH85: 0 | AI85: 82 | AJ85: 82.7 | AK85: 50 | AL85: 1 | AM85: 1 | AN85: 1 | AO85: =MAX(1,ROUND(L85*AU85*AT85*IF(ISNUMBER(SEARCH("SUPER TOP",X85&"")),1.08,IF(AS85="Top",1.04,IF(AS85="Semitop",1,IF(AS85="Starter",0.94,IF(AS85="Scommessa",0.9,0.85))))),0)) | AP85: =IF(AR85="Non433","BASSO",IF(OR(AR85="A",AR85="Pc"),"ALTISSIMO",IF(OR(AR85="M",AR85="C",AR85="Jolly"),"ALTO",IF(OR(AR85="Dd",AR85="Ds"),"MEDIO-ALTO","MEDIO")))) | AQ85: =IF(C85="*","EVITA - FUORI LISTA",IF(AR85="Non433","NON PRIORITARIO 4-3-3",IF(AND(OR(AR85="Pc",AR85="A"),AS85="Top"),"ALL-IN CONTROLLATO",IF(AND(AE85<=8,O85>=80),"GIOIELLO / TITOLARE LOW COST",IF(OR(AS85="Top",AS85="Semitop"),"COMPRA A VALORE",IF(O85>=80,"TITOLARE DA ASPETTARE","SOLO LOW COST")))))) | AR85: =IF(G85="Por","Por",IF(ISNUMBER(SEARCH("/Pc/","/"&G85&"/")),"Pc",IF(ISNUMBER(SEARCH("/A/","/"&G85&"/")),"A",IF(ISNUMBER(SEARCH("/M/","/"&G85&"/")),"M",IF(ISNUMBER(SEARCH("/C/","/"&G85&"/")),"C",IF(ISNUMBER(SEARCH("/Dd/","/"&G85&"/")),"Dd",IF(ISNUMBER(SEARCH("/Ds/","/"&G85&"/")),"Ds",IF(ISNUMBER(SEARCH("/Dc/","/"&G85&"/")),"Dc",IF(OR(ISNUMBER(SEARCH("/E/","/"&G85&"/")),ISNUMBER(SEARCH("/W/","/"&G85&"/")),ISNUMBER(SEARCH("/T/","/"&G85&"/")),ISNUMBER(SEARCH("/B/","/"&G85&"/"))),"Jolly","Non433"))))))))) | AS85: =IF(OR(X85="SUPER TOP",X85="TOP"),"Top",IF(X85="SEMITOP","Semitop",IF(OR(ISNUMBER(SEARCH("POSSIBILI SORPRESE",X85&"")),ISNUMBER(SEARCH("SCOMMES",X85&""))),"Scommessa",IF(OR(ISNUMBER(SEARCH("FASCIA ALTA",X85&"")),ISNUMBER(SEARCH("JOLLY 1",X85&"")),O85>=85),"Starter",IF(O85>=68,"Scommessa","Low"))))) | AT85: =IF(O85>=90,1,IF(O85>=80,0.93,IF(O85>=65,0.85,0.72)))*IF(ISNUMBER(SEARCH("MERCATO",V85&"")),0.85,1)*IF(ISNUMBER(SEARCH("INFORTUN",V85&"")),0.9,1)*IF(C85="*",0.55,1) | AU85: =IFERROR(VLOOKUP(AR85,'Strategia 433'!$A$29:$B$38,2,FALSE),0.9) | AV85: =IFERROR(INDEX('Strategia 433'!$D$15:$H$24,MATCH(AR85,'Strategia 433'!$A$15:$A$24,0),MATCH(AS85,'Strategia 433'!$D$14:$H$14,0))*IF(AND(ISNUMBER(SEARCH("SUPER TOP",X85&"")),OR(AR85="Por",AR85="Pc")),1.08,1),1) | AW85: Taratura storico lega 12x500 + QUOT Fantacalcio | https://www.fantacalcio.it/quotazioni-fantacalcio | AX85: =MAX(1,ROUND(AE85*IF(AND(AR85="Pc",AS85="Top"),0.95,IF(AND(OR(AR85="A",AR85="Por",AR85="Dc"),AS85="Top"),0.90,0.85)),0))
A86: 5119 | B86: Samardzic | D86: Atalanta | E86: 24 | F86: C | G86: C/T | H86: 1 | I86: 6 | J86: 6 | K86: 21 | L86: 12 | O86: =MAX(0,MIN(99,AG86+AH86)) | P86: =IF(O86>=80,"Alta",IF(O86>=60,"Medio-alta",IF(O86>=40,"Media",IF(O86>=20,"Bassa","Minima")))) | Q86: =MAX(5,MIN(99,ROUND(IF(AI86>0,0.5*AI86+0.25*AJ86+0.2*O86+0.05*AK86,0.55*AJ86+0.32*O86+0.08*AK86+0.05*MIN(100,L86*4))+MIN(6,(LEN(G86)-LEN(SUBSTITUTE(G86,"/","")))*2.5)-IF(C86="*",3,0),0))) | R86: =MAX(5,MIN(99,ROUND(50+0.65*(Q86-50)+0.2*(O86-60)-0.55*(AJ86-50),0))) | S86: =IF(Q86>=90,"S",IF(Q86>=80,"A",IF(Q86>=70,"B",IF(Q86>=60,"C",IF(Q86>=48,"D","E"))))) | T86: =IF(AND(Q86>=90,O86>=62),"PUNTA FORTE",IF(AND(Q86>=80,O86>=58),"COMPRA",IF(AND(R86>=75,Q86>=62,O86>=55),"AFFARE / ATTACCA",IF(AND(Q86>=69,O86>=50),"AL GIUSTO PREZZO",IF(AND(Q86>=58,O86>=40),"JOLLY / SCOMMESSA",IF(Q86>=45,"SOLO LOW COST","EVITA")))))) | U86: 4 | V86: BALLOTTAGGIO | W86: =LEN(G86)-LEN(SUBSTITUTE(G86,"/",""))+1 | X86: SOTTO AI SEMITOP | Y86: =IF(AL86+AM86+AN86>=3,"Alta",IF(AL86+AM86+AN86>=2,"Medio-alta",IF(AL86+AM86+AN86=1,"Media","Bassa"))) | Z86: XI base; ballottaggio; SOS: sotto ai semitop; pluriruolo | AA86: https://www.fantacalcio.it/news/calcio-italia/06_08_2026/asta-fantacalcio-le-probabili-formazioni-della-serie-a-enilive-2026-27-495558 | https://www.fantacalcio.it/probabili-formazioni-serie-a | AB86: https://www.sosfanta.com/guida-asta-fantacalcio/fantacalcio-mantra-ecco-la-guida-allasta-2026-27-la-divisione-ruolo-per-ruolo/ | AC86: https://www.fantacalcio.it/probabili-formazioni-serie-a | https://www.fantacalcio.it/quotazioni-fantacalcio | AD86: Da valutare | AE86: =MAX(1,MIN(AV86,ROUND(AO86*1.06,0))) | AG86: 82 | AH86: 0 | AI86: 75 | AJ86: 82.7 | AK86: 50 | AL86: 1 | AM86: 1 | AN86: 1 | AO86: =MAX(1,ROUND(L86*AU86*AT86*IF(ISNUMBER(SEARCH("SUPER TOP",X86&"")),1.08,IF(AS86="Top",1.04,IF(AS86="Semitop",1,IF(AS86="Starter",0.94,IF(AS86="Scommessa",0.9,0.85))))),0)) | AP86: =IF(AR86="Non433","BASSO",IF(OR(AR86="A",AR86="Pc"),"ALTISSIMO",IF(OR(AR86="M",AR86="C",AR86="Jolly"),"ALTO",IF(OR(AR86="Dd",AR86="Ds"),"MEDIO-ALTO","MEDIO")))) | AQ86: =IF(C86="*","EVITA - FUORI LISTA",IF(AR86="Non433","NON PRIORITARIO 4-3-3",IF(AND(OR(AR86="Pc",AR86="A"),AS86="Top"),"ALL-IN CONTROLLATO",IF(AND(AE86<=8,O86>=80),"GIOIELLO / TITOLARE LOW COST",IF(OR(AS86="Top",AS86="Semitop"),"COMPRA A VALORE",IF(O86>=80,"TITOLARE DA ASPETTARE","SOLO LOW COST")))))) | AR86: =IF(G86="Por","Por",IF(ISNUMBER(SEARCH("/Pc/","/"&G86&"/")),"Pc",IF(ISNUMBER(SEARCH("/A/","/"&G86&"/")),"A",IF(ISNUMBER(SEARCH("/M/","/"&G86&"/")),"M",IF(ISNUMBER(SEARCH("/C/","/"&G86&"/")),"C",IF(ISNUMBER(SEARCH("/Dd/","/"&G86&"/")),"Dd",IF(ISNUMBER(SEARCH("/Ds/","/"&G86&"/")),"Ds",IF(ISNUMBER(SEARCH("/Dc/","/"&G86&"/")),"Dc",IF(OR(ISNUMBER(SEARCH("/E/","/"&G86&"/")),ISNUMBER(SEARCH("/W/","/"&G86&"/")),ISNUMBER(SEARCH("/T/","/"&G86&"/")),ISNUMBER(SEARCH("/B/","/"&G86&"/"))),"Jolly","Non433"))))))))) | AS86: =IF(OR(X86="SUPER TOP",X86="TOP"),"Top",IF(X86="SEMITOP","Semitop",IF(OR(ISNUMBER(SEARCH("POSSIBILI SORPRESE",X86&"")),ISNUMBER(SEARCH("SCOMMES",X86&""))),"Scommessa",IF(OR(ISNUMBER(SEARCH("FASCIA ALTA",X86&"")),ISNUMBER(SEARCH("JOLLY 1",X86&"")),O86>=85),"Starter",IF(O86>=68,"Scommessa","Low"))))) | AT86: =IF(O86>=90,1,IF(O86>=80,0.93,IF(O86>=65,0.85,0.72)))*IF(ISNUMBER(SEARCH("MERCATO",V86&"")),0.85,1)*IF(ISNUMBER(SEARCH("INFORTUN",V86&"")),0.9,1)*IF(C86="*",0.55,1) | AU86: =IFERROR(VLOOKUP(AR86,'Strategia 433'!$A$29:$B$38,2,FALSE),0.9) | AV86: =IFERROR(INDEX('Strategia 433'!$D$15:$H$24,MATCH(AR86,'Strategia 433'!$A$15:$A$24,0),MATCH(AS86,'Strategia 433'!$D$14:$H$14,0))*IF(AND(ISNUMBER(SEARCH("SUPER TOP",X86&"")),OR(AR86="Por",AR86="Pc")),1.08,1),1) | AW86: Taratura storico lega 12x500 + QUOT Fantacalcio | https://www.fantacalcio.it/quotazioni-fantacalcio | AX86: =MAX(1,ROUND(AE86*IF(AND(AR86="Pc",AS86="Top"),0.95,IF(AND(OR(AR86="A",AR86="Por",AR86="Dc"),AS86="Top"),0.90,0.85)),0))
A87: 4463 | B87: Esposito Se. | D87: Cagliari | E87: 24 | F87: A | G87: A | H87: 0 | I87: 0 | J87: 0 | K87: 20 | L87: 14 | O87: =MAX(0,MIN(99,AG87+AH87)) | P87: =IF(O87>=80,"Alta",IF(O87>=60,"Medio-alta",IF(O87>=40,"Media",IF(O87>=20,"Bassa","Minima")))) | Q87: =MAX(5,MIN(99,ROUND(IF(AI87>0,0.5*AI87+0.25*AJ87+0.2*O87+0.05*AK87,0.55*AJ87+0.32*O87+0.08*AK87+0.05*MIN(100,L87*4))+MIN(6,(LEN(G87)-LEN(SUBSTITUTE(G87,"/","")))*2.5)-IF(C87="*",3,0),0))) | R87: =MAX(5,MIN(99,ROUND(50+0.65*(Q87-50)+0.2*(O87-60)-0.55*(AJ87-50),0))) | S87: =IF(Q87>=90,"S",IF(Q87>=80,"A",IF(Q87>=70,"B",IF(Q87>=60,"C",IF(Q87>=48,"D","E"))))) | T87: =IF(AND(Q87>=90,O87>=62),"PUNTA FORTE",IF(AND(Q87>=80,O87>=58),"COMPRA",IF(AND(R87>=75,Q87>=62,O87>=55),"AFFARE / ATTACCA",IF(AND(Q87>=69,O87>=50),"AL GIUSTO PREZZO",IF(AND(Q87>=58,O87>=40),"JOLLY / SCOMMESSA",IF(Q87>=45,"SOLO LOW COST","EVITA")))))) | U87: 1 | V87: MERCATO | W87: =LEN(G87)-LEN(SUBSTITUTE(G87,"/",""))+1 | X87: MERCATO | Y87: =IF(AL87+AM87+AN87>=3,"Alta",IF(AL87+AM87+AN87>=2,"Medio-alta",IF(AL87+AM87+AN87=1,"Media","Bassa"))) | Z87: SOS: mercato | AA87: https://www.fantacalcio.it/news/calcio-italia/06_08_2026/asta-fantacalcio-le-probabili-formazioni-della-serie-a-enilive-2026-27-495558 | https://www.fantacalcio.it/probabili-formazioni-serie-a | AB87: https://www.sosfanta.com/guida-asta-fantacalcio/fantacalcio-mantra-ecco-la-guida-allasta-2026-27-la-divisione-ruolo-per-ruolo/ | AC87: https://www.fantacalcio.it/probabili-formazioni-serie-a | https://www.fantacalcio.it/quotazioni-fantacalcio | AD87: Da valutare | AE87: =MAX(1,MIN(AV87,ROUND(AO87*1.06,0))) | AG87: 32 | AH87: 0 | AI87: 45 | AJ87: 66.5 | AK87: 50 | AL87: 0 | AM87: 1 | AN87: 0 | AO87: =MAX(1,ROUND(L87*AU87*AT87*IF(ISNUMBER(SEARCH("SUPER TOP",X87&"")),1.08,IF(AS87="Top",1.04,IF(AS87="Semitop",1,IF(AS87="Starter",0.94,IF(AS87="Scommessa",0.9,0.85))))),0)) | AP87: =IF(AR87="Non433","BASSO",IF(OR(AR87="A",AR87="Pc"),"ALTISSIMO",IF(OR(AR87="M",AR87="C",AR87="Jolly"),"ALTO",IF(OR(AR87="Dd",AR87="Ds"),"MEDIO-ALTO","MEDIO")))) | AQ87: =IF(C87="*","EVITA - FUORI LISTA",IF(AR87="Non433","NON PRIORITARIO 4-3-3",IF(AND(OR(AR87="Pc",AR87="A"),AS87="Top"),"ALL-IN CONTROLLATO",IF(AND(AE87<=8,O87>=80),"GIOIELLO / TITOLARE LOW COST",IF(OR(AS87="Top",AS87="Semitop"),"COMPRA A VALORE",IF(O87>=80,"TITOLARE DA ASPETTARE","SOLO LOW COST")))))) | AR87: =IF(G87="Por","Por",IF(ISNUMBER(SEARCH("/Pc/","/"&G87&"/")),"Pc",IF(ISNUMBER(SEARCH("/A/","/"&G87&"/")),"A",IF(ISNUMBER(SEARCH("/M/","/"&G87&"/")),"M",IF(ISNUMBER(SEARCH("/C/","/"&G87&"/")),"C",IF(ISNUMBER(SEARCH("/Dd/","/"&G87&"/")),"Dd",IF(ISNUMBER(SEARCH("/Ds/","/"&G87&"/")),"Ds",IF(ISNUMBER(SEARCH("/Dc/","/"&G87&"/")),"Dc",IF(OR(ISNUMBER(SEARCH("/E/","/"&G87&"/")),ISNUMBER(SEARCH("/W/","/"&G87&"/")),ISNUMBER(SEARCH("/T/","/"&G87&"/")),ISNUMBER(SEARCH("/B/","/"&G87&"/"))),"Jolly","Non433"))))))))) | AS87: =IF(OR(X87="SUPER TOP",X87="TOP"),"Top",IF(X87="SEMITOP","Semitop",IF(OR(ISNUMBER(SEARCH("POSSIBILI SORPRESE",X87&"")),ISNUMBER(SEARCH("SCOMMES",X87&""))),"Scommessa",IF(OR(ISNUMBER(SEARCH("FASCIA ALTA",X87&"")),ISNUMBER(SEARCH("JOLLY 1",X87&"")),O87>=85),"Starter",IF(O87>=68,"Scommessa","Low"))))) | AT87: =IF(O87>=90,1,IF(O87>=80,0.93,IF(O87>=65,0.85,0.72)))*IF(ISNUMBER(SEARCH("MERCATO",V87&"")),0.85,1)*IF(ISNUMBER(SEARCH("INFORTUN",V87&"")),0.9,1)*IF(C87="*",0.55,1) | AU87: =IFERROR(VLOOKUP(AR87,'Strategia 433'!$A$29:$B$38,2,FALSE),0.9) | AV87: =IFERROR(INDEX('Strategia 433'!$D$15:$H$24,MATCH(AR87,'Strategia 433'!$A$15:$A$24,0),MATCH(AS87,'Strategia 433'!$D$14:$H$14,0))*IF(AND(ISNUMBER(SEARCH("SUPER TOP",X87&"")),OR(AR87="Por",AR87="Pc")),1.08,1),1) | AW87: Taratura storico lega 12x500 + QUOT Fantacalcio | https://www.fantacalcio.it/quotazioni-fantacalcio | AX87: =MAX(1,ROUND(AE87*IF(AND(AR87="Pc",AS87="Top"),0.95,IF(AND(OR(AR87="A",AR87="Por",AR87="Dc"),AS87="Top"),0.90,0.85)),0))
A88: 5844 | B88: Thorstvedt | D88: Sassuolo | E88: 27 | F88: C | G88: C/T | H88: 1 | I88: 6 | J88: 6 | K88: 20 | L88: 10 | O88: =MAX(0,MIN(99,AG88+AH88)) | P88: =IF(O88>=80,"Alta",IF(O88>=60,"Medio-alta",IF(O88>=40,"Media",IF(O88>=20,"Bassa","Minima")))) | Q88: =MAX(5,MIN(99,ROUND(IF(AI88>0,0.5*AI88+0.25*AJ88+0.2*O88+0.05*AK88,0.55*AJ88+0.32*O88+0.08*AK88+0.05*MIN(100,L88*4))+MIN(6,(LEN(G88)-LEN(SUBSTITUTE(G88,"/","")))*2.5)-IF(C88="*",3,0),0))) | R88: =MAX(5,MIN(99,ROUND(50+0.65*(Q88-50)+0.2*(O88-60)-0.55*(AJ88-50),0))) | S88: =IF(Q88>=90,"S",IF(Q88>=80,"A",IF(Q88>=70,"B",IF(Q88>=60,"C",IF(Q88>=48,"D","E"))))) | T88: =IF(AND(Q88>=90,O88>=62),"PUNTA FORTE",IF(AND(Q88>=80,O88>=58),"COMPRA",IF(AND(R88>=75,Q88>=62,O88>=55),"AFFARE / ATTACCA",IF(AND(Q88>=69,O88>=50),"AL GIUSTO PREZZO",IF(AND(Q88>=58,O88>=40),"JOLLY / SCOMMESSA",IF(Q88>=45,"SOLO LOW COST","EVITA")))))) | U88: 4 | V88: BASSO | W88: =LEN(G88)-LEN(SUBSTITUTE(G88,"/",""))+1 | X88: SOTTO AI SEMITOP | Y88: =IF(AL88+AM88+AN88>=3,"Alta",IF(AL88+AM88+AN88>=2,"Medio-alta",IF(AL88+AM88+AN88=1,"Media","Bassa"))) | Z88: XI base; SOS: sotto ai semitop; pluriruolo | AA88: https://www.fantacalcio.it/news/calcio-italia/06_08_2026/asta-fantacalcio-le-probabili-formazioni-della-serie-a-enilive-2026-27-495558 | https://www.fantacalcio.it/probabili-formazioni-serie-a | AB88: https://www.sosfanta.com/guida-asta-fantacalcio/fantacalcio-mantra-ecco-la-guida-allasta-2026-27-la-divisione-ruolo-per-ruolo/ | AC88: https://www.fantacalcio.it/probabili-formazioni-serie-a | https://www.fantacalcio.it/quotazioni-fantacalcio | AD88: Da valutare | AE88: =MAX(1,MIN(AV88,ROUND(AO88*1.06,0))) | AG88: 91 | AH88: 0 | AI88: 75 | AJ88: 81.1 | AK88: 50 | AL88: 1 | AM88: 1 | AN88: 0 | AO88: =MAX(1,ROUND(L88*AU88*AT88*IF(ISNUMBER(SEARCH("SUPER TOP",X88&"")),1.08,IF(AS88="Top",1.04,IF(AS88="Semitop",1,IF(AS88="Starter",0.94,IF(AS88="Scommessa",0.9,0.85))))),0)) | AP88: =IF(AR88="Non433","BASSO",IF(OR(AR88="A",AR88="Pc"),"ALTISSIMO",IF(OR(AR88="M",AR88="C",AR88="Jolly"),"ALTO",IF(OR(AR88="Dd",AR88="Ds"),"MEDIO-ALTO","MEDIO")))) | AQ88: =IF(C88="*","EVITA - FUORI LISTA",IF(AR88="Non433","NON PRIORITARIO 4-3-3",IF(AND(OR(AR88="Pc",AR88="A"),AS88="Top"),"ALL-IN CONTROLLATO",IF(AND(AE88<=8,O88>=80),"GIOIELLO / TITOLARE LOW COST",IF(OR(AS88="Top",AS88="Semitop"),"COMPRA A VALORE",IF(O88>=80,"TITOLARE DA ASPETTARE","SOLO LOW COST")))))) | AR88: =IF(G88="Por","Por",IF(ISNUMBER(SEARCH("/Pc/","/"&G88&"/")),"Pc",IF(ISNUMBER(SEARCH("/A/","/"&G88&"/")),"A",IF(ISNUMBER(SEARCH("/M/","/"&G88&"/")),"M",IF(ISNUMBER(SEARCH("/C/","/"&G88&"/")),"C",IF(ISNUMBER(SEARCH("/Dd/","/"&G88&"/")),"Dd",IF(ISNUMBER(SEARCH("/Ds/","/"&G88&"/")),"Ds",IF(ISNUMBER(SEARCH("/Dc/","/"&G88&"/")),"Dc",IF(OR(ISNUMBER(SEARCH("/E/","/"&G88&"/")),ISNUMBER(SEARCH("/W/","/"&G88&"/")),ISNUMBER(SEARCH("/T/","/"&G88&"/")),ISNUMBER(SEARCH("/B/","/"&G88&"/"))),"Jolly","Non433"))))))))) | AS88: =IF(OR(X88="SUPER TOP",X88="TOP"),"Top",IF(X88="SEMITOP","Semitop",IF(OR(ISNUMBER(SEARCH("POSSIBILI SORPRESE",X88&"")),ISNUMBER(SEARCH("SCOMMES",X88&""))),"Scommessa",IF(OR(ISNUMBER(SEARCH("FASCIA ALTA",X88&"")),ISNUMBER(SEARCH("JOLLY 1",X88&"")),O88>=85),"Starter",IF(O88>=68,"Scommessa","Low"))))) | AT88: =IF(O88>=90,1,IF(O88>=80,0.93,IF(O88>=65,0.85,0.72)))*IF(ISNUMBER(SEARCH("MERCATO",V88&"")),0.85,1)*IF(ISNUMBER(SEARCH("INFORTUN",V88&"")),0.9,1)*IF(C88="*",0.55,1) | AU88: =IFERROR(VLOOKUP(AR88,'Strategia 433'!$A$29:$B$38,2,FALSE),0.9) | AV88: =IFERROR(INDEX('Strategia 433'!$D$15:$H$24,MATCH(AR88,'Strategia 433'!$A$15:$A$24,0),MATCH(AS88,'Strategia 433'!$D$14:$H$14,0))*IF(AND(ISNUMBER(SEARCH("SUPER TOP",X88&"")),OR(AR88="Por",AR88="Pc")),1.08,1),1) | AW88: Taratura storico lega 12x500 + QUOT Fantacalcio | https://www.fantacalcio.it/quotazioni-fantacalcio | AX88: =MAX(1,ROUND(AE88*IF(AND(AR88="Pc",AS88="Top"),0.95,IF(AND(OR(AR88="A",AR88="Por",AR88="Dc"),AS88="Top"),0.90,0.85)),0))
A89: 5800 | B89: Gudmundsson A. | D89: Fiorentina | E89: 29 | F89: C | G89: T/A | H89: 0 | I89: 0 | J89: 0 | K89: 20 | L89: 12 | O89: =MAX(0,MIN(99,AG89+AH89)) | P89: =IF(O89>=80,"Alta",IF(O89>=60,"Medio-alta",IF(O89>=40,"Media",IF(O89>=20,"Bassa","Minima")))) | Q89: =MAX(5,MIN(99,ROUND(IF(AI89>0,0.5*AI89+0.25*AJ89+0.2*O89+0.05*AK89,0.55*AJ89+0.32*O89+0.08*AK89+0.05*MIN(100,L89*4))+MIN(6,(LEN(G89)-LEN(SUBSTITUTE(G89,"/","")))*2.5)-IF(C89="*",3,0),0))) | R89: =MAX(5,MIN(99,ROUND(50+0.65*(Q89-50)+0.2*(O89-60)-0.55*(AJ89-50),0))) | S89: =IF(Q89>=90,"S",IF(Q89>=80,"A",IF(Q89>=70,"B",IF(Q89>=60,"C",IF(Q89>=48,"D","E"))))) | T89: =IF(AND(Q89>=90,O89>=62),"PUNTA FORTE",IF(AND(Q89>=80,O89>=58),"COMPRA",IF(AND(R89>=75,Q89>=62,O89>=55),"AFFARE / ATTACCA",IF(AND(Q89>=69,O89>=50),"AL GIUSTO PREZZO",IF(AND(Q89>=58,O89>=40),"JOLLY / SCOMMESSA",IF(Q89>=45,"SOLO LOW COST","EVITA")))))) | U89: 4 | V89: MERCATO - situazione da monitorare | W89: =LEN(G89)-LEN(SUBSTITUTE(G89,"/",""))+1 | X89: SOTTO AI SEMITOP | Y89: =IF(AL89+AM89+AN89>=3,"Alta",IF(AL89+AM89+AN89>=2,"Medio-alta",IF(AL89+AM89+AN89=1,"Media","Bassa"))) | Z89: XI base; SOS: semitop; pluriruolo | AA89: https://www.fantacalcio.it/news/calcio-italia/06_08_2026/asta-fantacalcio-le-probabili-formazioni-della-serie-a-enilive-2026-27-495558 | https://www.fantacalcio.it/probabili-formazioni-serie-a | AB89: https://www.sosfanta.com/guida-asta-fantacalcio/fantacalcio-mantra-ecco-la-guida-allasta-2026-27-la-divisione-ruolo-per-ruolo/ | AC89: https://www.fantacalcio.it/probabili-formazioni-serie-a | https://www.fantacalcio.it/quotazioni-fantacalcio | AD89: Da valutare | AE89: =MAX(1,MIN(AV89,ROUND(AO89*1.06,0))) | AG89: 94 | AH89: 0 | AI89: 82 | AJ89: 81.1 | AK89: 50 | AL89: 1 | AM89: 1 | AN89: 1 | AO89: =MAX(1,ROUND(L89*AU89*AT89*IF(ISNUMBER(SEARCH("SUPER TOP",X89&"")),1.08,IF(AS89="Top",1.04,IF(AS89="Semitop",1,IF(AS89="Starter",0.94,IF(AS89="Scommessa",0.9,0.85))))),0)) | AP89: =IF(AR89="Non433","BASSO",IF(OR(AR89="A",AR89="Pc"),"ALTISSIMO",IF(OR(AR89="M",AR89="C",AR89="Jolly"),"ALTO",IF(OR(AR89="Dd",AR89="Ds"),"MEDIO-ALTO","MEDIO")))) | AQ89: =IF(C89="*","EVITA - FUORI LISTA",IF(AR89="Non433","NON PRIORITARIO 4-3-3",IF(AND(OR(AR89="Pc",AR89="A"),AS89="Top"),"ALL-IN CONTROLLATO",IF(AND(AE89<=8,O89>=80),"GIOIELLO / TITOLARE LOW COST",IF(OR(AS89="Top",AS89="Semitop"),"COMPRA A VALORE",IF(O89>=80,"TITOLARE DA ASPETTARE","SOLO LOW COST")))))) | AR89: =IF(G89="Por","Por",IF(ISNUMBER(SEARCH("/Pc/","/"&G89&"/")),"Pc",IF(ISNUMBER(SEARCH("/A/","/"&G89&"/")),"A",IF(ISNUMBER(SEARCH("/M/","/"&G89&"/")),"M",IF(ISNUMBER(SEARCH("/C/","/"&G89&"/")),"C",IF(ISNUMBER(SEARCH("/Dd/","/"&G89&"/")),"Dd",IF(ISNUMBER(SEARCH("/Ds/","/"&G89&"/")),"Ds",IF(ISNUMBER(SEARCH("/Dc/","/"&G89&"/")),"Dc",IF(OR(ISNUMBER(SEARCH("/E/","/"&G89&"/")),ISNUMBER(SEARCH("/W/","/"&G89&"/")),ISNUMBER(SEARCH("/T/","/"&G89&"/")),ISNUMBER(SEARCH("/B/","/"&G89&"/"))),"Jolly","Non433"))))))))) | AS89: =IF(OR(X89="SUPER TOP",X89="TOP"),"Top",IF(X89="SEMITOP","Semitop",IF(OR(ISNUMBER(SEARCH("POSSIBILI SORPRESE",X89&"")),ISNUMBER(SEARCH("SCOMMES",X89&""))),"Scommessa",IF(OR(ISNUMBER(SEARCH("FASCIA ALTA",X89&"")),ISNUMBER(SEARCH("JOLLY 1",X89&"")),O89>=85),"Starter",IF(O89>=68,"Scommessa","Low"))))) | AT89: =IF(O89>=90,1,IF(O89>=80,0.93,IF(O89>=65,0.85,0.72)))*IF(ISNUMBER(SEARCH("MERCATO",V89&"")),0.85,1)*IF(ISNUMBER(SEARCH("INFORTUN",V89&"")),0.9,1)*IF(C89="*",0.55,1) | AU89: =IFERROR(VLOOKUP(AR89,'Strategia 433'!$A$29:$B$38,2,FALSE),0.9) | AV89: =IFERROR(INDEX('Strategia 433'!$D$15:$H$24,MATCH(AR89,'Strategia 433'!$A$15:$A$24,0),MATCH(AS89,'Strategia 433'!$D$14:$H$14,0))*IF(AND(ISNUMBER(SEARCH("SUPER TOP",X89&"")),OR(AR89="Por",AR89="Pc")),1.08,1),1) | AW89: Taratura storico lega 12x500 + QUOT Fantacalcio | https://www.fantacalcio.it/quotazioni-fantacalcio | AX89: =MAX(1,ROUND(AE89*IF(AND(AR89="Pc",AS89="Top"),0.95,IF(AND(OR(AR89="A",AR89="Por",AR89="Dc"),AS89="Top"),0.90,0.85)),0))
A90: 7129 | B90: Rodriguez Je. | D90: Como | E90: 21 | F90: C | G90: W/A | H90: 1 | I90: 5.5 | J90: 5.5 | K90: 16 | L90: 11 | O90: =MAX(0,MIN(99,AG90+AH90)) | P90: =IF(O90>=80,"Alta",IF(O90>=60,"Medio-alta",IF(O90>=40,"Media",IF(O90>=20,"Bassa","Minima")))) | Q90: =MAX(5,MIN(99,ROUND(IF(AI90>0,0.5*AI90+0.25*AJ90+0.2*O90+0.05*AK90,0.55*AJ90+0.32*O90+0.08*AK90+0.05*MIN(100,L90*4))+MIN(6,(LEN(G90)-LEN(SUBSTITUTE(G90,"/","")))*2.5)-IF(C90="*",3,0),0))) | R90: =MAX(5,MIN(99,ROUND(50+0.65*(Q90-50)+0.2*(O90-60)-0.55*(AJ90-50),0))) | S90: =IF(Q90>=90,"S",IF(Q90>=80,"A",IF(Q90>=70,"B",IF(Q90>=60,"C",IF(Q90>=48,"D","E"))))) | T90: =IF(AND(Q90>=90,O90>=62),"PUNTA FORTE",IF(AND(Q90>=80,O90>=58),"COMPRA",IF(AND(R90>=75,Q90>=62,O90>=55),"AFFARE / ATTACCA",IF(AND(Q90>=69,O90>=50),"AL GIUSTO PREZZO",IF(AND(Q90>=58,O90>=40),"JOLLY / SCOMMESSA",IF(Q90>=45,"SOLO LOW COST","EVITA")))))) | U90: 3 | V90: BALLOTTAGGIO | W90: =LEN(G90)-LEN(SUBSTITUTE(G90,"/",""))+1 | X90: FASCIA ALTA | Y90: =IF(AL90+AM90+AN90>=3,"Alta",IF(AL90+AM90+AN90>=2,"Medio-alta",IF(AL90+AM90+AN90=1,"Media","Bassa"))) | Z90: ballottaggio; SOS: sotto ai semitop; pluriruolo | AA90: https://www.fantacalcio.it/news/calcio-italia/06_08_2026/asta-fantacalcio-le-probabili-formazioni-della-serie-a-enilive-2026-27-495558 | https://www.fantacalcio.it/probabili-formazioni-serie-a | AB90: https://www.sosfanta.com/guida-asta-fantacalcio/fantacalcio-mantra-ecco-la-guida-allasta-2026-27-la-divisione-ruolo-per-ruolo/ | AC90: https://www.fantacalcio.it/probabili-formazioni-serie-a | https://www.fantacalcio.it/quotazioni-fantacalcio | AD90: Da valutare | AE90: =MAX(1,MIN(AV90,ROUND(AO90*1.06,0))) | AG90: 82 | AH90: 0 | AI90: 75 | AJ90: 81.1 | AK90: 32 | AL90: 1 | AM90: 1 | AN90: 1 | AO90: =MAX(1,ROUND(L90*AU90*AT90*IF(ISNUMBER(SEARCH("SUPER TOP",X90&"")),1.08,IF(AS90="Top",1.04,IF(AS90="Semitop",1,IF(AS90="Starter",0.94,IF(AS90="Scommessa",0.9,0.85))))),0)) | AP90: =IF(AR90="Non433","BASSO",IF(OR(AR90="A",AR90="Pc"),"ALTISSIMO",IF(OR(AR90="M",AR90="C",AR90="Jolly"),"ALTO",IF(OR(AR90="Dd",AR90="Ds"),"MEDIO-ALTO","MEDIO")))) | AQ90: =IF(C90="*","EVITA - FUORI LISTA",IF(AR90="Non433","NON PRIORITARIO 4-3-3",IF(AND(OR(AR90="Pc",AR90="A"),AS90="Top"),"ALL-IN CONTROLLATO",IF(AND(AE90<=8,O90>=80),"GIOIELLO / TITOLARE LOW COST",IF(OR(AS90="Top",AS90="Semitop"),"COMPRA A VALORE",IF(O90>=80,"TITOLARE DA ASPETTARE","SOLO LOW COST")))))) | AR90: =IF(G90="Por","Por",IF(ISNUMBER(SEARCH("/Pc/","/"&G90&"/")),"Pc",IF(ISNUMBER(SEARCH("/A/","/"&G90&"/")),"A",IF(ISNUMBER(SEARCH("/M/","/"&G90&"/")),"M",IF(ISNUMBER(SEARCH("/C/","/"&G90&"/")),"C",IF(ISNUMBER(SEARCH("/Dd/","/"&G90&"/")),"Dd",IF(ISNUMBER(SEARCH("/Ds/","/"&G90&"/")),"Ds",IF(ISNUMBER(SEARCH("/Dc/","/"&G90&"/")),"Dc",IF(OR(ISNUMBER(SEARCH("/E/","/"&G90&"/")),ISNUMBER(SEARCH("/W/","/"&G90&"/")),ISNUMBER(SEARCH("/T/","/"&G90&"/")),ISNUMBER(SEARCH("/B/","/"&G90&"/"))),"Jolly","Non433"))))))))) | AS90: =IF(OR(X90="SUPER TOP",X90="TOP"),"Top",IF(X90="SEMITOP","Semitop",IF(OR(ISNUMBER(SEARCH("POSSIBILI SORPRESE",X90&"")),ISNUMBER(SEARCH("SCOMMES",X90&""))),"Scommessa",IF(OR(ISNUMBER(SEARCH("FASCIA ALTA",X90&"")),ISNUMBER(SEARCH("JOLLY 1",X90&"")),O90>=85),"Starter",IF(O90>=68,"Scommessa","Low"))))) | AT90: =IF(O90>=90,1,IF(O90>=80,0.93,IF(O90>=65,0.85,0.72)))*IF(ISNUMBER(SEARCH("MERCATO",V90&"")),0.85,1)*IF(ISNUMBER(SEARCH("INFORTUN",V90&"")),0.9,1)*IF(C90="*",0.55,1) | AU90: =IFERROR(VLOOKUP(AR90,'Strategia 433'!$A$29:$B$38,2,FALSE),0.9) | AV90: =IFERROR(INDEX('Strategia 433'!$D$15:$H$24,MATCH(AR90,'Strategia 433'!$A$15:$A$24,0),MATCH(AS90,'Strategia 433'!$D$14:$H$14,0))*IF(AND(ISNUMBER(SEARCH("SUPER TOP",X90&"")),OR(AR90="Por",AR90="Pc")),1.08,1),1) | AW90: Taratura storico lega 12x500 + QUOT Fantacalcio | https://www.fantacalcio.it/quotazioni-fantacalcio | AX90: =MAX(1,ROUND(AE90*IF(AND(AR90="Pc",AS90="Top"),0.95,IF(AND(OR(AR90="A",AR90="Por",AR90="Dc"),AS90="Top"),0.90,0.85)),0))
A91: 2816 | B91: Di Lorenzo | D91: Napoli | E91: 33 | F91: D | G91: Dd/E | H91: 1 | I91: 6.5 | J91: 6.5 | K91: 20 | L91: 12 | O91: =MAX(0,MIN(99,AG91+AH91)) | P91: =IF(O91>=80,"Alta",IF(O91>=60,"Medio-alta",IF(O91>=40,"Media",IF(O91>=20,"Bassa","Minima")))) | Q91: =MAX(5,MIN(99,ROUND(IF(AI91>0,0.5*AI91+0.25*AJ91+0.2*O91+0.05*AK91,0.55*AJ91+0.32*O91+0.08*AK91+0.05*MIN(100,L91*4))+MIN(6,(LEN(G91)-LEN(SUBSTITUTE(G91,"/","")))*2.5)-IF(C91="*",3,0),0))) | R91: =MAX(5,MIN(99,ROUND(50+0.65*(Q91-50)+0.2*(O91-60)-0.55*(AJ91-50),0))) | S91: =IF(Q91>=90,"S",IF(Q91>=80,"A",IF(Q91>=70,"B",IF(Q91>=60,"C",IF(Q91>=48,"D","E"))))) | T91: =IF(AND(Q91>=90,O91>=62),"PUNTA FORTE",IF(AND(Q91>=80,O91>=58),"COMPRA",IF(AND(R91>=75,Q91>=62,O91>=55),"AFFARE / ATTACCA",IF(AND(Q91>=69,O91>=50),"AL GIUSTO PREZZO",IF(AND(Q91>=58,O91>=40),"JOLLY / SCOMMESSA",IF(Q91>=45,"SOLO LOW COST","EVITA")))))) | U91: 5 | V91: BASSO | W91: =LEN(G91)-LEN(SUBSTITUTE(G91,"/",""))+1 | X91: TOP | Y91: =IF(AL91+AM91+AN91>=3,"Alta",IF(AL91+AM91+AN91>=2,"Medio-alta",IF(AL91+AM91+AN91=1,"Media","Bassa"))) | Z91: XI base; SOS: top; pluriruolo | AA91: https://www.fantacalcio.it/news/calcio-italia/06_08_2026/asta-fantacalcio-le-probabili-formazioni-della-serie-a-enilive-2026-27-495558 | https://www.fantacalcio.it/probabili-formazioni-serie-a | AB91: https://www.sosfanta.com/guida-asta-fantacalcio/fantacalcio-mantra-ecco-la-guida-allasta-2026-27-la-divisione-ruolo-per-ruolo/ | AC91: https://www.fantacalcio.it/probabili-formazioni-serie-a | https://www.fantacalcio.it/quotazioni-fantacalcio | AD91: Da valutare | AE91: =MAX(1,MIN(AV91,ROUND(AO91*1.06,0))) | AG91: 98 | AH91: 0 | AI91: 90 | AJ91: 93.1 | AK91: 59 | AL91: 1 | AM91: 1 | AN91: 1 | AO91: =MAX(1,ROUND(L91*AU91*AT91*IF(ISNUMBER(SEARCH("SUPER TOP",X91&"")),1.08,IF(AS91="Top",1.04,IF(AS91="Semitop",1,IF(AS91="Starter",0.94,IF(AS91="Scommessa",0.9,0.85))))),0)) | AP91: =IF(AR91="Non433","BASSO",IF(OR(AR91="A",AR91="Pc"),"ALTISSIMO",IF(OR(AR91="M",AR91="C",AR91="Jolly"),"ALTO",IF(OR(AR91="Dd",AR91="Ds"),"MEDIO-ALTO","MEDIO")))) | AQ91: =IF(C91="*","EVITA - FUORI LISTA",IF(AR91="Non433","NON PRIORITARIO 4-3-3",IF(AND(OR(AR91="Pc",AR91="A"),AS91="Top"),"ALL-IN CONTROLLATO",IF(AND(AE91<=8,O91>=80),"GIOIELLO / TITOLARE LOW COST",IF(OR(AS91="Top",AS91="Semitop"),"COMPRA A VALORE",IF(O91>=80,"TITOLARE DA ASPETTARE","SOLO LOW COST")))))) | AR91: =IF(G91="Por","Por",IF(ISNUMBER(SEARCH("/Pc/","/"&G91&"/")),"Pc",IF(ISNUMBER(SEARCH("/A/","/"&G91&"/")),"A",IF(ISNUMBER(SEARCH("/M/","/"&G91&"/")),"M",IF(ISNUMBER(SEARCH("/C/","/"&G91&"/")),"C",IF(ISNUMBER(SEARCH("/Dd/","/"&G91&"/")),"Dd",IF(ISNUMBER(SEARCH("/Ds/","/"&G91&"/")),"Ds",IF(ISNUMBER(SEARCH("/Dc/","/"&G91&"/")),"Dc",IF(OR(ISNUMBER(SEARCH("/E/","/"&G91&"/")),ISNUMBER(SEARCH("/W/","/"&G91&"/")),ISNUMBER(SEARCH("/T/","/"&G91&"/")),ISNUMBER(SEARCH("/B/","/"&G91&"/"))),"Jolly","Non433"))))))))) | AS91: =IF(OR(X91="SUPER TOP",X91="TOP"),"Top",IF(X91="SEMITOP","Semitop",IF(OR(ISNUMBER(SEARCH("POSSIBILI SORPRESE",X91&"")),ISNUMBER(SEARCH("SCOMMES",X91&""))),"Scommessa",IF(OR(ISNUMBER(SEARCH("FASCIA ALTA",X91&"")),ISNUMBER(SEARCH("JOLLY 1",X91&"")),O91>=85),"Starter",IF(O91>=68,"Scommessa","Low"))))) | AT91: =IF(O91>=90,1,IF(O91>=80,0.93,IF(O91>=65,0.85,0.72)))*IF(ISNUMBER(SEARCH("MERCATO",V91&"")),0.85,1)*IF(ISNUMBER(SEARCH("INFORTUN",V91&"")),0.9,1)*IF(C91="*",0.55,1) | AU91: =IFERROR(VLOOKUP(AR91,'Strategia 433'!$A$29:$B$38,2,FALSE),0.9) | AV91: =IFERROR(INDEX('Strategia 433'!$D$15:$H$24,MATCH(AR91,'Strategia 433'!$A$15:$A$24,0),MATCH(AS91,'Strategia 433'!$D$14:$H$14,0))*IF(AND(ISNUMBER(SEARCH("SUPER TOP",X91&"")),OR(AR91="Por",AR91="Pc")),1.08,1),1) | AW91: Taratura storico lega 12x500 + QUOT Fantacalcio | https://www.fantacalcio.it/quotazioni-fantacalcio | AX91: =MAX(1,ROUND(AE91*IF(AND(AR91="Pc",AS91="Top"),0.95,IF(AND(OR(AR91="A",AR91="Por",AR91="Dc"),AS91="Top"),0.90,0.85)),0))
A92: 2521 | B92: De Gea | D92: Fiorentina | E92: 36 | F92: P | G92: Por | H92: 1 | I92: 5.5 | J92: 1.5 | K92: 20 | L92: 12 | O92: =MAX(0,MIN(99,AG92+AH92)) | P92: =IF(O92>=80,"Alta",IF(O92>=60,"Medio-alta",IF(O92>=40,"Media",IF(O92>=20,"Bassa","Minima")))) | Q92: =MAX(5,MIN(99,ROUND(IF(AI92>0,0.5*AI92+0.25*AJ92+0.2*O92+0.05*AK92,0.55*AJ92+0.32*O92+0.08*AK92+0.05*MIN(100,L92*4))+MIN(6,(LEN(G92)-LEN(SUBSTITUTE(G92,"/","")))*2.5)-IF(C92="*",3,0),0))) | R92: =MAX(5,MIN(99,ROUND(50+0.65*(Q92-50)+0.2*(O92-60)-0.55*(AJ92-50),0))) | S92: =IF(Q92>=90,"S",IF(Q92>=80,"A",IF(Q92>=70,"B",IF(Q92>=60,"C",IF(Q92>=48,"D","E"))))) | T92: =IF(AND(Q92>=90,O92>=62),"PUNTA FORTE",IF(AND(Q92>=80,O92>=58),"COMPRA",IF(AND(R92>=75,Q92>=62,O92>=55),"AFFARE / ATTACCA",IF(AND(Q92>=69,O92>=50),"AL GIUSTO PREZZO",IF(AND(Q92>=58,O92>=40),"JOLLY / SCOMMESSA",IF(Q92>=45,"SOLO LOW COST","EVITA")))))) | U92: 4 | V92: BASSO | W92: =LEN(G92)-LEN(SUBSTITUTE(G92,"/",""))+1 | X92: FASCIA ALTA | Y92: =IF(AL92+AM92+AN92>=3,"Alta",IF(AL92+AM92+AN92>=2,"Medio-alta",IF(AL92+AM92+AN92=1,"Media","Bassa"))) | Z92: XI base; SOS: fascia alta | AA92: https://www.fantacalcio.it/news/calcio-italia/06_08_2026/asta-fantacalcio-le-probabili-formazioni-della-serie-a-enilive-2026-27-495558 | https://www.fantacalcio.it/probabili-formazioni-serie-a | AB92: https://www.sosfanta.com/guida-asta-fantacalcio/fantacalcio-mantra-ecco-la-guida-allasta-2026-27-la-divisione-ruolo-per-ruolo/ | AC92: https://www.fantacalcio.it/probabili-formazioni-serie-a | https://www.fantacalcio.it/quotazioni-fantacalcio | AD92: Da valutare | AE92: =MAX(1,MIN(AV92,ROUND(AO92*1.06,0))) | AG92: 98 | AH92: 0 | AI92: 69 | AJ92: 89.1 | AK92: 5 | AL92: 1 | AM92: 1 | AN92: 1 | AO92: =MAX(1,ROUND(L92*AU92*AT92*IF(ISNUMBER(SEARCH("SUPER TOP",X92&"")),1.08,IF(AS92="Top",1.04,IF(AS92="Semitop",1,IF(AS92="Starter",0.94,IF(AS92="Scommessa",0.9,0.85))))),0)) | AP92: =IF(AR92="Non433","BASSO",IF(OR(AR92="A",AR92="Pc"),"ALTISSIMO",IF(OR(AR92="M",AR92="C",AR92="Jolly"),"ALTO",IF(OR(AR92="Dd",AR92="Ds"),"MEDIO-ALTO","MEDIO")))) | AQ92: =IF(C92="*","EVITA - FUORI LISTA",IF(AR92="Non433","NON PRIORITARIO 4-3-3",IF(AND(OR(AR92="Pc",AR92="A"),AS92="Top"),"ALL-IN CONTROLLATO",IF(AND(AE92<=8,O92>=80),"GIOIELLO / TITOLARE LOW COST",IF(OR(AS92="Top",AS92="Semitop"),"COMPRA A VALORE",IF(O92>=80,"TITOLARE DA ASPETTARE","SOLO LOW COST")))))) | AR92: =IF(G92="Por","Por",IF(ISNUMBER(SEARCH("/Pc/","/"&G92&"/")),"Pc",IF(ISNUMBER(SEARCH("/A/","/"&G92&"/")),"A",IF(ISNUMBER(SEARCH("/M/","/"&G92&"/")),"M",IF(ISNUMBER(SEARCH("/C/","/"&G92&"/")),"C",IF(ISNUMBER(SEARCH("/Dd/","/"&G92&"/")),"Dd",IF(ISNUMBER(SEARCH("/Ds/","/"&G92&"/")),"Ds",IF(ISNUMBER(SEARCH("/Dc/","/"&G92&"/")),"Dc",IF(OR(ISNUMBER(SEARCH("/E/","/"&G92&"/")),ISNUMBER(SEARCH("/W/","/"&G92&"/")),ISNUMBER(SEARCH("/T/","/"&G92&"/")),ISNUMBER(SEARCH("/B/","/"&G92&"/"))),"Jolly","Non433"))))))))) | AS92: =IF(OR(X92="SUPER TOP",X92="TOP"),"Top",IF(X92="SEMITOP","Semitop",IF(OR(ISNUMBER(SEARCH("POSSIBILI SORPRESE",X92&"")),ISNUMBER(SEARCH("SCOMMES",X92&""))),"Scommessa",IF(OR(ISNUMBER(SEARCH("FASCIA ALTA",X92&"")),ISNUMBER(SEARCH("JOLLY 1",X92&"")),O92>=85),"Starter",IF(O92>=68,"Scommessa","Low"))))) | AT92: =IF(O92>=90,1,IF(O92>=80,0.93,IF(O92>=65,0.85,0.72)))*IF(ISNUMBER(SEARCH("MERCATO",V92&"")),0.85,1)*IF(ISNUMBER(SEARCH("INFORTUN",V92&"")),0.9,1)*IF(C92="*",0.55,1) | AU92: =IFERROR(VLOOKUP(AR92,'Strategia 433'!$A$29:$B$38,2,FALSE),0.9) | AV92: =IFERROR(INDEX('Strategia 433'!$D$15:$H$24,MATCH(AR92,'Strategia 433'!$A$15:$A$24,0),MATCH(AS92,'Strategia 433'!$D$14:$H$14,0))*IF(AND(ISNUMBER(SEARCH("SUPER TOP",X92&"")),OR(AR92="Por",AR92="Pc")),1.08,1),1) | AW92: Taratura storico lega 12x500 + QUOT Fantacalcio | https://www.fantacalcio.it/quotazioni-fantacalcio | AX92: =MAX(1,ROUND(AE92*IF(AND(AR92="Pc",AS92="Top"),0.95,IF(AND(OR(AR92="A",AR92="Por",AR92="Dc"),AS92="Top"),0.90,0.85)),0))
A93: 827 | B93: Locatelli | D93: Juventus | E93: 28 | F93: C | G93: M/C | H93: 1 | I93: 6 | J93: 6 | K93: 19 | L93: 9 | O93: =MAX(0,MIN(99,AG93+AH93)) | P93: =IF(O93>=80,"Alta",IF(O93>=60,"Medio-alta",IF(O93>=40,"Media",IF(O93>=20,"Bassa","Minima")))) | Q93: =MAX(5,MIN(99,ROUND(IF(AI93>0,0.5*AI93+0.25*AJ93+0.2*O93+0.05*AK93,0.55*AJ93+0.32*O93+0.08*AK93+0.05*MIN(100,L93*4))+MIN(6,(LEN(G93)-LEN(SUBSTITUTE(G93,"/","")))*2.5)-IF(C93="*",3,0),0))) | R93: =MAX(5,MIN(99,ROUND(50+0.65*(Q93-50)+0.2*(O93-60)-0.55*(AJ93-50),0))) | S93: =IF(Q93>=90,"S",IF(Q93>=80,"A",IF(Q93>=70,"B",IF(Q93>=60,"C",IF(Q93>=48,"D","E"))))) | T93: =IF(AND(Q93>=90,O93>=62),"PUNTA FORTE",IF(AND(Q93>=80,O93>=58),"COMPRA",IF(AND(R93>=75,Q93>=62,O93>=55),"AFFARE / ATTACCA",IF(AND(Q93>=69,O93>=50),"AL GIUSTO PREZZO",IF(AND(Q93>=58,O93>=40),"JOLLY / SCOMMESSA",IF(Q93>=45,"SOLO LOW COST","EVITA")))))) | U93: 5 | V93: BASSO | W93: =LEN(G93)-LEN(SUBSTITUTE(G93,"/",""))+1 | X93: SEMITOP | Y93: =IF(AL93+AM93+AN93>=3,"Alta",IF(AL93+AM93+AN93>=2,"Medio-alta",IF(AL93+AM93+AN93=1,"Media","Bassa"))) | Z93: XI base; SOS: semitop; pluriruolo | AA93: https://www.fantacalcio.it/news/calcio-italia/06_08_2026/asta-fantacalcio-le-probabili-formazioni-della-serie-a-enilive-2026-27-495558 | https://www.fantacalcio.it/probabili-formazioni-serie-a | AB93: https://www.sosfanta.com/guida-asta-fantacalcio/fantacalcio-mantra-ecco-la-guida-allasta-2026-27-la-divisione-ruolo-per-ruolo/ | AC93: https://www.fantacalcio.it/probabili-formazioni-serie-a | https://www.fantacalcio.it/quotazioni-fantacalcio | AD93: Da valutare | AE93: =MAX(1,MIN(AV93,ROUND(AO93*1.06,0))) | AG93: 98 | AH93: 0 | AI93: 82 | AJ93: 80.1 | AK93: 50 | AL93: 1 | AM93: 1 | AN93: 1 | AO93: =MAX(1,ROUND(L93*AU93*AT93*IF(ISNUMBER(SEARCH("SUPER TOP",X93&"")),1.08,IF(AS93="Top",1.04,IF(AS93="Semitop",1,IF(AS93="Starter",0.94,IF(AS93="Scommessa",0.9,0.85))))),0)) | AP93: =IF(AR93="Non433","BASSO",IF(OR(AR93="A",AR93="Pc"),"ALTISSIMO",IF(OR(AR93="M",AR93="C",AR93="Jolly"),"ALTO",IF(OR(AR93="Dd",AR93="Ds"),"MEDIO-ALTO","MEDIO")))) | AQ93: =IF(C93="*","EVITA - FUORI LISTA",IF(AR93="Non433","NON PRIORITARIO 4-3-3",IF(AND(OR(AR93="Pc",AR93="A"),AS93="Top"),"ALL-IN CONTROLLATO",IF(AND(AE93<=8,O93>=80),"GIOIELLO / TITOLARE LOW COST",IF(OR(AS93="Top",AS93="Semitop"),"COMPRA A VALORE",IF(O93>=80,"TITOLARE DA ASPETTARE","SOLO LOW COST")))))) | AR93: =IF(G93="Por","Por",IF(ISNUMBER(SEARCH("/Pc/","/"&G93&"/")),"Pc",IF(ISNUMBER(SEARCH("/A/","/"&G93&"/")),"A",IF(ISNUMBER(SEARCH("/M/","/"&G93&"/")),"M",IF(ISNUMBER(SEARCH("/C/","/"&G93&"/")),"C",IF(ISNUMBER(SEARCH("/Dd/","/"&G93&"/")),"Dd",IF(ISNUMBER(SEARCH("/Ds/","/"&G93&"/")),"Ds",IF(ISNUMBER(SEARCH("/Dc/","/"&G93&"/")),"Dc",IF(OR(ISNUMBER(SEARCH("/E/","/"&G93&"/")),ISNUMBER(SEARCH("/W/","/"&G93&"/")),ISNUMBER(SEARCH("/T/","/"&G93&"/")),ISNUMBER(SEARCH("/B/","/"&G93&"/"))),"Jolly","Non433"))))))))) | AS93: =IF(OR(X93="SUPER TOP",X93="TOP"),"Top",IF(X93="SEMITOP","Semitop",IF(OR(ISNUMBER(SEARCH("POSSIBILI SORPRESE",X93&"")),ISNUMBER(SEARCH("SCOMMES",X93&""))),"Scommessa",IF(OR(ISNUMBER(SEARCH("FASCIA ALTA",X93&"")),ISNUMBER(SEARCH("JOLLY 1",X93&"")),O93>=85),"Starter",IF(O93>=68,"Scommessa","Low"))))) | AT93: =IF(O93>=90,1,IF(O93>=80,0.93,IF(O93>=65,0.85,0.72)))*IF(ISNUMBER(SEARCH("MERCATO",V93&"")),0.85,1)*IF(ISNUMBER(SEARCH("INFORTUN",V93&"")),0.9,1)*IF(C93="*",0.55,1) | AU93: =IFERROR(VLOOKUP(AR93,'Strategia 433'!$A$29:$B$38,2,FALSE),0.9) | AV93: =IFERROR(INDEX('Strategia 433'!$D$15:$H$24,MATCH(AR93,'Strategia 433'!$A$15:$A$24,0),MATCH(AS93,'Strategia 433'!$D$14:$H$14,0))*IF(AND(ISNUMBER(SEARCH("SUPER TOP",X93&"")),OR(AR93="Por",AR93="Pc")),1.08,1),1) | AW93: Taratura storico lega 12x500 + QUOT Fantacalcio | https://www.fantacalcio.it/quotazioni-fantacalcio | AX93: =MAX(1,ROUND(AE93*IF(AND(AR93="Pc",AS93="Top"),0.95,IF(AND(OR(AR93="A",AR93="Por",AR93="Dc"),AS93="Top"),0.90,0.85)),0))
A94: 6217 | B94: Bisseck | D94: Inter | E94: 26 | F94: D | G94: Dc | H94: 1 | I94: 7 | J94: 10 | K94: 19 | L94: 12 | O94: =MAX(0,MIN(99,AG94+AH94)) | P94: =IF(O94>=80,"Alta",IF(O94>=60,"Medio-alta",IF(O94>=40,"Media",IF(O94>=20,"Bassa","Minima")))) | Q94: =MAX(5,MIN(99,ROUND(IF(AI94>0,0.5*AI94+0.25*AJ94+0.2*O94+0.05*AK94,0.55*AJ94+0.32*O94+0.08*AK94+0.05*MIN(100,L94*4))+MIN(6,(LEN(G94)-LEN(SUBSTITUTE(G94,"/","")))*2.5)-IF(C94="*",3,0),0))) | R94: =MAX(5,MIN(99,ROUND(50+0.65*(Q94-50)+0.2*(O94-60)-0.55*(AJ94-50),0))) | S94: =IF(Q94>=90,"S",IF(Q94>=80,"A",IF(Q94>=70,"B",IF(Q94>=60,"C",IF(Q94>=48,"D","E"))))) | T94: =IF(AND(Q94>=90,O94>=62),"PUNTA FORTE",IF(AND(Q94>=80,O94>=58),"COMPRA",IF(AND(R94>=75,Q94>=62,O94>=55),"AFFARE / ATTACCA",IF(AND(Q94>=69,O94>=50),"AL GIUSTO PREZZO",IF(AND(Q94>=58,O94>=40),"JOLLY / SCOMMESSA",IF(Q94>=45,"SOLO LOW COST","EVITA")))))) | U94: 3 | V94: BALLOTTAGGIO | W94: =LEN(G94)-LEN(SUBSTITUTE(G94,"/",""))+1 | X94: SEMITOP | Y94: =IF(AL94+AM94+AN94>=3,"Alta",IF(AL94+AM94+AN94>=2,"Medio-alta",IF(AL94+AM94+AN94=1,"Media","Bassa"))) | Z94: in pole oggi; ballottaggio; SOS: sotto ai semitop | AA94: https://www.fantacalcio.it/news/calcio-italia/06_08_2026/asta-fantacalcio-le-probabili-formazioni-della-serie-a-enilive-2026-27-495558 | https://www.fantacalcio.it/probabili-formazioni-serie-a | AB94: https://www.sosfanta.com/guida-asta-fantacalcio/fantacalcio-mantra-ecco-la-guida-allasta-2026-27-la-divisione-ruolo-per-ruolo/ | AC94: https://www.fantacalcio.it/probabili-formazioni-serie-a | https://www.fantacalcio.it/quotazioni-fantacalcio | AD94: Da valutare | AE94: =MAX(1,MIN(AV94,ROUND(AO94*1.06,0))) | AG94: 58 | AH94: 0 | AI94: 75 | AJ94: 92.4 | AK94: 100 | AL94: 1 | AM94: 1 | AN94: 1 | AO94: =MAX(1,ROUND(L94*AU94*AT94*IF(ISNUMBER(SEARCH("SUPER TOP",X94&"")),1.08,IF(AS94="Top",1.04,IF(AS94="Semitop",1,IF(AS94="Starter",0.94,IF(AS94="Scommessa",0.9,0.85))))),0)) | AP94: =IF(AR94="Non433","BASSO",IF(OR(AR94="A",AR94="Pc"),"ALTISSIMO",IF(OR(AR94="M",AR94="C",AR94="Jolly"),"ALTO",IF(OR(AR94="Dd",AR94="Ds"),"MEDIO-ALTO","MEDIO")))) | AQ94: =IF(C94="*","EVITA - FUORI LISTA",IF(AR94="Non433","NON PRIORITARIO 4-3-3",IF(AND(OR(AR94="Pc",AR94="A"),AS94="Top"),"ALL-IN CONTROLLATO",IF(AND(AE94<=8,O94>=80),"GIOIELLO / TITOLARE LOW COST",IF(OR(AS94="Top",AS94="Semitop"),"COMPRA A VALORE",IF(O94>=80,"TITOLARE DA ASPETTARE","SOLO LOW COST")))))) | AR94: =IF(G94="Por","Por",IF(ISNUMBER(SEARCH("/Pc/","/"&G94&"/")),"Pc",IF(ISNUMBER(SEARCH("/A/","/"&G94&"/")),"A",IF(ISNUMBER(SEARCH("/M/","/"&G94&"/")),"M",IF(ISNUMBER(SEARCH("/C/","/"&G94&"/")),"C",IF(ISNUMBER(SEARCH("/Dd/","/"&G94&"/")),"Dd",IF(ISNUMBER(SEARCH("/Ds/","/"&G94&"/")),"Ds",IF(ISNUMBER(SEARCH("/Dc/","/"&G94&"/")),"Dc",IF(OR(ISNUMBER(SEARCH("/E/","/"&G94&"/")),ISNUMBER(SEARCH("/W/","/"&G94&"/")),ISNUMBER(SEARCH("/T/","/"&G94&"/")),ISNUMBER(SEARCH("/B/","/"&G94&"/"))),"Jolly","Non433"))))))))) | AS94: =IF(OR(X94="SUPER TOP",X94="TOP"),"Top",IF(X94="SEMITOP","Semitop",IF(OR(ISNUMBER(SEARCH("POSSIBILI SORPRESE",X94&"")),ISNUMBER(SEARCH("SCOMMES",X94&""))),"Scommessa",IF(OR(ISNUMBER(SEARCH("FASCIA ALTA",X94&"")),ISNUMBER(SEARCH("JOLLY 1",X94&"")),O94>=85),"Starter",IF(O94>=68,"Scommessa","Low"))))) | AT94: =IF(O94>=90,1,IF(O94>=80,0.93,IF(O94>=65,0.85,0.72)))*IF(ISNUMBER(SEARCH("MERCATO",V94&"")),0.85,1)*IF(ISNUMBER(SEARCH("INFORTUN",V94&"")),0.9,1)*IF(C94="*",0.55,1) | AU94: =IFERROR(VLOOKUP(AR94,'Strategia 433'!$A$29:$B$38,2,FALSE),0.9) | AV94: =IFERROR(INDEX('Strategia 433'!$D$15:$H$24,MATCH(AR94,'Strategia 433'!$A$15:$A$24,0),MATCH(AS94,'Strategia 433'!$D$14:$H$14,0))*IF(AND(ISNUMBER(SEARCH("SUPER TOP",X94&"")),OR(AR94="Por",AR94="Pc")),1.08,1),1) | AW94: Taratura storico lega 12x500 + QUOT Fantacalcio | https://www.fantacalcio.it/quotazioni-fantacalcio | AX94: =MAX(1,ROUND(AE94*IF(AND(AR94="Pc",AS94="Top"),0.95,IF(AND(OR(AR94="A",AR94="Por",AR94="Dc"),AS94="Top"),0.90,0.85)),0))
A95: 5982 | B95: Spence | D95: Inter | E95: 26 | F95: D | G95: E | H95: 0 | I95: 0 | J95: 0 | K95: 19 | L95: 11 | O95: =MAX(0,MIN(99,AG95+AH95)) | P95: =IF(O95>=80,"Alta",IF(O95>=60,"Medio-alta",IF(O95>=40,"Media",IF(O95>=20,"Bassa","Minima")))) | Q95: =MAX(5,MIN(99,ROUND(IF(AI95>0,0.5*AI95+0.25*AJ95+0.2*O95+0.05*AK95,0.55*AJ95+0.32*O95+0.08*AK95+0.05*MIN(100,L95*4))+MIN(6,(LEN(G95)-LEN(SUBSTITUTE(G95,"/","")))*2.5)-IF(C95="*",3,0),0))) | R95: =MAX(5,MIN(99,ROUND(50+0.65*(Q95-50)+0.2*(O95-60)-0.55*(AJ95-50),0))) | S95: =IF(Q95>=90,"S",IF(Q95>=80,"A",IF(Q95>=70,"B",IF(Q95>=60,"C",IF(Q95>=48,"D","E"))))) | T95: =IF(AND(Q95>=90,O95>=62),"PUNTA FORTE",IF(AND(Q95>=80,O95>=58),"COMPRA",IF(AND(R95>=75,Q95>=62,O95>=55),"AFFARE / ATTACCA",IF(AND(Q95>=69,O95>=50),"AL GIUSTO PREZZO",IF(AND(Q95>=58,O95>=40),"JOLLY / SCOMMESSA",IF(Q95>=45,"SOLO LOW COST","EVITA")))))) | U95: 2 | V95: MEDIO | W95: =LEN(G95)-LEN(SUBSTITUTE(G95,"/",""))+1 | X95: Non classificato | Y95: =IF(AL95+AM95+AN95>=3,"Alta",IF(AL95+AM95+AN95>=2,"Medio-alta",IF(AL95+AM95+AN95=1,"Media","Bassa"))) | Z95: Profilo da valutare soprattutto in base a prezzo e copertura ruolo. | AA95: https://www.fantacalcio.it/news/calcio-italia/06_08_2026/asta-fantacalcio-le-probabili-formazioni-della-serie-a-enilive-2026-27-495558 | https://www.fantacalcio.it/probabili-formazioni-serie-a | AB95: https://www.sosfanta.com/guida-asta-fantacalcio/fantacalcio-mantra-ecco-la-guida-allasta-2026-27-la-divisione-ruolo-per-ruolo/ | AC95: https://www.fantacalcio.it/probabili-formazioni-serie-a | https://www.fantacalcio.it/quotazioni-fantacalcio | AD95: Da valutare | AE95: =MAX(1,MIN(AV95,ROUND(AO95*1.06,0))) | AG95: 49 | AH95: 0 | AI95: 0 | AJ95: 92.4 | AK95: 50 | AL95: 0 | AM95: 0 | AN95: 0 | AO95: =MAX(1,ROUND(L95*AU95*AT95*IF(ISNUMBER(SEARCH("SUPER TOP",X95&"")),1.08,IF(AS95="Top",1.04,IF(AS95="Semitop",1,IF(AS95="Starter",0.94,IF(AS95="Scommessa",0.9,0.85))))),0)) | AP95: =IF(AR95="Non433","BASSO",IF(OR(AR95="A",AR95="Pc"),"ALTISSIMO",IF(OR(AR95="M",AR95="C",AR95="Jolly"),"ALTO",IF(OR(AR95="Dd",AR95="Ds"),"MEDIO-ALTO","MEDIO")))) | AQ95: =IF(C95="*","EVITA - FUORI LISTA",IF(AR95="Non433","NON PRIORITARIO 4-3-3",IF(AND(OR(AR95="Pc",AR95="A"),AS95="Top"),"ALL-IN CONTROLLATO",IF(AND(AE95<=8,O95>=80),"GIOIELLO / TITOLARE LOW COST",IF(OR(AS95="Top",AS95="Semitop"),"COMPRA A VALORE",IF(O95>=80,"TITOLARE DA ASPETTARE","SOLO LOW COST")))))) | AR95: =IF(G95="Por","Por",IF(ISNUMBER(SEARCH("/Pc/","/"&G95&"/")),"Pc",IF(ISNUMBER(SEARCH("/A/","/"&G95&"/")),"A",IF(ISNUMBER(SEARCH("/M/","/"&G95&"/")),"M",IF(ISNUMBER(SEARCH("/C/","/"&G95&"/")),"C",IF(ISNUMBER(SEARCH("/Dd/","/"&G95&"/")),"Dd",IF(ISNUMBER(SEARCH("/Ds/","/"&G95&"/")),"Ds",IF(ISNUMBER(SEARCH("/Dc/","/"&G95&"/")),"Dc",IF(OR(ISNUMBER(SEARCH("/E/","/"&G95&"/")),ISNUMBER(SEARCH("/W/","/"&G95&"/")),ISNUMBER(SEARCH("/T/","/"&G95&"/")),ISNUMBER(SEARCH("/B/","/"&G95&"/"))),"Jolly","Non433"))))))))) | AS95: =IF(OR(X95="SUPER TOP",X95="TOP"),"Top",IF(X95="SEMITOP","Semitop",IF(OR(ISNUMBER(SEARCH("POSSIBILI SORPRESE",X95&"")),ISNUMBER(SEARCH("SCOMMES",X95&""))),"Scommessa",IF(OR(ISNUMBER(SEARCH("FASCIA ALTA",X95&"")),ISNUMBER(SEARCH("JOLLY 1",X95&"")),O95>=85),"Starter",IF(O95>=68,"Scommessa","Low"))))) | AT95: =IF(O95>=90,1,IF(O95>=80,0.93,IF(O95>=65,0.85,0.72)))*IF(ISNUMBER(SEARCH("MERCATO",V95&"")),0.85,1)*IF(ISNUMBER(SEARCH("INFORTUN",V95&"")),0.9,1)*IF(C95="*",0.55,1) | AU95: =IFERROR(VLOOKUP(AR95,'Strategia 433'!$A$29:$B$38,2,FALSE),0.9) | AV95: =IFERROR(INDEX('Strategia 433'!$D$15:$H$24,MATCH(AR95,'Strategia 433'!$A$15:$A$24,0),MATCH(AS95,'Strategia 433'!$D$14:$H$14,0))*IF(AND(ISNUMBER(SEARCH("SUPER TOP",X95&"")),OR(AR95="Por",AR95="Pc")),1.08,1),1) | AW95: Taratura storico lega 12x500 + QUOT Fantacalcio | https://www.fantacalcio.it/quotazioni-fantacalcio | AX95: =MAX(1,ROUND(AE95*IF(AND(AR95="Pc",AS95="Top"),0.95,IF(AND(OR(AR95="A",AR95="Por",AR95="Dc"),AS95="Top"),0.90,0.85)),0))
... A145: 6531 | B145: Jimenez A. | D145: Fiorentina | E145: 21 | F145: D | G145: Dd/Ds/E | H145: 1 | I145: 5.5 | J145: 5.5 | K145: 13 | L145: 9 | O145: =MAX(0,MIN(99,AG145+AH145)) | P145: =IF(O145>=80,"Alta",IF(O145>=60,"Medio-alta",IF(O145>=40,"Media",IF(O145>=20,"Bassa","Minima")))) | Q145: =MAX(5,MIN(99,ROUND(IF(AI145>0,0.5*AI145+0.25*AJ145+0.2*O145+0.05*AK145,0.55*AJ145+0.32*O145+0.08*AK145+0.05*MIN(100,L145*4))+MIN(6,(LEN(G145)-LEN(SUBSTITUTE(G145,"/","")))*2.5)-IF(C145="*",3,0),0))) | R145: =MAX(5,MIN(99,ROUND(50+0.65*(Q145-50)+0.2*(O145-60)-0.55*(AJ145-50),0))) | S145: =IF(Q145>=90,"S",IF(Q145>=80,"A",IF(Q145>=70,"B",IF(Q145>=60,"C",IF(Q145>=48,"D","E"))))) | T145: =IF(AND(Q145>=90,O145>=62),"PUNTA FORTE",IF(AND(Q145>=80,O145>=58),"COMPRA",IF(AND(R145>=75,Q145>=62,O145>=55),"AFFARE / ATTACCA",IF(AND(Q145>=69,O145>=50),"AL GIUSTO PREZZO",IF(AND(Q145>=58,O145>=40),"JOLLY / SCOMMESSA",IF(Q145>=45,"SOLO LOW COST","EVITA")))))) | U145: 4 | V145: BALLOTTAGGIO | W145: =LEN(G145)-LEN(SUBSTITUTE(G145,"/",""))+1 | X145: TOP | Y145: =IF(AL145+AM145+AN145>=3,"Alta",IF(AL145+AM145+AN145>=2,"Medio-alta",IF(AL145+AM145+AN145=1,"Media","Bassa"))) | Z145: XI base; ballottaggio; SOS: semitop; pluriruolo | AA145: https://www.fantacalcio.it/news/calcio-italia/06_08_2026/asta-fantacalcio-le-probabili-formazioni-della-serie-a-enilive-2026-27-495558 | https://www.fantacalcio.it/probabili-formazioni-serie-a | AB145: https://www.sosfanta.com/guida-asta-fantacalcio/fantacalcio-mantra-ecco-la-guida-allasta-2026-27-la-divisione-ruolo-per-ruolo/ | AC145: https://www.fantacalcio.it/probabili-formazioni-serie-a | https://www.fantacalcio.it/quotazioni-fantacalcio | AD145: Da valutare | AE145: =MAX(1,MIN(AV145,ROUND(AO145*1.06,0))) | AG145: 75 | AH145: 0 | AI145: 82 | AJ145: 86 | AK145: 41 | AL145: 1 | AM145: 1 | AN145: 0 | AO145: =MAX(1,ROUND(L145*AU145*AT145*IF(ISNUMBER(SEARCH("SUPER TOP",X145&"")),1.08,IF(AS145="Top",1.04,IF(AS145="Semitop",1,IF(AS145="Starter",0.94,IF(AS145="Scommessa",0.9,0.85))))),0)) | AP145: =IF(AR145="Non433","BASSO",IF(OR(AR145="A",AR145="Pc"),"ALTISSIMO",IF(OR(AR145="M",AR145="C",AR145="Jolly"),"ALTO",IF(OR(AR145="Dd",AR145="Ds"),"MEDIO-ALTO","MEDIO")))) | AQ145: =IF(C145="*","EVITA - FUORI LISTA",IF(AR145="Non433","NON PRIORITARIO 4-3-3",IF(AND(OR(AR145="Pc",AR145="A"),AS145="Top"),"ALL-IN CONTROLLATO",IF(AND(AE145<=8,O145>=80),"GIOIELLO / TITOLARE LOW COST",IF(OR(AS145="Top",AS145="Semitop"),"COMPRA A VALORE",IF(O145>=80,"TITOLARE DA ASPETTARE","SOLO LOW COST")))))) | AR145: =IF(G145="Por","Por",IF(ISNUMBER(SEARCH("/Pc/","/"&G145&"/")),"Pc",IF(ISNUMBER(SEARCH("/A/","/"&G145&"/")),"A",IF(ISNUMBER(SEARCH("/M/","/"&G145&"/")),"M",IF(ISNUMBER(SEARCH("/C/","/"&G145&"/")),"C",IF(ISNUMBER(SEARCH("/Dd/","/"&G145&"/")),"Dd",IF(ISNUMBER(SEARCH("/Ds/","/"&G145&"/")),"Ds",IF(ISNUMBER(SEARCH("/Dc/","/"&G145&"/")),"Dc",IF(OR(ISNUMBER(SEARCH("/E/","/"&G145&"/")),ISNUMBER(SEARCH("/W/","/"&G145&"/")),ISNUMBER(SEARCH("/T/","/"&G145&"/")),ISNUMBER(SEARCH("/B/","/"&G145&"/"))),"Jolly","Non433"))))))))) | AS145: =IF(OR(X145="SUPER TOP",X145="TOP"),"Top",IF(X145="SEMITOP","Semitop",IF(OR(ISNUMBER(SEARCH("POSSIBILI SORPRESE",X145&"")),ISNUMBER(SEARCH("SCOMMES",X145&""))),"Scommessa",IF(OR(ISNUMBER(SEARCH("FASCIA ALTA",X145&"")),ISNUMBER(SEARCH("JOLLY 1",X145&"")),O145>=85),"Starter",IF(O145>=68,"Scommessa","Low"))))) | AT145: =IF(O145>=90,1,IF(O145>=80,0.93,IF(O145>=65,0.85,0.72)))*IF(ISNUMBER(SEARCH("MERCATO",V145&"")),0.85,1)*IF(ISNUMBER(SEARCH("INFORTUN",V145&"")),0.9,1)*IF(C145="*",0.55,1) | AU145: =IFERROR(VLOOKUP(AR145,'Strategia 433'!$A$29:$B$38,2,FALSE),0.9) | AV145: =IFERROR(INDEX('Strategia 433'!$D$15:$H$24,MATCH(AR145,'Strategia 433'!$A$15:$A$24,0),MATCH(AS145,'Strategia 433'!$D$14:$H$14,0))*IF(AND(ISNUMBER(SEARCH("SUPER TOP",X145&"")),OR(AR145="Por",AR145="Pc")),1.08,1),1) | AW145: Taratura storico lega 12x500 + QUOT Fantacalcio | https://www.fantacalcio.it/quotazioni-fantacalcio | AX145: =MAX(1,ROUND(AE145*IF(AND(AR145="Pc",AS145="Top"),0.95,IF(AND(OR(AR145="A",AR145="Por",AR145="Dc"),AS145="Top"),0.90,0.85)),0))
A146: 5427 | B146: Gutierrez | C146: * | D146: Napoli | E146: 25 | F146: D | G146: Ds/E | H146: 0 | I146: 0 | J146: 0 | K146: 13 | L146: 8 | O146: =MAX(0,MIN(99,AG146+AH146)) | P146: =IF(O146>=80,"Alta",IF(O146>=60,"Medio-alta",IF(O146>=40,"Media",IF(O146>=20,"Bassa","Minima")))) | Q146: =MAX(5,MIN(99,ROUND(IF(AI146>0,0.5*AI146+0.25*AJ146+0.2*O146+0.05*AK146,0.55*AJ146+0.32*O146+0.08*AK146+0.05*MIN(100,L146*4))+MIN(6,(LEN(G146)-LEN(SUBSTITUTE(G146,"/","")))*2.5)-IF(C146="*",3,0),0))) | R146: =MAX(5,MIN(99,ROUND(50+0.65*(Q146-50)+0.2*(O146-60)-0.55*(AJ146-50),0))) | S146: =IF(Q146>=90,"S",IF(Q146>=80,"A",IF(Q146>=70,"B",IF(Q146>=60,"C",IF(Q146>=48,"D","E"))))) | T146: =IF(AND(Q146>=90,O146>=62),"PUNTA FORTE",IF(AND(Q146>=80,O146>=58),"COMPRA",IF(AND(R146>=75,Q146>=62,O146>=55),"AFFARE / ATTACCA",IF(AND(Q146>=69,O146>=50),"AL GIUSTO PREZZO",IF(AND(Q146>=58,O146>=40),"JOLLY / SCOMMESSA",IF(Q146>=45,"SOLO LOW COST","EVITA")))))) | U146: 2 | V146: FUORI LISTA * | W146: =LEN(G146)-LEN(SUBSTITUTE(G146,"/",""))+1 | X146: Non classificato | Y146: =IF(AL146+AM146+AN146>=3,"Alta",IF(AL146+AM146+AN146>=2,"Medio-alta",IF(AL146+AM146+AN146=1,"Media","Bassa"))) | Z146: pluriruolo; flag fuori lista nel file: verifica prima di rilanciare | AA146: https://www.fantacalcio.it/news/calcio-italia/06_08_2026/asta-fantacalcio-le-probabili-formazioni-della-serie-a-enilive-2026-27-495558 | https://www.fantacalcio.it/probabili-formazioni-serie-a | AB146: https://www.sosfanta.com/guida-asta-fantacalcio/fantacalcio-mantra-ecco-la-guida-allasta-2026-27-la-divisione-ruolo-per-ruolo/ | AC146: https://www.fantacalcio.it/probabili-formazioni-serie-a | https://www.fantacalcio.it/quotazioni-fantacalcio | AD146: Da valutare | AE146: =MAX(1,MIN(AV146,ROUND(AO146*1.06,0))) | AG146: 39 | AH146: 0 | AI146: 0 | AJ146: 86 | AK146: 50 | AL146: 0 | AM146: 0 | AN146: 0 | AO146: =MAX(1,ROUND(L146*AU146*AT146*IF(ISNUMBER(SEARCH("SUPER TOP",X146&"")),1.08,IF(AS146="Top",1.04,IF(AS146="Semitop",1,IF(AS146="Starter",0.94,IF(AS146="Scommessa",0.9,0.85))))),0)) | AP146: =IF(AR146="Non433","BASSO",IF(OR(AR146="A",AR146="Pc"),"ALTISSIMO",IF(OR(AR146="M",AR146="C",AR146="Jolly"),"ALTO",IF(OR(AR146="Dd",AR146="Ds"),"MEDIO-ALTO","MEDIO")))) | AQ146: =IF(C146="*","EVITA - FUORI LISTA",IF(AR146="Non433","NON PRIORITARIO 4-3-3",IF(AND(OR(AR146="Pc",AR146="A"),AS146="Top"),"ALL-IN CONTROLLATO",IF(AND(AE146<=8,O146>=80),"GIOIELLO / TITOLARE LOW COST",IF(OR(AS146="Top",AS146="Semitop"),"COMPRA A VALORE",IF(O146>=80,"TITOLARE DA ASPETTARE","SOLO LOW COST")))))) | AR146: =IF(G146="Por","Por",IF(ISNUMBER(SEARCH("/Pc/","/"&G146&"/")),"Pc",IF(ISNUMBER(SEARCH("/A/","/"&G146&"/")),"A",IF(ISNUMBER(SEARCH("/M/","/"&G146&"/")),"M",IF(ISNUMBER(SEARCH("/C/","/"&G146&"/")),"C",IF(ISNUMBER(SEARCH("/Dd/","/"&G146&"/")),"Dd",IF(ISNUMBER(SEARCH("/Ds/","/"&G146&"/")),"Ds",IF(ISNUMBER(SEARCH("/Dc/","/"&G146&"/")),"Dc",IF(OR(ISNUMBER(SEARCH("/E/","/"&G146&"/")),ISNUMBER(SEARCH("/W/","/"&G146&"/")),ISNUMBER(SEARCH("/T/","/"&G146&"/")),ISNUMBER(SEARCH("/B/","/"&G146&"/"))),"Jolly","Non433"))))))))) | AS146: =IF(OR(X146="SUPER TOP",X146="TOP"),"Top",IF(X146="SEMITOP","Semitop",IF(OR(ISNUMBER(SEARCH("POSSIBILI SORPRESE",X146&"")),ISNUMBER(SEARCH("SCOMMES",X146&""))),"Scommessa",IF(OR(ISNUMBER(SEARCH("FASCIA ALTA",X146&"")),ISNUMBER(SEARCH("JOLLY 1",X146&"")),O146>=85),"Starter",IF(O146>=68,"Scommessa","Low"))))) | AT146: =IF(O146>=90,1,IF(O146>=80,0.93,IF(O146>=65,0.85,0.72)))*IF(ISNUMBER(SEARCH("MERCATO",V146&"")),0.85,1)*IF(ISNUMBER(SEARCH("INFORTUN",V146&"")),0.9,1)*IF(C146="*",0.55,1) | AU146: =IFERROR(VLOOKUP(AR146,'Strategia 433'!$A$29:$B$38,2,FALSE),0.9) | AV146: =IFERROR(INDEX('Strategia 433'!$D$15:$H$24,MATCH(AR146,'Strategia 433'!$A$15:$A$24,0),MATCH(AS146,'Strategia 433'!$D$14:$H$14,0))*IF(AND(ISNUMBER(SEARCH("SUPER TOP",X146&"")),OR(AR146="Por",AR146="Pc")),1.08,1),1) | AW146: Taratura storico lega 12x500 + QUOT Fantacalcio | https://www.fantacalcio.it/quotazioni-fantacalcio | AX146: =MAX(1,ROUND(AE146*IF(AND(AR146="Pc",AS146="Top"),0.95,IF(AND(OR(AR146="A",AR146="Por",AR146="Dc"),AS146="Top"),0.90,0.85)),0))
A147: 4807 | B147: Hermoso | D147: Roma | E147: 31 | F147: D | G147: Dc | H147: 1 | I147: 6.5 | J147: 6 | K147: 13 | L147: 10 | O147: =MAX(0,MIN(99,AG147+AH147)) | P147: =IF(O147>=80,"Alta",IF(O147>=60,"Medio-alta",IF(O147>=40,"Media",IF(O147>=20,"Bassa","Minima")))) | Q147: =MAX(5,MIN(99,ROUND(IF(AI147>0,0.5*AI147+0.25*AJ147+0.2*O147+0.05*AK147,0.55*AJ147+0.32*O147+0.08*AK147+0.05*MIN(100,L147*4))+MIN(6,(LEN(G147)-LEN(SUBSTITUTE(G147,"/","")))*2.5)-IF(C147="*",3,0),0))) | R147: =MAX(5,MIN(99,ROUND(50+0.65*(Q147-50)+0.2*(O147-60)-0.55*(AJ147-50),0))) | S147: =IF(Q147>=90,"S",IF(Q147>=80,"A",IF(Q147>=70,"B",IF(Q147>=60,"C",IF(Q147>=48,"D","E"))))) | T147: =IF(AND(Q147>=90,O147>=62),"PUNTA FORTE",IF(AND(Q147>=80,O147>=58),"COMPRA",IF(AND(R147>=75,Q147>=62,O147>=55),"AFFARE / ATTACCA",IF(AND(Q147>=69,O147>=50),"AL GIUSTO PREZZO",IF(AND(Q147>=58,O147>=40),"JOLLY / SCOMMESSA",IF(Q147>=45,"SOLO LOW COST","EVITA")))))) | U147: 3 | V147: BALLOTTAGGIO | W147: =LEN(G147)-LEN(SUBSTITUTE(G147,"/",""))+1 | X147: JOLLY 1ª FASCIA | Y147: =IF(AL147+AM147+AN147>=3,"Alta",IF(AL147+AM147+AN147>=2,"Medio-alta",IF(AL147+AM147+AN147=1,"Media","Bassa"))) | Z147: XI base; ballottaggio; SOS: jolly 1ª fascia | AA147: https://www.fantacalcio.it/news/calcio-italia/06_08_2026/asta-fantacalcio-le-probabili-formazioni-della-serie-a-enilive-2026-27-495558 | https://www.fantacalcio.it/probabili-formazioni-serie-a | AB147: https://www.sosfanta.com/guida-asta-fantacalcio/fantacalcio-mantra-ecco-la-guida-allasta-2026-27-la-divisione-ruolo-per-ruolo/ | AC147: https://www.fantacalcio.it/probabili-formazioni-serie-a | https://www.fantacalcio.it/quotazioni-fantacalcio | AD147: Da valutare | AE147: =MAX(1,MIN(AV147,ROUND(AO147*1.06,0))) | AG147: 82 | AH147: 0 | AI147: 64 | AJ147: 86 | AK147: 50 | AL147: 1 | AM147: 1 | AN147: 1 | AO147: =MAX(1,ROUND(L147*AU147*AT147*IF(ISNUMBER(SEARCH("SUPER TOP",X147&"")),1.08,IF(AS147="Top",1.04,IF(AS147="Semitop",1,IF(AS147="Starter",0.94,IF(AS147="Scommessa",0.9,0.85))))),0)) | AP147: =IF(AR147="Non433","BASSO",IF(OR(AR147="A",AR147="Pc"),"ALTISSIMO",IF(OR(AR147="M",AR147="C",AR147="Jolly"),"ALTO",IF(OR(AR147="Dd",AR147="Ds"),"MEDIO-ALTO","MEDIO")))) | AQ147: =IF(C147="*","EVITA - FUORI LISTA",IF(AR147="Non433","NON PRIORITARIO 4-3-3",IF(AND(OR(AR147="Pc",AR147="A"),AS147="Top"),"ALL-IN CONTROLLATO",IF(AND(AE147<=8,O147>=80),"GIOIELLO / TITOLARE LOW COST",IF(OR(AS147="Top",AS147="Semitop"),"COMPRA A VALORE",IF(O147>=80,"TITOLARE DA ASPETTARE","SOLO LOW COST")))))) | AR147: =IF(G147="Por","Por",IF(ISNUMBER(SEARCH("/Pc/","/"&G147&"/")),"Pc",IF(ISNUMBER(SEARCH("/A/","/"&G147&"/")),"A",IF(ISNUMBER(SEARCH("/M/","/"&G147&"/")),"M",IF(ISNUMBER(SEARCH("/C/","/"&G147&"/")),"C",IF(ISNUMBER(SEARCH("/Dd/","/"&G147&"/")),"Dd",IF(ISNUMBER(SEARCH("/Ds/","/"&G147&"/")),"Ds",IF(ISNUMBER(SEARCH("/Dc/","/"&G147&"/")),"Dc",IF(OR(ISNUMBER(SEARCH("/E/","/"&G147&"/")),ISNUMBER(SEARCH("/W/","/"&G147&"/")),ISNUMBER(SEARCH("/T/","/"&G147&"/")),ISNUMBER(SEARCH("/B/","/"&G147&"/"))),"Jolly","Non433"))))))))) | AS147: =IF(OR(X147="SUPER TOP",X147="TOP"),"Top",IF(X147="SEMITOP","Semitop",IF(OR(ISNUMBER(SEARCH("POSSIBILI SORPRESE",X147&"")),ISNUMBER(SEARCH("SCOMMES",X147&""))),"Scommessa",IF(OR(ISNUMBER(SEARCH("FASCIA ALTA",X147&"")),ISNUMBER(SEARCH("JOLLY 1",X147&"")),O147>=85),"Starter",IF(O147>=68,"Scommessa","Low"))))) | AT147: =IF(O147>=90,1,IF(O147>=80,0.93,IF(O147>=65,0.85,0.72)))*IF(ISNUMBER(SEARCH("MERCATO",V147&"")),0.85,1)*IF(ISNUMBER(SEARCH("INFORTUN",V147&"")),0.9,1)*IF(C147="*",0.55,1) | AU147: =IFERROR(VLOOKUP(AR147,'Strategia 433'!$A$29:$B$38,2,FALSE),0.9) | AV147: =IFERROR(INDEX('Strategia 433'!$D$15:$H$24,MATCH(AR147,'Strategia 433'!$A$15:$A$24,0),MATCH(AS147,'Strategia 433'!$D$14:$H$14,0))*IF(AND(ISNUMBER(SEARCH("SUPER TOP",X147&"")),OR(AR147="Por",AR147="Pc")),1.08,1),1) | AW147: Taratura storico lega 12x500 + QUOT Fantacalcio | https://www.fantacalcio.it/quotazioni-fantacalcio | AX147: =MAX(1,ROUND(AE147*IF(AND(AR147="Pc",AS147="Top"),0.95,IF(AND(OR(AR147="A",AR147="Por",AR147="Dc"),AS147="Top"),0.90,0.85)),0))
A148: 1852 | B148: Spinazzola | D148: Napoli | E148: 33 | F148: D | G148: Ds/E | H148: 1 | I148: 5.5 | J148: 5.5 | K148: 13 | L148: 8 | O148: =MAX(0,MIN(99,AG148+AH148)) | P148: =IF(O148>=80,"Alta",IF(O148>=60,"Medio-alta",IF(O148>=40,"Media",IF(O148>=20,"Bassa","Minima")))) | Q148: =MAX(5,MIN(99,ROUND(IF(AI148>0,0.5*AI148+0.25*AJ148+0.2*O148+0.05*AK148,0.55*AJ148+0.32*O148+0.08*AK148+0.05*MIN(100,L148*4))+MIN(6,(LEN(G148)-LEN(SUBSTITUTE(G148,"/","")))*2.5)-IF(C148="*",3,0),0))) | R148: =MAX(5,MIN(99,ROUND(50+0.65*(Q148-50)+0.2*(O148-60)-0.55*(AJ148-50),0))) | S148: =IF(Q148>=90,"S",IF(Q148>=80,"A",IF(Q148>=70,"B",IF(Q148>=60,"C",IF(Q148>=48,"D","E"))))) | T148: =IF(AND(Q148>=90,O148>=62),"PUNTA FORTE",IF(AND(Q148>=80,O148>=58),"COMPRA",IF(AND(R148>=75,Q148>=62,O148>=55),"AFFARE / ATTACCA",IF(AND(Q148>=69,O148>=50),"AL GIUSTO PREZZO",IF(AND(Q148>=58,O148>=40),"JOLLY / SCOMMESSA",IF(Q148>=45,"SOLO LOW COST","EVITA")))))) | U148: 4 | V148: BALLOTTAGGIO | W148: =LEN(G148)-LEN(SUBSTITUTE(G148,"/",""))+1 | X148: TOP | Y148: =IF(AL148+AM148+AN148>=3,"Alta",IF(AL148+AM148+AN148>=2,"Medio-alta",IF(AL148+AM148+AN148=1,"Media","Bassa"))) | Z148: XI base; ballottaggio; SOS: top; pluriruolo | AA148: https://www.fantacalcio.it/news/calcio-italia/06_08_2026/asta-fantacalcio-le-probabili-formazioni-della-serie-a-enilive-2026-27-495558 | https://www.fantacalcio.it/probabili-formazioni-serie-a | AB148: https://www.sosfanta.com/guida-asta-fantacalcio/fantacalcio-mantra-ecco-la-guida-allasta-2026-27-la-divisione-ruolo-per-ruolo/ | AC148: https://www.fantacalcio.it/probabili-formazioni-serie-a | https://www.fantacalcio.it/quotazioni-fantacalcio | AD148: Da valutare | AE148: =MAX(1,MIN(AV148,ROUND(AO148*1.06,0))) | AG148: 82 | AH148: 0 | AI148: 90 | AJ148: 86 | AK148: 41 | AL148: 1 | AM148: 1 | AN148: 1 | AO148: =MAX(1,ROUND(L148*AU148*AT148*IF(ISNUMBER(SEARCH("SUPER TOP",X148&"")),1.08,IF(AS148="Top",1.04,IF(AS148="Semitop",1,IF(AS148="Starter",0.94,IF(AS148="Scommessa",0.9,0.85))))),0)) | AP148: =IF(AR148="Non433","BASSO",IF(OR(AR148="A",AR148="Pc"),"ALTISSIMO",IF(OR(AR148="M",AR148="C",AR148="Jolly"),"ALTO",IF(OR(AR148="Dd",AR148="Ds"),"MEDIO-ALTO","MEDIO")))) | AQ148: =IF(C148="*","EVITA - FUORI LISTA",IF(AR148="Non433","NON PRIORITARIO 4-3-3",IF(AND(OR(AR148="Pc",AR148="A"),AS148="Top"),"ALL-IN CONTROLLATO",IF(AND(AE148<=8,O148>=80),"GIOIELLO / TITOLARE LOW COST",IF(OR(AS148="Top",AS148="Semitop"),"COMPRA A VALORE",IF(O148>=80,"TITOLARE DA ASPETTARE","SOLO LOW COST")))))) | AR148: =IF(G148="Por","Por",IF(ISNUMBER(SEARCH("/Pc/","/"&G148&"/")),"Pc",IF(ISNUMBER(SEARCH("/A/","/"&G148&"/")),"A",IF(ISNUMBER(SEARCH("/M/","/"&G148&"/")),"M",IF(ISNUMBER(SEARCH("/C/","/"&G148&"/")),"C",IF(ISNUMBER(SEARCH("/Dd/","/"&G148&"/")),"Dd",IF(ISNUMBER(SEARCH("/Ds/","/"&G148&"/")),"Ds",IF(ISNUMBER(SEARCH("/Dc/","/"&G148&"/")),"Dc",IF(OR(ISNUMBER(SEARCH("/E/","/"&G148&"/")),ISNUMBER(SEARCH("/W/","/"&G148&"/")),ISNUMBER(SEARCH("/T/","/"&G148&"/")),ISNUMBER(SEARCH("/B/","/"&G148&"/"))),"Jolly","Non433"))))))))) | AS148: =IF(OR(X148="SUPER TOP",X148="TOP"),"Top",IF(X148="SEMITOP","Semitop",IF(OR(ISNUMBER(SEARCH("POSSIBILI SORPRESE",X148&"")),ISNUMBER(SEARCH("SCOMMES",X148&""))),"Scommessa",IF(OR(ISNUMBER(SEARCH("FASCIA ALTA",X148&"")),ISNUMBER(SEARCH("JOLLY 1",X148&"")),O148>=85),"Starter",IF(O148>=68,"Scommessa","Low"))))) | AT148: =IF(O148>=90,1,IF(O148>=80,0.93,IF(O148>=65,0.85,0.72)))*IF(ISNUMBER(SEARCH("MERCATO",V148&"")),0.85,1)*IF(ISNUMBER(SEARCH("INFORTUN",V148&"")),0.9,1)*IF(C148="*",0.55,1) | AU148: =IFERROR(VLOOKUP(AR148,'Strategia 433'!$A$29:$B$38,2,FALSE),0.9) | AV148: =IFERROR(INDEX('Strategia 433'!$D$15:$H$24,MATCH(AR148,'Strategia 433'!$A$15:$A$24,0),MATCH(AS148,'Strategia 433'!$D$14:$H$14,0))*IF(AND(ISNUMBER(SEARCH("SUPER TOP",X148&"")),OR(AR148="Por",AR148="Pc")),1.08,1),1) | AW148: Taratura storico lega 12x500 + QUOT Fantacalcio | https://www.fantacalcio.it/quotazioni-fantacalcio | AX148: =MAX(1,ROUND(AE148*IF(AND(AR148="Pc",AS148="Top"),0.95,IF(AND(OR(AR148="A",AR148="Por",AR148="Dc"),AS148="Top"),0.90,0.85)),0))
